Workbook

Sheet NRI 2025
A1: Economy | G1: NRIScore | I1: NRIRank | J1: 1.score | K1: 2.score | L1: 3.score | M1: 4.score | N1: 1.rank | O1: 2.rank | P1: 3.rank | Q1: 4.rank | R1: 1.1.score | S1: 1.2.score | T1: 1.3.score | U1: 2.1.score | V1: 2.2.score | W1: 2.3.score | X1: 3.1.score | Y1: 3.2.score | Z1: 3.3.score | AA1: 4.1.score | AB1: 4.2.score | AC1: 4.3.score | AD1: 1.1.rank | AE1: 1.2.rank | AF1: 1.3.rank | AG1: 2.1.rank | AH1: 2.2.rank | AI1: 2.3.rank | AJ1: 3.1.rank | AK1: 3.2.rank | AL1: 3.3.rank | AM1: 4.1.rank | AN1: 4.2.rank | AO1: 4.3.rank | AP1: 1.1.1score | AQ1: 1.1.2score | AR1: 1.1.3score | AS1: 1.1.4score | AT1: 1.1.5score | AU1: 1.1.6score | AV1: 1.2.1score | AW1: 1.2.2score | AX1: 1.2.3score | AY1: 1.2.4score | AZ1: 1.3.1score | BA1: 1.3.2score | BB1: 1.3.3score | BC1: 1.3.4score | BD1: 2.1.1score | BE1: 2.1.2score | BF1: 2.1.3score | BG1: 2.1.4score | BH1: 2.1.5score | BI1: 2.2.1score | BJ1: 2.2.2score | BK1: 2.2.3score | BL1: 2.2.4score | BM1: 2.3.1score | BN1: 2.3.2score | BO1: 2.3.3score | BP1: 2.3.4score | BQ1: 3.1.1score | BR1: 3.1.2score | BS1: 3.1.3score | BT1: 3.1.4score | BU1: 3.2.1score | BV1: 3.2.2score | BW1: 3.2.3score | BX1: 3.2.4score | BY1: 3.2.5score | BZ1: 3.3.1score | CA1: 3.3.2score | CB1: 3.3.3score | CC1: 3.3.4score | CD1: 4.1.1score | CE1: 4.1.2score | CF1: 4.1.3score | CG1: 4.1.4score | CH1: 4.2.1score | CI1: 4.2.2score | CJ1: 4.2.3score | CK1: 4.2.4score | CL1: 4.3.1score | CM1: 4.3.2score | CN1: 4.3.3score | CO1: 4.3.4score | CP1: 4.3.5score | CQ1: 1.1.1rank | CR1: 1.1.2rank | CS1: 1.1.3rank | CT1: 1.1.4rank | CU1: 1.1.5rank | CV1: 1.1.6rank | CW1: 1.2.1rank | CX1: 1.2.2rank | CY1: 1.2.3rank | CZ1: 1.2.4rank | DA1: 1.3.1rank | DB1: 1.3.2rank | DC1: 1.3.3rank | DD1: 1.3.4rank | DE1: 2.1.1rank | DF1: 2.1.2rank | DG1: 2.1.3rank | DH1: 2.1.4rank | DI1: 2.1.5rank | DJ1: 2.2.1rank | DK1: 2.2.2rank | DL1: 2.2.3rank | DM1: 2.2.4rank | DN1: 2.3.1rank | DO1: 2.3.2rank | DP1: 2.3.3rank | DQ1: 2.3.4rank | DR1: 3.1.1rank | DS1: 3.1.2rank | DT1: 3.1.3rank | DU1: 3.1.4rank | DV1: 3.2.1rank | DW1: 3.2.2rank | DX1: 3.2.3rank | DY1: 3.2.4rank | DZ1: 3.2.5rank | EA1: 3.3.1rank | EB1: 3.3.2rank | EC1: 3.3.3rank | ED1: 3.3.4rank | EE1: 4.1.1rank | EF1: 4.1.2rank | EG1: 4.1.3rank | EH1: 4.1.4rank | EI1: 4.2.1rank | EJ1: 4.2.2rank | EK1: 4.2.3rank | EL1: 4.2.4rank | EM1: 4.3.1rank | EN1: 4.3.2rank | EO1: 4.3.3rank | EP1: 4.3.4rank | EQ1: 4.3.5rank
G2: NRI | J2: PILLARS | R2: SUBPILLARS | AP2: 1.1.1 | AQ2: 1.1.2 | AR2: 1.1.3 | AS2: 1.1.4 | AT2: 1.1.5 | AU2: 1.1.6 | AV2: 1.2.1 | AW2: 1.2.2 | AX2: 1.2.3 | AY2: 1.2.4 | AZ2: 1.3.1 | BA2: 1.3.2 | BB2: 1.3.3 | BC2: 1.3.4 | BD2: 2.1.1 | BE2: 2.1.2 | BF2: 2.1.3 | BG2: 2.1.4 | BH2: 2.1.5 | BI2: 2.2.1 | BJ2: 2.2.2 | BK2: 2.2.3 | BL2: 2.2.4 | BM2: 2.3.1 | BN2: 2.3.2 | BO2: 2.3.3 | BP2: 2.3.4 | BQ2: 3.1.1 | BR2: 3.1.2 | BS2: 3.1.3 | BT2: 3.1.4 | BU2: 3.2.1 | BV2: 3.2.2 | BW2: 3.2.3 | BX2: 3.2.4 | BY2: 3.2.5 | BZ2: 3.3.1 | CA2: 3.3.2 | CB2: 3.3.3 | CC2: 3.3.4 | CD2: 4.1.1 | CE2: 4.1.2 | CF2: 4.1.3 | CG2: 4.1.4 | CH2: 4.2.1 | CI2: 4.2.2 | CJ2: 4.2.3 | CK2: 4.2.4 | CL2: 4.3.1 | CM2: 4.3.2 | CN2: 4.3.3 | CO2: 4.3.4 | CP2: 4.3.5 | CQ2: 1.1.1 | CR2: 1.1.2 | CS2: 1.1.3 | CT2: 1.1.4 | CU2: 1.1.5 | CV2: 1.1.6 | CW2: 1.2.1 | CX2: 1.2.2 | CY2: 1.2.3 | CZ2: 1.2.4 | DA2: 1.3.1 | DB2: 1.3.2 | DC2: 1.3.3 | DD2: 1.3.4 | DE2: 2.1.1 | DF2: 2.1.2 | DG2: 2.1.3 | DH2: 2.1.4 | DI2: 2.1.5 | DJ2: 2.2.1 | DK2: 2.2.2 | DL2: 2.2.3 | DM2: 2.2.4 | DN2: 2.3.1 | DO2: 2.3.2 | DP2: 2.3.3 | DQ2: 2.3.4 | DR2: 3.1.1 | DS2: 3.1.2 | DT2: 3.1.3 | DU2: 3.1.4 | DV2: 3.2.1 | DW2: 3.2.2 | DX2: 3.2.3 | DY2: 3.2.4 | DZ2: 3.2.5 | EA2: 3.3.1 | EB2: 3.3.2 | EC2: 3.3.3 | ED2: 3.3.4 | EE2: 4.1.1 | EF2: 4.1.2 | EG2: 4.1.3 | EH2: 4.1.4 | EI2: 4.2.1 | EJ2: 4.2.2 | EK2: 4.2.3 | EL2: 4.2.4 | EM2: 4.3.1 | EN2: 4.3.2 | EO2: 4.3.3 | EP2: 4.3.4 | EQ2: 4.3.5
G3: score | I3: ranking | J3: score | K3: score | L3: score | M3: score | N3: ranking | O3: ranking | P3: ranking | Q3: ranking | R3: score | S3: score | T3: score | U3: score | V3: score | W3: score | X3: score | Y3: score | Z3: score | AA3: score | AB3: score | AC3: score | AD3: ranking | AE3: ranking | AF3: ranking | AG3: ranking | AH3: ranking | AI3: ranking | AJ3: ranking | AK3: ranking | AL3: ranking | AM3: ranking | AN3: ranking | AO3: ranking | AP3: score | AQ3: score | AR3: score | AS3: score | AT3: score | AU3: score | AV3: score | AW3: score | AX3: score | AY3: score | AZ3: score | BA3: score | BB3: score | BC3: score | BD3: score | BE3: score | BF3: score | BG3: score | BH3: score | BI3: score | BJ3: score | BK3: score | BL3: score | BM3: score | BN3: score | BO3: score | BP3: score | BQ3: score | BR3: score | BS3: score | BT3: score | BU3: score | BV3: score | BW3: score | BX3: score | BY3: score | BZ3: score | CA3: score | CB3: score | CC3: score | CD3: score | CE3: score | CF3: score | CG3: score | CH3: score | CI3: score | CJ3: score | CK3: score | CL3: score | CM3: score | CN3: score | CO3: score | CP3: score | CQ3: rank | CR3: rank | CS3: rank | CT3: rank | CU3: rank | CV3: rank | CW3: rank | CX3: rank | CY3: rank | CZ3: rank | DA3: rank | DB3: rank | DC3: rank | DD3: rank | DE3: rank | DF3: rank | DG3: rank | DH3: rank | DI3: rank | DJ3: rank | DK3: rank | DL3: rank | DM3: rank | DN3: rank | DO3: rank | DP3: rank | DQ3: rank | DR3: rank | DS3: rank | DT3: rank | DU3: rank | DV3: rank | DW3: rank | DX3: rank | DY3: rank | DZ3: rank | EA3: rank | EB3: rank | EC3: rank | ED3: rank | EE3: rank | EF3: rank | EG3: rank | EH3: rank | EI3: rank | EJ3: rank | EK3: rank | EL3: rank | EM3: rank | EN3: rank | EO3: rank | EP3: rank | EQ3: rank
A4: NRI 2024 | G4: NRI | I4: NRI | J4: Technology | K4: People | L4: Governance | M4: Impact | N4: Technology | O4: People | P4: Governance | Q4: Impact | R4: Access | S4: Content | T4: Future Technologies | U4: Individuals | V4: Businesses | W4: Governments | X4: Trust | Y4: Regulation | Z4: Inclusion | AA4: Economy | AB4: Quality of Life | AC4: SDG Contribution | AD4: Access | AE4: Content | AF4: Future Technologies | AG4: Individuals | AH4: Businesses | AI4: Governments | AJ4: Trust | AK4: Regulation | AL4: Inclusion | AM4: Economy | AN4: Quality of Life | AO4: SDG Contribution | AP4: Mobile tariffs | AQ4: Handset prices | AR4: FTTH/building Internet subscriptions | AS4: Population covered by at least a 3G mobile network | AT4: International Internet bandwidth | AU4: Internet access in schools | AV4: GitHub commits | AW4: Internet domain registrations | AX4: Mobile apps development | AY4: AI scientific publications | AZ4: Adoption of emerging technologies | BA4: Investment in emerging technologies | BB4: Robot density | BC4: Computer software spending | BD4: Mobile broadband internet traffic within the country | BE4: ICT skills in the education system | BF4: Use of virtual social networks | BG4: Adult literacy rate | BH4: AI talent concentration | BI4: Firms with website | BJ4: Number of venture capital deals invested in AI | BK4: Annual investment in telecommunication services | BL4: Public cloud computing market scale | BM4: Government online services | BN4: Data Capabilities | BO4: Government promotion of emerging technologies | BP4: Gross expenditure on R&D | BQ4: Secure Internet servers | BR4: Cybersecurity | BS4: Online access to financial account | BT4: Internet shopping | BU4: Regulatory quality | BV4: ICT regulatory environment | BW4: Regulation of emerging technologies | BX4: E-commerce legislation | BY4: Privacy protection by law content | BZ4: E-Participation | CA4: Socioeconomic gap in use of digital payments | CB4: Gender gap in Internet use | CC4: Rural gap in use of digital payments | CD4: ICT patent applications | CE4: Domestic market scale | CF4: Technology-enabled work flexibility | CG4: ICT services exports | CH4: Happiness | CI4: Freedom to make life choices | CJ4: Income inequality | CK4: Healthy life expectancy at birth | CL4: SDG 3: Good Health and Well-Being | CM4: SDG 4: Quality Education | CN4: SDG 5: Women's economic opportunity | CO4: SDG 7: Affordable and Clean Energy | CP4: SDG 11: Sustainable Cities and Communities | CQ4: Mobile tariffs | CR4: Handset prices | CS4: FTTH/building Internet subscriptions | CT4: Population covered by at least a 3G mobile network | CU4: International Internet bandwidth | CV4: Internet access in schools | CW4: GitHub commits | CX4: Internet domain registrations | CY4: Mobile apps development | CZ4: AI scientific publications | DA4: Adoption of emerging technologies | DB4: Investment in emerging technologies | DC4: Robot density | DD4: Computer software spending | DE4: Mobile broadband internet traffic within the country | DF4: ICT skills in the education system | DG4: Use of virtual social networks | DH4: Adult literacy rate | DI4: AI talent concentration | DJ4: Firms with website | DK4: Number of venture capital deals invested in AI | DL4: Annual investment in telecommunication services | DM4: Public cloud computing market scale | DN4: Government online services | DO4: Data Capabilities | DP4: Government promotion of emerging technologies | DQ4: Gross expenditure on R&D | DR4: Secure Internet servers | DS4: Cybersecurity | DT4: Online access to financial account | DU4: Internet shopping | DV4: Regulatory quality | DW4: ICT regulatory environment | DX4: Regulation of emerging technologies | DY4: E-commerce legislation | DZ4: Privacy protection by law content | EA4: E-Participation | EB4: Socioeconomic gap in use of digital payments | EC4: Gender gap in Internet use | ED4: Rural gap in use of digital payments | EE4: ICT patent applications | EF4: Domestic market scale | EG4: Technology-enabled work flexibility | EH4: ICT services exports | EI4: Happiness | EJ4: Freedom to make life choices | EK4: Income inequality | EL4: Healthy life expectancy at birth | EM4: SDG 3: Good Health and Well-Being | EN4: SDG 4: Quality Education | EO4: SDG 5: Women's economic opportunity | EP4: SDG 7: Affordable and Clean Energy | EQ4: SDG 11: Sustainable Cities and Communities
G5: nri.score | I5: nri.ranking | J5: 1. | K5: 2. | L5: 3. | M5: 4. | N5: 1. | O5: 2. | P5: 3. | Q5: 4. | R5: 1.1. | S5: 1.2. | T5: 1.3. | U5: 2.1. | V5: 2.2. | W5: 2.3. | X5: 3.1. | Y5: 3.2. | Z5: 3.3. | AA5: 4.1. | AB5: 4.2. | AC5: 4.3. | AD5: 1.1. | AE5: 1.2. | AF5: 1.3. | AG5: 2.1. | AH5: 2.2. | AI5: 2.3. | AJ5: 3.1. | AK5: 3.2. | AL5: 3.3. | AM5: 4.1. | AN5: 4.2. | AO5: 4.3. | AP5: 1.1.1. | AQ5: 1.1.2. | AR5: 1.1.3. | AS5: 1.1.4. | AT5: 1.1.5. | AU5: 1.1.6. | AV5: 1.2.1. | AW5: 1.2.2. | AX5: 1.2.3. | AY5: 1.2.4. | AZ5: 1.3.1. | BA5: 1.3.2. | BB5: 1.3.3. | BC5: 1.3.4. | BD5: 2.1.1. | BE5: 2.1.2. | BF5: 2.1.3. | BG5: 2.1.4. | BH5: 2.1.5. | BI5: 2.2.1. | BJ5: 2.2.2. | BK5: 2.2.3. | BL5: 2.2.4. | BM5: 2.3.1. | BN5: 2.3.2. | BO5: 2.3.3. | BP5: 2.3.4. | BQ5: 3.1.1. | BR5: 3.1.2. | BS5: 3.1.3. | BT5: 3.1.4. | BU5: 3.2.1. | BV5: 3.2.2. | BW5: 3.2.3. | BX5: 3.2.4. | BY5: 3.2.5. | BZ5: 3.3.1. | CA5: 3.3.2. | CB5: 3.3.3. | CC5: 3.3.4. | CD5: 4.1.1. | CE5: 4.1.2. | CF5: 4.1.3. | CG5: 4.1.4. | CH5: 4.2.1. | CI5: 4.2.2. | CJ5: 4.2.3. | CK5: 4.2.4. | CL5: 4.3.1. | CM5: 4.3.2. | CN5: 4.3.3. | CO5: 4.3.4. | CP5: 4.3.5. | CQ5: 1.1.1. | CR5: 1.1.2. | CS5: 1.1.3. | CT5: 1.1.4. | CU5: 1.1.5. | CV5: 1.1.6. | CW5: 1.2.1. | CX5: 1.2.2. | CY5: 1.2.3. | CZ5: 1.2.4. | DA5: 1.3.1. | DB5: 1.3.2. | DC5: 1.3.3. | DD5: 1.3.4. | DE5: 2.1.1. | DF5: 2.1.2. | DG5: 2.1.3. | DH5: 2.1.4. | DI5: 2.1.5. | DJ5: 2.2.1. | DK5: 2.2.2. | DL5: 2.2.3. | DM5: 2.2.4. | DN5: 2.3.1. | DO5: 2.3.2. | DP5: 2.3.3. | DQ5: 2.3.4. | DR5: 3.1.1. | DS5: 3.1.2. | DT5: 3.1.3. | DU5: 3.1.4. | DV5: 3.2.1. | DW5: 3.2.2. | DX5: 3.2.3. | DY5: 3.2.4. | DZ5: 3.2.5. | EA5: 3.3.1. | EB5: 3.3.2. | EC5: 3.3.3. | ED5: 3.3.4. | EE5: 4.1.1. | EF5: 4.1.2. | EG5: 4.1.3. | EH5: 4.1.4. | EI5: 4.2.1. | EJ5: 4.2.2. | EK5: 4.2.3. | EL5: 4.2.4. | EM5: 4.3.1. | EN5: 4.3.2. | EO5: 4.3.3. | EP5: 4.3.4. | EQ5: 4.3.5.
A6: Economy | B6: ISO3Code | C6: region | D6: inc.group | E6: gdp.capita | F6: population | G6: NRI.score | H6: ISO2code | I6: NRI.ranking | J6: 1.score | K6: 2.score | L6: 3.score | M6: 4.score | N6: 1.ranking | O6: 2.ranking | P6: 3.ranking | Q6: 4.ranking | R6: 1.1.score | S6: 1.2.score | T6: 1.3.score | U6: 2.1.score | V6: 2.2.score | W6: 2.3.score | X6: 3.1.score | Y6: 3.2.score | Z6: 3.3.score | AA6: 4.1.score | AB6: 4.2.score | AC6: 4.3.score | AD6: 1.1.ranking | AE6: 1.2.ranking | AF6: 1.3.ranking | AG6: 2.1.ranking | AH6: 2.2.ranking | AI6: 2.3.ranking | AJ6: 3.1.ranking | AK6: 3.2.ranking | AL6: 3.3.ranking | AM6: 4.1.ranking | AN6: 4.2.ranking | AO6: 4.3.ranking | AP6: 1.1.1.score | AQ6: 1.1.2.score | AR6: 1.1.3.score | AS6: 1.1.4.score | AT6: 1.1.5.score | AU6: 1.1.6.score | AV6: 1.2.1.score | AW6: 1.2.2.score | AX6: 1.2.3.score | AY6: 1.2.4.score | AZ6: 1.3.1.score | BA6: 1.3.2.score | BB6: 1.3.3.score | BC6: 1.3.4.score | BD6: 2.1.1.score | BE6: 2.1.2.score | BF6: 2.1.3.score | BG6: 2.1.4.score | BH6: 2.1.5.score | BI6: 2.2.1.score | BJ6: 2.2.2.score | BK6: 2.2.3.score | BL6: 2.2.4.score | BM6: 2.3.1.score | BN6: 2.3.2.score | BO6: 2.3.3.score | BP6: 2.3.4.score | BQ6: 3.1.1.score | BR6: 3.1.2.score | BS6: 3.1.3.score | BT6: 3.1.4.score | BU6: 3.2.1.score | BV6: 3.2.2.score | BW6: 3.2.3.score | BX6: 3.2.4.score | BY6: 3.2.5.score | BZ6: 3.3.1.score | CA6: 3.3.2.score | CB6: 3.3.3.score | CC6: 3.3.4.score | CD6: 4.1.1.score | CE6: 4.1.2.score | CF6: 4.1.3.score | CG6: 4.1.4.score | CH6: 4.2.1.score | CI6: 4.2.2.score | CJ6: 4.2.3.score | CK6: 4.2.4.score | CL6: 4.3.1.score | CM6: 4.3.2.score | CN6: 4.3.3.score | CO6: 4.3.4.score | CP6: 4.3.5.score | CQ6: 1.1.1.rank | CR6: 1.1.2.rank | CS6: 1.1.3.rank | CT6: 1.1.4.rank | CU6: 1.1.5.rank | CV6: 1.1.6.rank | CW6: 1.2.1.rank | CX6: 1.2.2.rank | CY6: 1.2.3.rank | CZ6: 1.2.4.rank | DA6: 1.3.1.rank | DB6: 1.3.2.rank | DC6: 1.3.3.rank | DD6: 1.3.4.rank | DE6: 2.1.1.rank | DF6: 2.1.2.rank | DG6: 2.1.3.rank | DH6: 2.1.4.rank | DI6: 2.1.5.rank | DJ6: 2.2.1.rank | DK6: 2.2.2.rank | DL6: 2.2.3.rank | DM6: 2.2.4.rank | DN6: 2.3.1.rank | DO6: 2.3.2.rank | DP6: 2.3.3.rank | DQ6: 2.3.4.rank | DR6: 3.1.1.rank | DS6: 3.1.2.rank | DT6: 3.1.3.rank | DU6: 3.1.4.rank | DV6: 3.2.1.rank | DW6: 3.2.2.rank | DX6: 3.2.3.rank | DY6: 3.2.4.rank | DZ6: 3.2.5.rank | EA6: 3.3.1.rank | EB6: 3.3.2.rank | EC6: 3.3.3.rank | ED6: 3.3.4.rank | EE6: 4.1.1.rank | EF6: 4.1.2.rank | EG6: 4.1.3.rank | EH6: 4.1.4.rank | EI6: 4.2.1.rank | EJ6: 4.2.2.rank | EK6: 4.2.3.rank | EL6: 4.2.4.rank | EM6: 4.3.1.rank | EN6: 4.3.2.rank | EO6: 4.3.3.rank | EP6: 4.3.4.rank | EQ6: 4.3.5.rank
A7: United States of America | B7: USA | C7: The Americas | D7: High-income | E7: 89598.86 | F7: 343477000 | G7: 79.130951 | H7: US | I7: 1 | J7: 82.46917 | K7: 76.156544 | L7: 86.480215 | M7: 71.417873 | N7: 1 | O7: 1 | P7: 9 | Q7: 16 | R7: 87.233503 | S7: 76.143478 | T7: 84.030529 | U7: 67.071532 | V7: 84.060786 | W7: 77.337313 | X7: 94.729462 | Y7: 80.60483 | Z7: 84.106355 | AA7: 73.507594 | AB7: 63.247559 | AC7: 77.498468 | AD7: 2 | AE7: 1 | AF7: 1 | AG7: 14 | AH7: 1 | AI7: 2 | AJ7: 3 | AK7: 18 | AL7: 12 | AM7: 3 | AN7: 73 | AO7: 34 | AP7: 84.541446 | AQ7: 95.961898 | AR7: 58.483683 | AS7: 94.736842 | AT7: 89.67715 | AU7: 100 | AV7: 61.663406 | AW7: 68.932766 | AX7: 73.977738 | AY7: 100 | AZ7: 98.647926 | BA7: 100 | BB7: 37.47419 | BC7: 100 | BD7: 83.00324 | BE7: 80.518087 | BF7: 73.447061 | BG7: n/a | BH7: 31.317741 | BI7: n/a | BJ7: 58.063167 | BK7: 94.119192 | BL7: 100 | BM7: 89.603109 | BN7: 65.46443 | BO7: 100 | BP7: 54.281712 | BQ7: 98.17468 | BR7: 99.827535 | BS7: n/a | BT7: 86.18617 | BU7: 77.106013 | BV7: 74.6875 | BW7: 88.206996 | BX7: 100 | BY7: 63.023642 | BZ7: 94.202285 | CA7: 88.495713 | CB7: 69.621065 | CC7: n/a | CD7: 100 | CE7: 97.720334 | CF7: 81.235777 | CG7: 15.074263 | CH7: 77.390527 | CI7: 52.083333 | CJ7: 54.081633 | CK7: 66.455998 | CL7: 100 | CM7: 62.904905 | CN7: 87.272727 | CO7: 69.106566 | CP7: 81.419344 | CQ7: 28 | CR7: 17 | CS7: 13 | CT7: 63 | CU7: 6 | CV7: 1 | CW7: 16 | CX7: 8 | CY7: 19 | CZ7: 1 | DA7: 4 | DB7: 1 | DC7: 10 | DD7: 1 | DE7: 3 | DF7: 12 | DG7: 55 | DH7: n/a | DI7: 25 | DJ7: n/a | DK7: 8 | DL7: 2 | DM7: 1 | DN7: 17 | DO7: 16 | DP7: 1 | DQ7: 4 | DR7: 5 | DS7: 13 | DT7: n/a | DU7: 8 | DV7: 18 | DW7: 61 | DX7: 6 | DY7: 1 | DZ7: 63 | EA7: 11 | EB7: 33 | EC7: 19 | ED7: n/a | EE7: 1 | EF7: 2 | EG7: 7 | EH7: 59 | EI7: 24 | EJ7: 103 | EK7: 87 | EL7: 63 | EM7: 1 | EN7: 17 | EO7: 37 | EP7: 83 | EQ7: 31
A8: Finland | B8: FIN | C8: Europe | D8: High-income | E8: 66512.47 | F8: 5601000 | G8: 75.823837 | H8: FI | I8: 2 | J8: 66.281468 | K8: 62.938287 | L8: 88.905536 | M8: 85.170059 | N8: 9 | O8: 10 | P8: 4 | Q8: 1 | R8: 79.372358 | S8: 56.236637 | T8: 63.235408 | U8: 66.167772 | V8: 55.461729 | W8: 67.185361 | X8: 92.813656 | Y8: 91.16848 | Z8: 82.734471 | AA8: 79.005205 | AB8: 95.205334 | AC8: 81.299637 | AD8: 22 | AE8: 10 | AF8: 10 | AG8: 17 | AH8: 18 | AI8: 10 | AJ8: 6 | AK8: 3 | AL8: 17 | AM8: 2 | AN8: 1 | AO8: 25 | AP8: 78.898928 | AQ8: 100 | AR8: 30.333542 | AS8: 99.947368 | AT8: 67.054312 | AU8: 100 | AV8: 98.817152 | AW8: 39.684846 | AX8: 79.282406 | AY8: 7.1621455 | AZ8: 96.072497 | BA8: 87.75 | BB8: 22.318795 | BC8: 46.800341 | BD8: 29.727528 | BE8: 100 | BF8: 83.431864 | BG8: n/a | BH8: 51.511694 | BI8: 100 | BJ8: 42.611544 | BK8: 46.290606 | BL8: 32.944767 | BM8: 89.139929 | BN8: 71.304038 | BO8: 59.588556 | BP8: 48.70892 | BQ8: 97.348226 | BR8: 100 | BS8: n/a | BT8: 81.092743 | BU8: 86.400571 | BV8: 98.125 | BW8: 94.564445 | BX8: 100 | BY8: 76.752385 | BZ8: 88.40457 | CA8: 95.394515 | CB8: 64.404327 | CC8: n/a | CD8: 100 | CE8: 55.856156 | CF8: 94.292965 | CG8: 65.871698 | CH8: 100 | CI8: 96.614583 | CJ8: 90.816327 | CK8: 87.186513 | CL8: 100 | CM8: 65.261074 | CN8: 96.363636 | CO8: 65.339074 | CP8: 96.469524 | CQ8: 39 | CR8: 1 | CS8: 68 | CT8: 25 | CU8: 89 | CV8: 1 | CW8: 3 | CX8: 21 | CY8: 9 | CZ8: 54 | DA8: 7 | DB8: 5 | DC8: 20 | DD8: 14 | DE8: 38 | DF8: 1 | DG8: 15 | DH8: n/a | DI8: 6 | DJ8: 1 | DK8: 13 | DL8: 47 | DM8: 22 | DN8: 19 | DO8: 7 | DP8: 29 | DQ8: 10 | DR8: 6 | DS8: 1 | DT8: n/a | DU8: 13 | DV8: 7 | DW8: 3 | DX8: 2 | DY8: 1 | DZ8: 35 | EA8: 19 | EB8: 20 | EC8: 58 | ED8: n/a | EE8: 1 | EF8: 59 | EG8: 3 | EH8: 7 | EI8: 1 | EJ8: 4 | EK8: 14 | EL8: 20 | EM8: 1 | EN8: 11 | EO8: 15 | EP8: 90 | EQ8: 5
A9: Singapore | B9: SGP | C9: Asia & Pacific | D9: High-income | E9: 156969.07 | F9: 5789000 | G9: 75.462405 | H9: SG | I9: 3 | J9: 70.422542 | K9: 68.104724 | L9: 84.408291 | M9: 78.914062 | N9: 4 | O9: 4 | P9: 15 | Q9: 7 | R9: 85.695613 | S9: 52.548694 | T9: 73.023318 | U9: 74.433802 | V9: 56.800785 | W9: 73.079586 | X9: 88.566838 | Y9: 80.274911 | Z9: 84.383123 | AA9: 68.197574 | AB9: 81.410299 | AC9: 87.134313 | AD9: 4 | AE9: 14 | AF9: 2 | AG9: 3 | AH9: 14 | AI9: 4 | AJ9: 12 | AK9: 19 | AL9: 9 | AM9: 6 | AN9: 17 | AO9: 4 | AP9: 96.73774 | AQ9: 100 | AR9: 24.482816 | AS9: 100 | AT9: 92.953119 | AU9: 100 | AV9: 100 | AW9: 20.259801 | AX9: 84.518629 | AY9: 5.416346 | AZ9: 97.378329 | BA9: 78.5 | BB9: 100 | BC9: 16.214943 | BD9: 12.663184 | BE9: 90.376798 | BF9: 91.658317 | BG9: 96.923077 | BH9: 80.547633 | BI9: 61.383446 | BJ9: 83.572407 | BK9: 45.180098 | BL9: 37.067188 | BM9: 97.962007 | BN9: n/a | BO9: 92.241239 | BP9: 29.035511 | BQ9: 98.694832 | BR9: 99.827535 | BS9: n/a | BT9: 67.178148 | BU9: 100 | BV9: 87.8125 | BW9: 93.767363 | BX9: 75 | BY9: 44.794691 | BZ9: 95.651714 | CA9: 91.834174 | CB9: 65.66348 | CC9: n/a | CD9: 98.306305 | CE9: 64.392816 | CF9: 85.963445 | CG9: 24.127729 | CH9: 73.838248 | CI9: 79.6875 | CJ9: n/a | CK9: 100 | CL9: 100 | CM9: 91.937508 | CN9: 74.545455 | CO9: 86.8676 | CP9: 90.373384 | CQ9: 4 | CR9: 1 | CS9: 84 | CT9: 1 | CU9: 4 | CV9: 1 | CW9: 1 | CX9: 34 | CY9: 3 | CZ9: 65 | DA9: 5 | DB9: 13 | DC9: 1 | DD9: 69 | DE9: 71 | DF9: 2 | DG9: 4 | DH9: 28 | DI9: 2 | DJ9: 51 | DK9: 5 | DL9: 50 | DM9: 18 | DN9: 6 | DO9: n/a | DP9: 3 | DQ9: 19 | DR9: 3 | DS9: 13 | DT9: n/a | DU9: 23 | DV9: 1 | DW9: 25 | DX9: 3 | DY9: 72 | DZ9: 95 | EA9: 7 | EB9: 26 | EC9: 52 | ED9: n/a | EE9: 6 | EF9: 34 | EG9: 4 | EH9: 41 | EI9: 31 | EJ9: 49 | EK9: n/a | EL9: 1 | EM9: 1 | EN9: 2 | EO9: 72 | EP9: 22 | EQ9: 18
A10: Denmark | B10: DNK | C10: Europe | D10: High-income | E10: 84762.884 | F10: 5948000 | G10: 75.135904 | H10: DK | I10: 4 | J10: 67.473821 | K10: 58.748614 | L10: 92.023059 | M10: 82.298123 | N10: 8 | O10: 17 | P10: 1 | Q10: 3 | R10: 80.432016 | S10: 57.897621 | T10: 64.091826 | U10: 53.686631 | V10: 58.585059 | W10: 63.974153 | X10: 99.977835 | Y10: 87.456211 | Z10: 88.63513 | AA10: 67.597527 | AB10: 91.269017 | AC10: 88.027825 | AD10: 16 | AE10: 8 | AF10: 9 | AG10: 54 | AH10: 11 | AI10: 18 | AJ10: 1 | AK10: 8 | AL10: 2 | AM10: 7 | AN10: 4 | AO10: 2 | AP10: 92.422848 | AQ10: 93.036021 | AR10: 29.120567 | AS10: 100 | AT10: 68.012658 | AU10: 100 | AV10: 74.284614 | AW10: 79.588897 | AX10: 73.517309 | AY10: 4.1996652 | AZ10: 90.636248 | BA10: 76.75 | BB10: 40.164264 | BC10: 48.816793 | BD10: 20.896896 | BE10: 78.932749 | BF10: 83.25687 | BG10: n/a | BH10: 31.660011 | BI10: 92.248862 | BJ10: 54.912272 | BK10: 51.505422 | BL10: 35.673681 | BM10: 99.908567 | BN10: 69.284186 | BO10: 39.698501 | BP10: 47.005355 | BQ10: 100 | BR10: 100 | BS10: n/a | BT10: 99.933505 | BU10: 88.261664 | BV10: 94.375 | BW10: 77.746838 | BX10: 100 | BY10: 76.897553 | BZ10: 98.550571 | CA10: 99.078964 | CB10: 68.275856 | CC10: n/a | CD10: 86.253361 | CE10: 58.916077 | CF10: 100 | CG10: 25.220671 | CH10: 95.196604 | CI10: 92.578125 | CJ10: 84.438776 | CK10: 87.625868 | CL10: 100 | CM10: 63.408659 | CN10: 100 | CO10: 92.787944 | CP10: 91.829397 | CQ10: 9 | CR10: 23 | CS10: 73 | CT10: 1 | CU10: 84 | CV10: 1 | CW10: 9 | CX10: 6 | CY10: 21 | CZ10: 69 | DA10: 11 | DB10: 14 | DC10: 8 | DD10: 8 | DE10: 48 | DF10: 15 | DG10: 17 | DH10: n/a | DI10: 23 | DJ10: 11 | DK10: 9 | DL10: 28 | DM10: 20 | DN10: 2 | DO10: 12 | DP10: 55 | DQ10: 11 | DR10: 1 | DS10: 1 | DT10: n/a | DU10: 2 | DV10: 5 | DW10: 5 | DX10: 17 | DY10: 1 | DZ10: 34 | EA10: 2 | EB10: 6 | EC10: 29 | ED10: n/a | EE10: 10 | EF10: 51 | EG10: 1 | EH10: 39 | EI10: 2 | EJ10: 11 | EK10: 23 | EL10: 16 | EM10: 1 | EN10: 16 | EO10: 1 | EP10: 8 | EQ10: 15
A11: Sweden | B11: SWE | C11: Europe | D11: High-income | E11: 73069.51 | F11: 10551000 | G11: 75.086618 | H11: SE | I11: 5 | J11: 69.043628 | K11: 62.360027 | L11: 86.679974 | M11: 82.262845 | N11: 6 | O11: 11 | P11: 8 | Q11: 4 | R11: 79.816405 | S11: 57.278724 | T11: 70.035756 | U11: 58.508155 | V11: 58.451885 | W11: 70.120039 | X11: 92.551596 | Y11: 87.972395 | Z11: 79.51593 | AA11: 71.162056 | AB11: 90.692968 | AC11: 84.933509 | AD11: 19 | AE11: 9 | AF11: 3 | AG11: 34 | AH11: 12 | AI11: 6 | AJ11: 7 | AK11: 5 | AL11: 24 | AM11: 5 | AN11: 5 | AO11: 10 | AP11: 86.457628 | AQ11: 83.911159 | AR11: 39.049143 | AS11: 100 | AT11: 69.480497 | AU11: 100 | AV11: 85.139554 | AW11: 57.316392 | AX11: 78.370324 | AY11: 8.2886252 | AZ11: 88.502538 | BA11: 92 | BB11: 45.98188 | BC11: 53.658605 | BD11: 26.062296 | BE11: 85.208413 | BF11: 84.655809 | BG11: n/a | BH11: 38.106104 | BI11: 92.643535 | BJ11: 50.254737 | BK11: 50.798079 | BL11: 40.111189 | BM11: 85.997522 | BN11: 58.110725 | BO11: 79.645581 | BP11: 56.726329 | BQ11: 87.929554 | BR11: 99.174284 | BS11: n/a | BT11: 90.550951 | BU11: 85.221104 | BV11: 81.25 | BW11: 79.404972 | BX11: 100 | BY11: 93.985898 | BZ11: 78.25857 | CA11: 96.188741 | CB11: 64.100479 | CC11: n/a | CD11: 100 | CE11: 63.036348 | CF11: 69.550273 | CG11: 52.061602 | CH11: 91.264522 | CI11: 92.1875 | CJ11: 85.969388 | CK11: 91.284378 | CL11: 100 | CM11: 62.08404 | CN11: 100 | CO11: 78.794403 | CP11: 97.711191 | CQ11: 18 | CR11: 40 | CS11: 44 | CT11: 1 | CU11: 74 | CV11: 1 | CW11: 5 | CX11: 14 | CY11: 11 | CZ11: 50 | DA11: 13 | DB11: 3 | DC11: 6 | DD11: 4 | DE11: 41 | DF11: 6 | DG11: 11 | DH11: n/a | DI11: 15 | DJ11: 8 | DK11: 11 | DL11: 30 | DM11: 15 | DN11: 27 | DO11: 19 | DP11: 11 | DQ11: 3 | DR11: 19 | DS11: 18 | DT11: n/a | DU11: 3 | DV11: 10 | DW11: 41 | DX11: 15 | DY11: 1 | DZ11: 7 | EA11: 35 | EB11: 14 | EC11: 63 | ED11: n/a | EE11: 1 | EF11: 40 | EG11: 23 | EH11: 12 | EI11: 4 | EJ11: 13 | EK11: 19 | EL11: 8 | EM11: 1 | EN11: 18 | EO11: 1 | EP11: 50 | EQ11: 3
A12: Netherlands | B12: NLD | C12: Europe | D12: High-income | E12: 84035.223 | F12: 18093000 | G12: 75.084632 | H12: NL | I12: 6 | J12: 72.01495 | K12: 58.711721 | L12: 89.564062 | M12: 80.047793 | N12: 3 | O12: 18 | P12: 3 | Q12: 5 | R12: 80.84258 | S12: 69.61211 | T12: 65.59016 | U12: 55.556759 | V12: 57.604596 | W12: 62.973808 | X12: 94.835416 | Y12: 89.67707 | Z12: 84.179702 | AA12: 67.458627 | AB12: 87.279674 | AC12: 85.405078 | AD12: 15 | AE12: 3 | AF12: 7 | AG12: 45 | AH12: 13 | AI12: 19 | AJ12: 2 | AK12: 4 | AL12: 11 | AM12: 8 | AN12: 7 | AO12: 8 | AP12: 86.162742 | AQ12: 94.006383 | AR12: 34.956122 | AS12: 94.736842 | AT12: 75.193391 | AU12: 100 | AV12: 93.595754 | AW12: 100 | AX12: 72.130879 | AY12: 12.721806 | AZ12: 96.373878 | BA12: 87.75 | BB12: 35.791563 | BC12: 42.445197 | BD12: 20.55566 | BE12: 67.541494 | BF12: 86.154981 | BG12: n/a | BH12: 47.9749 | BI12: 88.698512 | BJ12: 35.621531 | BK12: 59.404439 | BL12: 46.693903 | BM12: 90.517438 | BN12: 73.285472 | BO12: 53.047656 | BP12: 35.044667 | BQ12: 98.261094 | BR12: 99.059948 | BS12: n/a | BT12: 87.185206 | BU12: 87.046632 | BV12: 89.6875 | BW12: 81.356734 | BX12: 100 | BY12: 90.294484 | BZ12: 92.752857 | CA12: 95.953965 | CB12: 63.832283 | CC12: n/a | CD12: 72.473749 | CE12: 69.2295 | CF12: 94.324526 | CG12: 33.806731 | CH12: 90.393208 | CI12: 80.208333 | CJ12: 95.153061 | CK12: 87.3219 | CL12: 100 | CM12: 59.040855 | CN12: 100 | CO12: 87.082885 | CP12: 90.99314 | CQ12: 23 | CR12: 22 | CS12: 54 | CT12: 63 | CU12: 44 | CV12: 1 | CW12: 4 | CX12: 1 | CY12: 27 | CZ12: 44 | DA12: 6 | DB12: 5 | DC12: 12 | DD12: 20 | DE12: 49 | DF12: 34 | DG12: 9 | DH12: n/a | DI12: 9 | DJ12: 14 | DK12: 17 | DL12: 17 | DM12: 10 | DN12: 15 | DO12: 5 | DP12: 32 | DQ12: 15 | DR12: 4 | DS12: 22 | DT12: n/a | DU12: 7 | DV12: 6 | DW12: 19 | DX12: 12 | DY12: 1 | DZ12: 12 | EA12: 12 | EB12: 16 | EC12: 65 | ED12: n/a | EE12: 11 | EF12: 27 | EG12: 2 | EH12: 26 | EI12: 5 | EJ12: 45 | EK12: 5 | EL12: 19 | EM12: 1 | EN12: 25 | EO12: 1 | EP12: 21 | EQ12: 17
A13: Germany | B13: DEU | C13: Europe | D13: High-income | E13: 73553.296 | F13: 84548000 | G13: 74.121352 | H13: DE | I13: 7 | J13: 70.274689 | K13: 63.049616 | L13: 86.835444 | M13: 76.325659 | N13: 5 | O13: 9 | P13: 6 | Q13: 9 | R13: 81.550008 | S13: 64.953371 | T13: 64.320689 | U13: 58.722097 | V13: 62.339869 | W13: 68.08688 | X13: 87.379837 | Y13: 85.512986 | Z13: 87.61351 | AA13: 64.566047 | AB13: 79.631509 | AC13: 84.779422 | AD13: 13 | AE13: 4 | AF13: 8 | AG13: 32 | AH13: 8 | AI13: 8 | AJ13: 16 | AK13: 14 | AL13: 5 | AM13: 9 | AN13: 22 | AO13: 12 | AP13: 90.40681 | AQ13: 97.813044 | AR13: 40.944455 | AS13: 99.842105 | AT13: 78.743623 | AU13: n/a | AV13: 60.656541 | AW13: 78.476659 | AX13: 69.3514 | AY13: 51.328885 | AZ13: 78.213017 | BA13: 86.75 | BB13: 54.779189 | BC13: 37.540549 | BD13: 40.321764 | BE13: 60.899431 | BF13: 84.665483 | BG13: n/a | BH13: 49.001711 | BI13: 93.835852 | BJ13: 17.314972 | BK13: 72.945954 | BL13: 65.2627 | BM13: 90.837454 | BN13: 71.150594 | BO13: 61.470294 | BP13: 48.889179 | BQ13: 96.110652 | BR13: 97.421985 | BS13: n/a | BT13: 68.606875 | BU13: 78.688625 | BV13: 89.6875 | BW13: 74.327754 | BX13: 100 | BY13: 84.861054 | BZ13: 97.101143 | CA13: 99.885735 | CB13: 65.853651 | CC13: n/a | CD13: 88.758458 | CE13: 82.710986 | CF13: 69.040548 | CG13: 17.754196 | CH13: 78.038427 | CI13: 79.947917 | CJ13: 78.061224 | CK13: 83.75514 | CL13: 100 | CM13: 59.980755 | CN13: 100 | CO13: 86.437029 | CP13: 85.399809 | CQ13: 10 | CR13: 9 | CS13: 41 | CT13: 28 | CU13: 27 | CV13: n/a | CW13: 17 | CX13: 7 | CY13: 44 | CZ13: 16 | DA13: 25 | DB13: 7 | DC13: 4 | DD13: 21 | DE13: 22 | DF13: 41 | DG13: 10 | DH13: n/a | DI13: 8 | DJ13: 4 | DK13: 34 | DL13: 5 | DM13: 3 | DN13: 12 | DO13: 9 | DP13: 26 | DQ13: 9 | DR13: 9 | DS13: 33 | DT13: n/a | DU13: 22 | DV13: 16 | DW13: 19 | DX13: 21 | DY13: 1 | DZ13: 21 | EA13: 4 | EB13: 2 | EC13: 50 | ED13: n/a | EE13: 9 | EF13: 6 | EG13: 24 | EH13: 52 | EI13: 22 | EJ13: 46 | EK13: 37 | EL13: 26 | EM13: 1 | EN13: 23 | EO13: 1 | EP13: 24 | EQ13: 26
A14: United Kingdom | B14: GBR | C14: Europe | D14: High-income | E14: 63759.051 | F14: 68683000 | G14: 73.851632 | H14: GB | I14: 8 | J14: 67.741272 | K14: 67.973041 | L14: 84.618739 | M14: 75.073475 | N14: 7 | O14: 5 | P14: 13 | Q14: 11 | R14: 83.053023 | S14: 64.277772 | T14: 55.893022 | U14: 58.706111 | V14: 71.552575 | W14: 73.660437 | X14: 87.948118 | Y14: 78.32928 | Z14: 87.57882 | AA14: 58.294252 | AB14: 79.882022 | AC14: 87.044151 | AD14: 11 | AE14: 5 | AF14: 17 | AG14: 33 | AH14: 3 | AI14: 3 | AJ14: 14 | AK14: 24 | AL14: 6 | AM14: 13 | AN14: 20 | AO14: 6 | AP14: 81.871537 | AQ14: 100 | AR14: 45.011122 | AS14: 99.473684 | AT14: 88.90877 | AU14: n/a | AV14: 55.610855 | AW14: 68.223533 | AX14: 72.937412 | AY14: 60.339289 | AZ14: 84.700879 | BA14: 82.25 | BB14: 12.603992 | BC14: 44.017215 | BD14: 42.255254 | BE14: 72.004103 | BF14: 84.227378 | BG14: n/a | BH14: 36.337707 | BI14: 83.084314 | BJ14: 70.071615 | BK14: 69.977142 | BL14: 63.07723 | BM14: 94.404543 | BN14: 71.310211 | BO14: 84.878502 | BP14: 44.048492 | BQ14: 89.677605 | BR14: 100 | BS14: n/a | BT14: 74.166747 | BU14: 80.680378 | BV14: 91.5625 | BW14: 66.54164 | BX14: 100 | BY14: 52.861883 | BZ14: 97.101143 | CA14: 99.335176 | CB14: 66.300141 | CC14: n/a | CD14: 40.828798 | CE14: 79.474574 | CF14: 79.462626 | CG14: 33.411011 | CH14: 77.479893 | CI14: 81.770833 | CJ14: 78.061224 | CK14: 82.729457 | CL14: 100 | CM14: 64.948432 | CN14: 96.363636 | CO14: 90.958019 | CP14: 91.813035 | CQ14: 34 | CR14: 1 | CS14: 32 | CT14: 29 | CU14: 7 | CV14: n/a | CW14: 20 | CX14: 10 | CY14: 25 | CZ14: 11 | DA14: 16 | DB14: 8 | DC14: 24 | DD14: 17 | DE14: 20 | DF14: 28 | DG14: 12 | DH14: n/a | DI14: 18 | DJ14: 22 | DK14: 7 | DL14: 7 | DM14: 4 | DN14: 7 | DO14: 6 | DP14: 7 | DQ14: 12 | DR14: 16 | DS14: 1 | DT14: n/a | DU14: 18 | DV14: 14 | DW14: 13 | DX14: 29 | DY14: 1 | DZ14: 84 | EA14: 4 | EB14: 5 | EC14: 45 | ED14: n/a | EE14: 20 | EF14: 10 | EG14: 10 | EH14: 27 | EI14: 23 | EJ14: 39 | EK14: 37 | EL14: 27 | EM14: 1 | EN14: 13 | EO14: 15 | EP14: 11 | EQ14: 16
A15: Switzerland | B15: CHE | C15: Europe | D15: High-income | E15: 97659.278 | F15: 8871000 | G15: 73.62597 | H15: CH | I15: 9 | J15: 73.595801 | K15: 59.490276 | L15: 83.761682 | M15: 77.656119 | N15: 2 | O15: 15 | P15: 17 | Q15: 8 | R15: 81.215336 | S15: 70.518444 | T15: 69.053624 | U15: 60.167528 | V15: 51.485538 | W15: 66.817762 | X15: 81.482312 | Y15: 87.872716 | Z15: 81.930019 | AA15: 64.27619 | AB15: 83.009722 | AC15: 85.682445 | AD15: 14 | AE15: 2 | AF15: 5 | AG15: 25 | AH15: 22 | AI15: 12 | AJ15: 30 | AK15: 6 | AL15: 19 | AM15: 10 | AN15: 13 | AO15: 7 | AP15: 94.535941 | AQ15: 96.152722 | AR15: 27.122856 | AS15: 100 | AT15: 69.480497 | AU15: 100 | AV15: 100 | AW15: 100 | AX15: 74.658435 | AY15: 7.415339 | AZ15: 99.624769 | BA15: 89.25 | BB15: 35.852803 | BC15: 51.486924 | BD15: 20.345277 | BE15: 86.077748 | BF15: 81.081086 | BG15: n/a | BH15: 53.166001 | BI15: n/a | BJ15: 53.220826 | BK15: 57.132374 | BL15: 44.103415 | BM15: 80.847199 | BN15: n/a | BO15: 67.665237 | BP15: 51.940851 | BQ15: 96.853928 | BR15: 89.492691 | BS15: n/a | BT15: 58.100318 | BU15: 85.505457 | BV15: 91.5625 | BW15: 89.576835 | BX15: 75 | BY15: 97.718789 | BZ15: 81.157427 | CA15: 100 | CB15: 64.63263 | CC15: n/a | CD15: 90.913043 | CE15: 64.074279 | CF15: 79.461048 | CG15: 22.656391 | CH15: 82.104558 | CI15: 83.984375 | CJ15: 74.489796 | CK15: 91.390673 | CL15: 100 | CM15: 66.438021 | CN15: 82.727273 | CO15: 95.47901 | CP15: 96.170954 | CQ15: 6 | CR15: 15 | CS15: 78 | CT15: 1 | CU15: 74 | CV15: 1 | CW15: 1 | CX15: 1 | CY15: 16 | CZ15: 52 | DA15: 2 | DB15: 4 | DC15: 11 | DD15: 6 | DE15: 52 | DF15: 5 | DG15: 25 | DH15: n/a | DI15: 5 | DJ15: n/a | DK15: 10 | DL15: 20 | DM15: 13 | DN15: 38 | DO15: n/a | DP15: 20 | DQ15: 7 | DR15: 7 | DS15: 63 | DT15: n/a | DU15: 38 | DV15: 9 | DW15: 13 | DX15: 5 | DY15: 72 | DZ15: 4 | EA15: 32 | EB15: 1 | EC15: 57 | ED15: n/a | EE15: 8 | EF15: 36 | EG15: 11 | EH15: 44 | EI15: 13 | EJ15: 33 | EK15: 48 | EL15: 7 | EM15: 1 | EN15: 9 | EO15: 51 | EP15: 4 | EQ15: 6
A16: Republic of Korea | B16: KOR | C16: Asia & Pacific | D16: High-income | E16: 65080.293 | F16: 51749000 | G16: 72.377478 | H16: KR | I16: 10 | J16: 66.070532 | K16: 72.554143 | L16: 82.045568 | M16: 68.839667 | N16: 10 | O16: 2 | P16: 20 | Q16: 22 | R16: 78.426782 | S16: 49.805448 | T16: 69.979368 | U16: 74.311554 | V16: 60.497275 | W16: 82.853601 | X16: 88.497555 | Y16: 71.440574 | Z16: 86.198576 | AA16: 59.474208 | AB16: 68.301939 | AC16: 78.742854 | AD16: 29 | AE16: 17 | AF16: 4 | AG16: 4 | AH16: 10 | AI16: 1 | AJ16: 13 | AK16: 38 | AL16: 7 | AM16: 12 | AN16: 56 | AO16: 31 | AP16: 65.376364 | AQ16: 67.924801 | AR16: 58.281703 | AS16: 99.473684 | AT16: 79.504138 | AU16: 100 | AV16: 57.036315 | AW16: 8.6966176 | AX16: 74.744798 | AY16: 58.744062 | AZ16: 100 | BA16: 59.5 | BB16: 100 | BC16: 20.417471 | BD16: 45.406593 | BE16: 81.714695 | BF16: 98.53453 | BG16: 98.155231 | BH16: 47.74672 | BI16: 69.135948 | BJ16: 74.451266 | BK16: 61.197162 | BL16: 37.204722 | BM16: 100 | BN16: 86.129231 | BO16: 67.159569 | BP16: 78.125605 | BQ16: 75.581933 | BR16: 100 | BS16: n/a | BT16: 89.910732 | BU16: 70.319096 | BV16: 55.9375 | BW16: 64.376384 | BX16: 100 | BY16: 66.569888 | BZ16: 97.101143 | CA16: 92.497878 | CB16: 68.996709 | CC16: n/a | CD16: 100 | CE16: 76.874065 | CF16: 47.878247 | CG16: 13.144521 | CH16: 62.064343 | CI16: 56.510417 | CJ16: 76.785714 | CK16: 95.8764 | CL16: 100 | CM16: 77.020409 | CN16: 82.727273 | CO16: 63.832078 | CP16: 82.783311 | CQ16: 67 | CR16: 59 | CS16: 14 | CT16: 29 | CU16: 25 | CV16: 1 | CW16: 19 | CX16: 48 | CY16: 15 | CZ16: 12 | DA16: 1 | DB16: 34 | DC16: 1 | DD16: 51 | DE16: 16 | DF16: 10 | DG16: 3 | DH16: 22 | DI16: 10 | DJ16: 38 | DK16: 6 | DL16: 14 | DM16: 17 | DN16: 1 | DO16: 2 | DP16: 21 | DQ16: 2 | DR16: 44 | DS16: 1 | DT16: n/a | DU16: 4 | DV16: 26 | DW16: 85 | DX16: 32 | DY16: 1 | DZ16: 55 | EA16: 4 | EB16: 25 | EC16: 23 | ED16: n/a | EE16: 1 | EF16: 14 | EG16: 51 | EH16: 64 | EI16: 56 | EJ16: 95 | EK16: 40 | EL16: 3 | EM16: 1 | EN16: 4 | EO16: 51 | EP16: 93 | EQ16: 29
A17: Japan | B17: JPN | C17: Asia & Pacific | D17: High-income | E17: 54815.317 | F17: 124371000 | G17: 70.21505 | H17: JP | I17: 11 | J17: 61.280022 | K17: 66.869788 | L17: 80.57883 | M17: 72.131561 | N17: 16 | O17: 8 | P17: 24 | Q17: 15 | R17: 83.203018 | S17: 37.757632 | T17: 62.879416 | U17: 72.681001 | V17: 61.777499 | W17: 66.150864 | X17: 80.392665 | Y17: 78.061123 | Z17: 83.2827 | AA17: 63.153139 | AB17: 72.862803 | AC17: 80.37874 | AD17: 10 | AE17: 41 | AF17: 11 | AG17: 6 | AH17: 9 | AI17: 15 | AJ17: 33 | AK17: 25 | AL17: 15 | AM17: 11 | AN17: 42 | AO17: 26 | AP17: 76.767733 | AQ17: 96.34768 | AR17: 66.023586 | AS17: 99.473684 | AT17: 77.402406 | AU17: n/a | AV17: 25.631816 | AW17: 12.703454 | AX17: 70.841509 | AY17: 41.853749 | AZ17: 91.42559 | BA17: 80 | BB17: 54.451485 | BC17: 25.640588 | BD17: 58.074245 | BE17: 79.504381 | BF17: 80.464375 | BG17: n/a | BH17: n/a | BI17: n/a | BJ17: 47.685911 | BK17: 76.502607 | BL17: 61.14398 | BM17: 93.111247 | BN17: n/a | BO17: 51.1529 | BP17: 54.188444 | BQ17: 83.782486 | BR17: 97.084106 | BS17: n/a | BT17: 60.311403 | BU17: 78.997702 | BV17: 52.1875 | BW17: 72.82842 | BX17: 100 | BY17: 86.291995 | BZ17: 98.550571 | CA17: 95.631653 | CB17: 55.665876 | CC17: n/a | CD17: 100 | CE17: 83.5502 | CF17: 60.772258 | CG17: 8.2900989 | CH17: 64.499553 | CI17: 65.364583 | CJ17: 78.316327 | CK17: 99.132217 | CL17: 100 | CM17: 80.818748 | CN17: 69.090909 | CO17: 78.256189 | CP17: 86.698226 | CQ17: 45 | CR17: 13 | CS17: 8 | CT17: 29 | CU17: 31 | CV17: n/a | CW17: 38 | CX17: 41 | CY17: 32 | CZ17: 18 | DA17: 10 | DB17: 9 | DC17: 5 | DD17: 36 | DE17: 7 | DF17: 14 | DG17: 27 | DH17: n/a | DI17: n/a | DJ17: n/a | DK17: 12 | DL17: 4 | DM17: 5 | DN17: 9 | DO17: n/a | DP17: 34 | DQ17: 5 | DR17: 29 | DS17: 34 | DT17: n/a | DU17: 33 | DV17: 15 | DW17: 94 | DX17: 26 | DY17: 1 | DZ17: 19 | EA17: 2 | EB17: 19 | EC17: 84 | ED17: n/a | EE17: 1 | EF17: 5 | EG17: 35 | EH17: 80 | EI17: 53 | EJ17: 79 | EK17: 36 | EL17: 2 | EM17: 1 | EN17: 3 | EO17: 91 | EP17: 54 | EQ17: 22
A18: Canada | B18: CAN | C18: The Americas | D18: High-income | E18: 65500.245 | F18: 39299000 | G18: 70.10526 | H18: CA | I18: 12 | J18: 65.571027 | K18: 61.370767 | L18: 82.960557 | M18: 70.51869 | N18: 11 | O18: 12 | P18: 18 | Q18: 19 | R18: 77.864503 | S18: 59.893971 | T18: 58.954606 | U18: 56.499143 | V18: 62.553294 | W18: 65.059865 | X18: 85.946602 | Y18: 78.577344 | Z18: 84.357725 | AA18: 53.225127 | AB18: 79.091585 | AC18: 79.239359 | AD18: 30 | AE18: 7 | AF18: 14 | AG18: 40 | AH18: 7 | AI18: 16 | AJ18: 18 | AK18: 23 | AL18: 10 | AM18: 18 | AN18: 24 | AO18: 28 | AP18: 75.557289 | AQ18: 94.685057 | AR18: 44.031639 | AS18: 98.421053 | AT18: 76.627479 | AU18: n/a | AV18: 69.56653 | AW18: 61.66948 | AX18: 69.682584 | AY18: 38.657289 | AZ18: 88.540728 | BA18: 68.25 | BB18: 29.367002 | BC18: 49.660694 | BD18: 25.263579 | BE18: 76.833061 | BF18: 83.968384 | BG18: n/a | BH18: 39.931546 | BI18: 92.870881 | BJ18: 34.923435 | BK18: 68.141081 | BL18: 54.277778 | BM18: 82.574801 | BN18: 70.116231 | BO18: 79.390744 | BP18: 28.157684 | BQ18: 85.29172 | BR18: 91.803402 | BS18: n/a | BT18: 80.744684 | BU18: 83.386633 | BV18: 76.5625 | BW18: 79.05953 | BX18: 100 | BY18: 53.878059 | BZ18: 91.303428 | CA18: 95.813159 | CB18: 65.956589 | CC18: n/a | CD18: 48.468305 | CE18: 74.659727 | CF18: 72.916673 | CG18: 16.855802 | CH18: 79.155496 | CI18: 74.088542 | CJ18: 81.377551 | CK18: 86.683885 | CL18: 100 | CM18: 69.922294 | CN18: 100 | CO18: 48.977395 | CP18: 96.115497 | CQ18: 49 | CR18: 20 | CS18: 34 | CT18: 48 | CU18: 37 | CV18: n/a | CW18: 11 | CX18: 12 | CY18: 42 | CZ18: 20 | DA18: 12 | DB18: 20 | DC18: 14 | DD18: 7 | DE18: 42 | DF18: 19 | DG18: 13 | DH18: n/a | DI18: 13 | DJ18: 7 | DK18: 19 | DL18: 8 | DM18: 7 | DN18: 34 | DO18: 10 | DP18: 12 | DQ18: 22 | DR18: 26 | DS18: 55 | DT18: n/a | DU18: 14 | DV18: 11 | DW18: 54 | DX18: 16 | DY18: 1 | DZ18: 82 | EA18: 15 | EB18: 17 | EC18: 49 | ED18: n/a | EE18: 15 | EF18: 16 | EG18: 19 | EH18: 54 | EI18: 18 | EJ18: 59 | EK18: 29 | EL18: 23 | EM18: 1 | EN18: 7 | EO18: 1 | EP18: 110 | EQ18: 7
A19: Estonia | B19: EST | C19: Europe | D19: High-income | E19: 49087.453 | F19: 1367000 | G19: 69.947892 | H19: EE | I19: 13 | J19: 54.15136 | K19: 66.909067 | L19: 88.053136 | M19: 70.678007 | N19: 32 | O19: 7 | P19: 5 | Q19: 17 | R19: 76.656223 | S19: 48.103461 | T19: 37.694395 | U19: 62.614978 | V19: 70.204352 | W19: 67.907873 | X19: 89.428773 | Y19: 86.896617 | Z19: 87.834017 | AA19: 50.652158 | AB19: 78.501664 | AC19: 82.880199 | AD19: 37 | AE19: 18 | AF19: 52 | AG19: 21 | AH19: 4 | AI19: 9 | AJ19: 10 | AK19: 10 | AL19: 3 | AM19: 21 | AN19: 25 | AO19: 19 | AP19: 90.136042 | AQ19: 90.567371 | AR19: 17.868109 | AS19: 100 | AT19: 61.365817 | AU19: 100 | AV19: 69.613876 | AW19: 37.656574 | AX19: 83.459747 | AY19: 1.6836445 | AZ19: 76.827699 | BA19: 58.75 | BB19: 6.1255307 | BC19: 9.0743527 | BD19: 12.176424 | BE19: 67.530013 | BF19: 80.108916 | BG19: 99.808308 | BH19: 53.451226 | BI19: 76.215847 | BJ19: 100 | BK19: 34.397209 | BL19: n/a | BM19: 99.440575 | BN19: 100 | BO19: 43.276483 | BP19: 28.914434 | BQ19: 95.387273 | BR19: 94.037136 | BS19: n/a | BT19: 78.861909 | BU19: 78.004665 | BV19: 82.1875 | BW19: 81.487104 | BX19: 100 | BY19: 92.803816 | BZ19: 95.651714 | CA19: 97.162476 | CB19: 70.687862 | CC19: n/a | CD19: 10.768904 | CE19: 39.029899 | CF19: 83.66384 | CG19: 69.145987 | CH19: 70.531725 | CI19: 85.677083 | CJ19: 82.397959 | CK19: 76.194409 | CL19: 97.777778 | CM19: 73.743197 | CN19: 96.363636 | CO19: 73.412271 | CP19: 78.225606 | CQ19: 11 | CR19: 28 | CS19: 99 | CT19: 1 | CU19: 112 | CV19: 1 | CW19: 10 | CX19: 24 | CY19: 5 | CZ19: 87 | DA19: 30 | DB19: 35 | DC19: 36 | DD19: 85 | DE19: 72 | DF19: 35 | DG19: 28 | DH19: 7 | DI19: 4 | DJ19: 34 | DK19: 1 | DL19: 94 | DM19: n/a | DN19: 3 | DO19: 1 | DP19: 47 | DQ19: 20 | DR19: 10 | DS19: 46 | DT19: n/a | DU19: 15 | DV19: 17 | DW19: 39 | DX19: 11 | DY19: 1 | DZ19: 8 | EA19: 7 | EB19: 11 | EC19: 12 | ED19: n/a | EE19: 30 | EF19: 104 | EG19: 5 | EH19: 6 | EI19: 36 | EJ19: 31 | EK19: 27 | EL19: 35 | EM19: 42 | EN19: 6 | EO19: 15 | EP19: 74 | EQ19: 35
A20: Norway | B20: NOR | C20: Europe | D20: High-income | E20: 106694.12 | F20: 5519000 | G20: 69.696212 | H20: NO | I20: 14 | J20: 59.943008 | K20: 54.943257 | L20: 89.660562 | M20: 74.238022 | N20: 18 | O20: 23 | P20: 2 | Q20: 12 | R20: 79.805097 | S20: 54.361598 | T20: 45.662329 | U20: 49.330737 | V20: 45.953285 | W20: 69.54575 | X20: 93.599346 | Y20: 91.831811 | Z20: 83.55053 | AA20: 46.435169 | AB20: 91.720607 | AC20: 84.558288 | AD20: 20 | AE20: 11 | AF20: 34 | AG20: 72 | AH20: 29 | AI20: 7 | AJ20: 4 | AK20: 2 | AL20: 13 | AM20: 27 | AN20: 3 | AO20: 14 | AP20: 84.568517 | AQ20: 97.608819 | AR20: 29.134186 | AS20: 99.473684 | AT20: 68.045377 | AU20: 100 | AV20: 80.70866 | AW20: 61.695166 | AX20: 70.98308 | AY20: 4.0594889 | AZ20: n/a | BA20: 73.5 | BB20: 15.584747 | BC20: 47.902239 | BD20: 10.562807 | BE20: 78.698401 | BF20: 83.304182 | BG20: n/a | BH20: 24.757558 | BI20: 82.431376 | BJ20: 17.865062 | BK20: 52.302026 | BL20: 31.214677 | BM20: 89.379339 | BN20: n/a | BO20: 90.119183 | BP20: 29.138727 | BQ20: 84.381419 | BR20: 96.416618 | BS20: n/a | BT20: 100 | BU20: 82.205797 | BV20: 93.4375 | BW20: n/a | BX20: 100 | BY20: 91.683949 | BZ20: 85.505713 | CA20: 97.219415 | CB20: 67.926462 | CC20: n/a | CD20: 28.355438 | CE20: 60.340838 | CF20: 80.58781 | CG20: 16.45659 | CH20: 89.410188 | CI20: 93.489583 | CJ20: 93.112245 | CK20: 91.411857 | CL20: 100 | CM20: 56.690343 | CN20: 95.454545 | CO20: 86.544672 | CP20: 99.087184 | CQ20: 27 | CR20: 11 | CS20: 72 | CT20: 29 | CU20: 83 | CV20: 1 | CW20: 6 | CX20: 11 | CY20: 31 | CZ20: 70 | DA20: n/a | DB20: 16 | DC20: 23 | DD20: 11 | DE20: 74 | DF20: 16 | DG20: 16 | DH20: n/a | DI20: 29 | DJ20: 23 | DK20: 31 | DL20: 27 | DM20: 23 | DN20: 18 | DO20: n/a | DP20: 5 | DQ20: 18 | DR20: 28 | DS20: 37 | DT20: n/a | DU20: 1 | DV20: 13 | DW20: 10 | DX20: n/a | DY20: 1 | DZ20: 11 | EA20: 22 | EB20: 10 | EC20: 31 | ED20: n/a | EE20: 22 | EF20: 47 | EG20: 8 | EH20: 55 | EI20: 7 | EJ20: 9 | EK20: 8 | EL20: 6 | EM20: 1 | EN20: 33 | EO20: 20 | EP20: 23 | EQ20: 2
A21: Ireland | B21: IRL | C21: Europe | D21: High-income | E21: 147878.19 | F21: 5197000 | G21: 69.375584 | H21: IE | I21: 15 | J21: 58.125036 | K21: 52.258376 | L21: 84.431486 | M21: 82.68744 | N21: 24 | O21: 30 | P21: 14 | Q21: 2 | R21: 76.257577 | S21: 44.761875 | T21: 53.355655 | U21: 55.357532 | V21: 47.892847 | W21: 53.524747 | X21: 88.6324 | Y21: 79.174995 | Z21: 85.487063 | AA21: 71.433501 | AB21: 84.787498 | AC21: 91.841319 | AD21: 39 | AE21: 28 | AF21: 21 | AG21: 47 | AH21: 27 | AI21: 29 | AJ21: 11 | AK21: 21 | AL21: 8 | AM21: 4 | AN21: 10 | AO21: 1 | AP21: 98.118497 | AQ21: 100 | AR21: 17.984597 | AS21: 99.473684 | AT21: 65.711108 | AU21: n/a | AV21: 65.659883 | AW21: 38.374056 | AX21: 72.131091 | AY21: 2.8824728 | AZ21: 79.090933 | BA21: 70.5 | BB21: 9.8906852 | BC21: 53.941002 | BD21: 4.6540531 | BE21: 87.08806 | BF21: 79.431311 | BG21: n/a | BH21: 50.256703 | BI21: 94.68965 | BJ21: 22.662015 | BK21: 48.878353 | BL21: 25.341372 | BM21: 85.175828 | BN21: 68.282797 | BO21: 35.761545 | BP21: 24.878819 | BQ21: 94.321086 | BR21: 89.052023 | BS21: n/a | BT21: 82.52409 | BU21: 86.005546 | BV21: 98.125 | BW21: 63.071679 | BX21: 100 | BY21: 48.67275 | BZ21: 91.303428 | CA21: 93.082601 | CB21: 72.075159 | CC21: n/a | CD21: 43.220122 | CE21: 62.093036 | CF21: 80.420847 | CG21: 100 | CH21: 81.076854 | CI21: 86.197917 | CJ21: 86.734694 | CK21: 87.440753 | CL21: 100 | CM21: 68.874514 | CN21: 100 | CO21: 100 | CP21: 96.981526 | CQ21: 2 | CR21: 1 | CS21: 98 | CT21: 29 | CU21: 98 | CV21: n/a | CW21: 14 | CX21: 23 | CY21: 26 | CZ21: 77 | DA21: 23 | DB21: 18 | DC21: 28 | DD21: 3 | DE21: 96 | DF21: 4 | DG21: 32 | DH21: n/a | DI21: 7 | DJ21: 3 | DK21: 27 | DL21: 35 | DM21: 31 | DN21: 29 | DO21: 13 | DP21: 66 | DQ21: 25 | DR21: 11 | DS21: 64 | DT21: n/a | DU21: 12 | DV21: 8 | DW21: 3 | DX21: 35 | DY21: 1 | DZ21: 90 | EA21: 15 | EB21: 24 | EC21: 11 | ED21: n/a | EE21: 18 | EF21: 41 | EG21: 9 | EH21: 1 | EI21: 15 | EJ21: 30 | EK21: 17 | EL21: 17 | EM21: 1 | EN21: 8 | EO21: 1 | EP21: 1 | EQ21: 4
A22: Israel | B22: ISR | C22: Europe | D22: High-income | E22: 55766.414 | F22: 9256000 | G22: 69.259843 | H22: IL | I22: 16 | J22: 54.784515 | K22: 69.53497 | L22: 72.938877 | M22: 79.78101 | N22: 31 | O22: 3 | P22: 38 | Q22: 6 | R22: 74.783033 | S22: 47.401622 | T22: 42.16889 | U22: 70.982716 | V22: 64.989094 | W22: 72.633101 | X22: 75.546625 | Y22: 73.149198 | Z22: 70.120808 | AA22: 85.436256 | AB22: 76.801223 | AC22: 77.105552 | AD22: 44 | AE22: 22 | AF22: 41 | AG22: 7 | AH22: 5 | AI22: 5 | AJ22: 40 | AK22: 35 | AL22: 52 | AM22: 1 | AN22: 27 | AO22: 36 | AP22: 78.106153 | AQ22: 84.947446 | AR22: 32.117232 | AS22: 94.736842 | AT22: 66.784356 | AU22: 92.006172 | AV22: 79.860081 | AW22: 18.039229 | AX22: 84.762643 | AY22: 6.944534 | AZ22: n/a | BA22: 96.25 | BB22: 11.898942 | BC22: 18.357729 | BD22: 20.545402 | BE22: 87.707869 | BF22: 75.677593 | BG22: n/a | BH22: 100 | BI22: 76.956654 | BJ22: 100 | BK22: 49.008345 | BL22: 33.991377 | BM22: 82.449682 | BN22: 46.438697 | BO22: 61.644024 | BP22: 100 | BQ22: 75.881497 | BR22: 92.500499 | BS22: n/a | BT22: 58.257878 | BU22: 70.300947 | BV22: 40.9375 | BW22: 91.639438 | BX22: 75 | BY22: 87.868105 | BZ22: 68.112569 | CA22: 88.243195 | CB22: 64.334112 | CC22: 59.793355 | CD22: 96.566841 | CE22: 59.741927 | CF22: n/a | CG22: 100 | CH22: 88.784629 | CI22: 64.583333 | CJ22: 64.030612 | CK22: 90.040798 | CL22: 100 | CM22: 53.003625 | CN22: 71.818182 | CO22: 86.329386 | CP22: 94.542028 | CQ22: 40 | CR22: 38 | CS22: 62 | CT22: 63 | CU22: 92 | CV22: 47 | CW22: 8 | CX22: 36 | CY22: 2 | CZ22: 56 | DA22: n/a | DB22: 2 | DC22: 27 | DD22: 59 | DE22: 50 | DF22: 3 | DG22: 46 | DH22: n/a | DI22: 1 | DJ22: 32 | DK22: 1 | DL22: 34 | DM22: 21 | DN22: 35 | DO22: 36 | DP22: 25 | DQ22: 1 | DR22: 42 | DS22: 51 | DT22: n/a | DU22: 37 | DV22: 27 | DW22: 111 | DX22: 4 | DY22: 72 | DZ22: 16 | EA22: 53 | EB22: 34 | EC22: 60 | ED22: 46 | EE22: 7 | EF22: 49 | EG22: n/a | EH22: 1 | EI22: 8 | EJ22: 81 | EK22: 74 | EL22: 10 | EM22: 1 | EN22: 36 | EO22: 81 | EP22: 25 | EQ22: 10
A23: Australia | B23: AUS | C23: Asia & Pacific | D23: High-income | E23: 71430.886 | F23: 26451000 | G23: 69.016043 | H23: AU | I23: 17 | J23: 59.697319 | K23: 59.509817 | L23: 86.284808 | M23: 70.572228 | N23: 19 | O23: 14 | P23: 10 | Q23: 18 | R23: 80.278127 | S23: 54.302876 | T23: 44.510954 | U23: 55.463571 | V23: 56.394776 | W23: 66.671106 | X23: 90.315861 | Y23: 86.116593 | Z23: 82.421969 | AA23: 46.71379 | AB23: 81.599452 | AC23: 83.40344 | AD23: 18 | AE23: 12 | AF23: 39 | AG23: 46 | AH23: 15 | AI23: 13 | AJ23: 9 | AK23: 11 | AL23: 18 | AM23: 26 | AN23: 16 | AO23: 17 | AP23: 73.519732 | AQ23: 100 | AR23: 36.021684 | AS23: 98.421053 | AT23: 73.706295 | AU23: 100 | AV23: 47.251227 | AW23: 68.822132 | AX23: 70.485689 | AY23: 30.652455 | AZ23: 85.729486 | BA23: 65.75 | BB23: 7.8740039 | BC23: 18.690327 | BD23: 32.077735 | BE23: 76.211613 | BF23: 81.220384 | BG23: n/a | BH23: 32.344552 | BI23: 80.253173 | BJ23: 31.668589 | BK23: 63.815731 | BL23: 49.84161 | BM23: 90.638948 | BN23: 69.740714 | BO23: 80.164267 | BP23: 26.140494 | BQ23: 86.169142 | BR23: 95.485959 | BS23: n/a | BT23: 89.292482 | BU23: 90.831335 | BV23: 89.6875 | BW23: 73.954632 | BX23: 100 | BY23: 76.109498 | BZ23: 85.505713 | CA23: 95.763206 | CB23: 65.996988 | CC23: n/a | CD23: 21.826338 | CE23: 71.72655 | CF23: 82.795886 | CG23: 10.506388 | CH23: 82.975871 | CI23: 79.817708 | CJ23: 74.489796 | CK23: 89.519759 | CL23: 100 | CM23: 66.202143 | CN23: 95.454545 | CO23: 74.058127 | CP23: 95.797889 | CQ23: 54 | CR23: 1 | CS23: 50 | CT23: 48 | CU23: 51 | CV23: 1 | CW23: 23 | CX23: 9 | CY23: 35 | CZ23: 27 | DA23: 14 | DB23: 24 | DC23: 31 | DD23: 58 | DE23: 31 | DF23: 21 | DG23: 23 | DH23: n/a | DI23: 21 | DJ23: 27 | DK23: 20 | DL23: 11 | DM23: 8 | DN23: 14 | DO23: 11 | DP23: 10 | DQ23: 24 | DR23: 23 | DS23: 45 | DT23: n/a | DU23: 5 | DV23: 2 | DW23: 19 | DX23: 22 | DY23: 1 | DZ23: 39 | EA23: 22 | EB23: 18 | EC23: 48 | ED23: n/a | EE23: 24 | EF23: 19 | EG23: 6 | EH23: 73 | EI23: 11 | EJ23: 48 | EK23: 48 | EL23: 13 | EM23: 1 | EN23: 10 | EO23: 20 | EP23: 70 | EQ23: 9
A24: Luxembourg | B24: LUX | C24: Europe | D24: High-income | E24: 152394.65 | F24: 665000 | G24: 68.365145 | H24: LU | I24: 18 | J24: 62.818431 | K24: 48.733396 | L24: 86.813056 | M24: 75.095695 | N24: 14 | O24: 35 | P24: 7 | Q24: 10 | R24: 79.14333 | S24: 50.397685 | T24: 58.91428 | U24: 45.507449 | V24: 52.88959 | W24: 47.803149 | X24: 93.426632 | Y24: 92.512223 | Z24: 74.500314 | AA24: 51.842536 | AB24: 86.35926 | AC24: 87.085289 | AD24: 23 | AE24: 16 | AF24: 15 | AG24: 87 | AH24: 20 | AI24: 41 | AJ24: 5 | AK24: 1 | AL24: 39 | AM24: 20 | AN24: 8 | AO24: 5 | AP24: 96.547119 | AQ24: 91.999717 | AR24: 6.2822742 | AS24: 100 | AT24: 80.030869 | AU24: 100 | AV24: 48.209135 | AW24: 82.586215 | AX24: 70.267034 | AY24: 0.52835467 | AZ24: 85.287652 | BA24: 79.5 | BB24: n/a | BC24: 11.955186 | BD24: 1.7231155 | BE24: 60.112203 | BF24: 50.770632 | BG24: n/a | BH24: 69.423845 | BI24: 83.339851 | BJ24: 39.911505 | BK24: 35.417415 | BL24: n/a | BM24: 70.589863 | BN24: n/a | BO24: 56.586586 | BP24: 16.232998 | BQ24: 88.395347 | BR24: 98.457916 | BS24: n/a | BT24: n/a | BU24: 90.502452 | BV24: 80.3125 | BW24: 100 | BX24: 100 | BY24: 91.746163 | BZ24: 60.865425 | CA24: 96.368711 | CB24: 66.266804 | CC24: n/a | CD24: 62.369428 | CE24: 43.489017 | CF24: 76.132522 | CG24: 25.379177 | CH24: 86.282395 | CI24: 89.453125 | CJ24: 75 | CK24: 91.684518 | CL24: 100 | CM24: 57.652894 | CN24: 100 | CO24: 93.4338 | CP24: 94.508926 | CQ24: 5 | CR24: 25 | CS24: 116 | CT24: 1 | CU24: 22 | CV24: 1 | CW24: 22 | CX24: 5 | CY24: 39 | CZ24: 106 | DA24: 15 | DB24: 10 | DC24: n/a | DD24: 79 | DE24: 115 | DF24: 43 | DG24: 91 | DH24: n/a | DI24: 3 | DJ24: 20 | DK24: 15 | DL24: 90 | DM24: n/a | DN24: 64 | DO24: n/a | DP24: 30 | DQ24: 40 | DR24: 17 | DS24: 26 | DT24: n/a | DU24: n/a | DV24: 3 | DW24: 46 | DX24: 1 | DY24: 1 | DZ24: 10 | EA24: 67 | EB24: 13 | EC24: 46 | ED24: n/a | EE24: 13 | EF24: 91 | EG24: 13 | EH24: 38 | EI24: 9 | EJ24: 17 | EK24: 46 | EL24: 5 | EM24: 1 | EN24: 32 | EO24: 1 | EP24: 6 | EQ24: 11
A25: France | B25: FRA | C25: Europe | D25: High-income | E25: 66060.528 | F25: 66439000 | G25: 68.162698 | H25: FR | I25: 19 | J25: 61.636419 | K25: 59.169449 | L25: 81.987441 | M25: 69.857482 | N25: 15 | O25: 16 | P25: 21 | Q25: 21 | R25: 83.399497 | S25: 46.747651 | T25: 54.76211 | U25: 57.652891 | V25: 53.644704 | W25: 66.210752 | X25: 82.466729 | Y25: 83.053526 | Z25: 80.442067 | AA25: 50.612503 | AB25: 74.364135 | AC25: 84.595809 | AD25: 9 | AE25: 24 | AF25: 18 | AG25: 37 | AH25: 19 | AI25: 14 | AJ25: 25 | AK25: 15 | AL25: 22 | AM25: 22 | AN25: 38 | AO25: 13 | AP25: 88.498653 | AQ25: 98.484296 | AR25: 57.966073 | AS25: 94.736842 | AT25: 77.311622 | AU25: n/a | AV25: 48.570921 | AW25: 37.618984 | AX25: 73.931841 | AY25: 26.86886 | AZ25: 79.78411 | BA25: 67.25 | BB25: 23.815469 | BC25: 48.198861 | BD25: 47.693072 | BE25: 70.889511 | BF25: 79.855565 | BG25: n/a | BH25: 32.173417 | BI25: 66.540111 | BJ25: 18.513209 | BK25: 71.876588 | BL25: 57.648907 | BM25: 81.23218 | BN25: 73.433156 | BO25: 75.771958 | BP25: 34.405715 | BQ25: 88.245895 | BR25: 98.771688 | BS25: n/a | BT25: 60.382605 | BU25: 71.094415 | BV25: 91.5625 | BW25: 81.872431 | BX25: 100 | BY25: 70.738283 | BZ25: 79.707998 | CA25: 96.123553 | CB25: 65.494651 | CC25: n/a | CD25: 43.253469 | CE25: 79.644596 | CF25: 60.797823 | CG25: 18.754122 | CH25: 74.463807 | CI25: 64.973958 | CJ25: 79.591837 | CK25: 87.717444 | CL25: 100 | CM25: 58.32149 | CN25: 100 | CO25: 84.068891 | CP25: 91.985714 | CQ25: 14 | CR25: 8 | CS25: 15 | CT25: 63 | CU25: 32 | CV25: n/a | CW25: 21 | CX25: 25 | CY25: 20 | CZ25: 31 | DA25: 22 | DB25: 22 | DC25: 19 | DD25: 9 | DE25: 11 | DF25: 30 | DG25: 29 | DH25: n/a | DI25: 22 | DJ25: 44 | DK25: 30 | DL25: 6 | DM25: 6 | DN25: 37 | DO25: 4 | DP25: 16 | DQ25: 16 | DR25: 18 | DS25: 23 | DT25: n/a | DU25: 32 | DV25: 25 | DW25: 13 | DX25: 10 | DY25: 1 | DZ25: 46 | EA25: 33 | EB25: 15 | EC25: 53 | ED25: n/a | EE25: 17 | EF25: 9 | EG25: 34 | EH25: 50 | EI25: 30 | EJ25: 80 | EK25: 33 | EL25: 15 | EM25: 1 | EN25: 26 | EO25: 1 | EP25: 37 | EQ25: 14
A26: Belgium | B26: BEL | C26: Europe | D26: High-income | E26: 75882.366 | F26: 11713000 | G26: 67.154411 | H26: BE | I26: 20 | J26: 59.574776 | K26: 55.860504 | L26: 81.033435 | M26: 72.148928 | N26: 21 | O26: 20 | P26: 23 | Q26: 14 | R26: 78.910556 | S26: 45.185474 | T26: 54.628299 | U26: 47.472378 | V26: 55.812665 | W26: 64.296469 | X26: 86.512956 | Y26: 87.409801 | Z26: 69.177548 | AA26: 47.964792 | AB26: 85.282053 | AC26: 83.199939 | AD26: 24 | AE26: 27 | AF26: 19 | AG26: 79 | AH26: 16 | AI26: 17 | AJ26: 17 | AK26: 9 | AL26: 53 | AM26: 23 | AN26: 9 | AO26: 18 | AP26: 85.700993 | AQ26: 95.74159 | AR26: 18.616039 | AS26: 100 | AT26: 73.404716 | AU26: 100 | AV26: 66.094173 | AW26: 47.188818 | AX26: 61.366509 | AY26: 6.0923961 | AZ26: 79.979893 | BA26: 67.5 | BB26: 28.263838 | BC26: 42.769466 | BD26: 13.356585 | BE26: 69.069291 | BF26: 81.622222 | BG26: n/a | BH26: 25.841415 | BI26: 93.439246 | BJ26: 37.21605 | BK26: 56.58834 | BL26: 36.007025 | BM26: 66.607716 | BN26: n/a | BO26: 73.953303 | BP26: 52.328386 | BQ26: 84.650705 | BR26: 96.17891 | BS26: n/a | BT26: 78.709253 | BU26: 71.462762 | BV26: 94.375 | BW26: 82.14032 | BX26: 100 | BY26: 89.070925 | BZ26: 47.820567 | CA26: 94.320324 | CB26: 65.391754 | CC26: n/a | CD26: 26.890069 | CE26: 64.215868 | CF26: 73.351282 | CG26: 27.40195 | CH26: 81.546023 | CI26: 84.765625 | CJ26: 92.346939 | CK26: 86.722082 | CL26: 100 | CM26: 61.618671 | CN26: 100 | CO26: 78.68676 | CP26: 84.988654 | CQ26: 25 | CR26: 18 | CS26: 95 | CT26: 1 | CU26: 53 | CV26: 1 | CW26: 13 | CX26: 18 | CY26: 75 | CZ26: 62 | DA26: 21 | DB26: 21 | DC26: 16 | DD26: 18 | DE26: 68 | DF26: 32 | DG26: 20 | DH26: n/a | DI26: 27 | DJ26: 5 | DK26: 16 | DL26: 22 | DM26: 19 | DN26: 70 | DO26: n/a | DP26: 17 | DQ26: 6 | DR26: 27 | DS26: 40 | DT26: n/a | DU26: 16 | DV26: 24 | DW26: 5 | DX26: 8 | DY26: 1 | DZ26: 14 | EA26: 83 | EB26: 21 | EC26: 54 | ED26: n/a | EE26: 23 | EF26: 35 | EG26: 17 | EH26: 34 | EI26: 14 | EJ26: 32 | EK26: 9 | EL26: 21 | EM26: 1 | EN26: 20 | EO26: 1 | EP26: 51 | EQ26: 28
A27: Austria | B27: AUT | C27: Europe | D27: High-income | E27: 74852.289 | F27: 9130000 | G27: 67.130278 | H27: AT | I27: 21 | J27: 59.679771 | K27: 52.356938 | L27: 82.742875 | M27: 73.741527 | N27: 20 | O27: 29 | P27: 19 | Q27: 13 | R27: 76.860949 | S27: 47.801781 | T27: 54.376584 | U27: 53.231898 | V27: 48.322054 | W27: 55.516861 | X27: 82.393427 | Y27: 85.596345 | Z27: 80.238854 | AA27: 56.21708 | AB27: 80.970882 | AC27: 84.03662 | AD27: 35 | AE27: 21 | AF27: 20 | AG27: 56 | AH27: 26 | AI27: 26 | AJ27: 27 | AK27: 13 | AL27: 23 | AM27: 15 | AN27: 19 | AO27: 15 | AP27: 92.572472 | AQ27: 96.073055 | AR27: 15.99217 | AS27: 89.473684 | AT27: 67.054312 | AU27: 100 | AV27: 58.287963 | AW27: 57.989416 | AX27: 68.545092 | AY27: 6.3846542 | AZ27: 74.896213 | BA27: 64.25 | BB27: 33.209857 | BC27: 45.150264 | BD27: 31.130881 | BE27: 65.03829 | BF27: 83.957509 | BG27: n/a | BH27: 32.800913 | BI27: 91.508851 | BJ27: 24.459413 | BK27: 47.30233 | BL27: 30.017624 | BM27: 80.545229 | BN27: n/a | BO27: 34.164933 | BP27: 51.840421 | BQ27: 86.67118 | BR27: 86.955217 | BS27: n/a | BT27: 73.553884 | BU27: 76.29614 | BV27: 85.9375 | BW27: 80.700388 | BX27: 100 | BY27: 85.047698 | BZ27: 76.809141 | CA27: 97.873832 | CB27: 66.033588 | CC27: n/a | CD27: 60.709153 | CE27: 61.744305 | CF27: 74.887087 | CG27: 27.527774 | CH27: 79.311886 | CI27: 79.6875 | CJ27: 81.122449 | CK27: 86.704071 | CL27: 100 | CM27: 61.622324 | CN27: 95.454545 | CO27: 85.791173 | CP27: 86.556874 | CQ27: 8 | CR27: 16 | CS27: 101 | CT27: 83 | CU27: 89 | CV27: 1 | CW27: 18 | CX27: 13 | CY27: 49 | CZ27: 59 | DA27: 34 | DB27: 26 | DC27: 13 | DD27: 16 | DE27: 35 | DF27: 37 | DG27: 14 | DH27: n/a | DI27: 20 | DJ27: 13 | DK27: 25 | DL27: 43 | DM27: 25 | DN27: 39 | DO27: n/a | DP27: 70 | DQ27: 8 | DR27: 22 | DS27: 66 | DT27: n/a | DU27: 19 | DV27: 19 | DW27: 30 | DX27: 13 | DY27: 1 | DZ27: 20 | EA27: 37 | EB27: 8 | EC27: 47 | ED27: n/a | EE27: 14 | EF27: 43 | EG27: 14 | EH27: 33 | EI27: 17 | EJ27: 49 | EK27: 31 | EL27: 22 | EM27: 1 | EN27: 19 | EO27: 20 | EP27: 29 | EQ27: 23
A28: Iceland | B28: ISL | C28: Europe | D28: High-income | E28: 80466.384 | F28: 388000 | G28: 66.095835 | H28: IS | I28: 22 | J28: 59.538723 | K28: 59.666607 | L28: 85.357302 | M28: 59.820707 | N28: 22 | O28: 13 | P28: 12 | Q28: 41 | R28: 72.998869 | S28: 60.250265 | T28: 45.367035 | U28: 44.316235 | V28: 74.607125 | W28: 60.076461 | X28: 91.014608 | Y28: 77.410426 | Z28: 87.646873 | AA28: 23.836784 | AB28: 93.991417 | AC28: 61.633919 | AD28: 52 | AE28: 6 | AF28: 36 | AG28: 92 | AH28: 2 | AI28: 23 | AJ28: 8 | AK28: 28 | AL28: 4 | AM28: 99 | AN28: 2 | AO28: 71 | AP28: 83.492414 | AQ28: 97.441407 | AR28: 9.1127436 | AS28: 97.368421 | AT28: 77.579358 | AU28: n/a | AV28: 80.408062 | AW28: 100 | AX28: 60.435922 | AY28: 0.1570754 | AZ28: 82.241747 | BA28: 65.75 | BB28: 12.073924 | BC28: 21.40247 | BD28: 2.8362708 | BE28: 82.479458 | BF28: 78.201349 | BG28: n/a | BH28: 13.747861 | BI28: 92.643535 | BJ28: 100 | BK28: 31.177839 | BL28: n/a | BM28: 88.87766 | BN28: n/a | BO28: 49.626131 | BP28: 41.725592 | BQ28: 91.340466 | BR28: 98.589309 | BS28: n/a | BT28: 83.114049 | BU28: 74.371099 | BV28: 85 | BW28: 73.896295 | BX28: 75 | BY28: 78.784737 | BZ28: 95.651714 | CA28: 99.372767 | CB28: 67.916137 | CC28: n/a | CD28: 13.13599 | CE28: 30.752061 | CF28: n/a | CG28: 27.622302 | CH28: 95.062556 | CI28: 94.661458 | CJ28: 92.346939 | CK28: 92.153536 | CL28: 100 | CM28: 45.45925 | CN28: 100 | CO28: 1.0764263 | CP28: 100 | CQ28: 30 | CR28: 12 | CS28: 111 | CT28: 57 | CU28: 29 | CV28: n/a | CW28: 7 | CX28: 1 | CY28: 77 | CZ28: 116 | DA28: 20 | DB28: 24 | DC28: 26 | DD28: 48 | DE28: 109 | DF28: 9 | DG28: 35 | DH28: n/a | DI28: 37 | DJ28: 8 | DK28: 1 | DL28: 106 | DM28: n/a | DN28: 20 | DO28: n/a | DP28: 36 | DQ28: 13 | DR28: 13 | DS28: 24 | DT28: n/a | DU28: 11 | DV28: 22 | DW28: 32 | DX28: 23 | DY28: 72 | DZ28: 29 | EA28: 7 | EB28: 4 | EC28: 35 | ED28: n/a | EE28: 28 | EF28: 123 | EG28: n/a | EH28: 32 | EI28: 3 | EJ28: 7 | EK28: 9 | EL28: 4 | EM28: 1 | EN28: 40 | EO28: 1 | EP28: 125 | EQ28: 1
A29: New Zealand | B29: NZL | C29: Asia & Pacific | D29: High-income | E29: 55781.2 | F29: 5173000 | G29: 65.950218 | H29: NZ | I29: 23 | J29: 56.423895 | K29: 51.894439 | L29: 85.576372 | M29: 69.906167 | N29: 28 | O29: 31 | P29: 11 | Q29: 20 | R29: 74.555645 | S29: 47.989047 | T29: 46.726995 | U29: 47.620839 | V29: 45.26127 | W29: 62.801209 | X29: 82.289629 | Y29: 81.123864 | Z29: 93.315624 | AA29: 44.25728 | AB29: 82.603547 | AC29: 82.857673 | AD29: 46 | AE29: 20 | AF29: 32 | AG29: 77 | AH29: 30 | AI29: 20 | AJ29: 28 | AK29: 17 | AL29: 1 | AM29: 29 | AN29: 14 | AO29: 20 | AP29: 77.71505 | AQ29: 100 | AR29: 32.245479 | AS29: 92.789474 | AT29: 70.028221 | AU29: n/a | AV29: 67.356854 | AW29: 51.210034 | AX29: 68.826455 | AY29: 4.5628434 | AZ29: 92.785832 | BA29: 68.5 | BB29: 6.6694332 | BC29: 18.952713 | BD29: 7.0640463 | BE29: 77.150731 | BF29: 82.937146 | BG29: n/a | BH29: 23.331432 | BI29: 92.643535 | BJ29: 13.916151 | BK29: 48.046125 | BL29: 26.439268 | BM29: 93.419232 | BN29: 62.925964 | BO29: 71.859785 | BP29: 22.999853 | BQ29: 79.153758 | BR29: 79.118525 | BS29: n/a | BT29: 88.596602 | BU29: 90.031118 | BV29: 78.4375 | BW29: 76.15941 | BX29: 100 | BY29: 60.99129 | BZ29: 92.752857 | CA29: 93.878392 | CB29: n/a | CC29: n/a | CD29: 36.312053 | CE29: 53.529368 | CF29: 73.104783 | CG29: 14.082917 | CH29: 82.484361 | CI29: 80.338542 | CJ29: n/a | CK29: 87.37193 | CL29: 100 | CM29: 65.087321 | CN29: 96.363636 | CO29: 74.811625 | CP29: 90.336221 | CQ29: 42 | CR29: 1 | CS29: 60 | CT29: 77 | CU29: 70 | CV29: n/a | CW29: 12 | CX29: 16 | CY29: 45 | CZ29: 68 | DA29: 9 | DB29: 19 | DC29: 35 | DD29: 57 | DE29: 84 | DF29: 17 | DG29: 18 | DH29: n/a | DI29: 30 | DJ29: 8 | DK29: 39 | DL29: 41 | DM29: 29 | DN29: 8 | DO29: 17 | DP29: 18 | DQ29: 30 | DR29: 37 | DS29: 79 | DT29: n/a | DU29: 6 | DV29: 4 | DW29: 49 | DX29: 20 | DY29: 1 | DZ29: 70 | EA29: 12 | EB29: 23 | EC29: n/a | ED29: n/a | EE29: 21 | EF29: 64 | EG29: 18 | EH29: 62 | EI29: 12 | EJ29: 44 | EK29: n/a | EL29: 18 | EM29: 1 | EN29: 12 | EO29: 15 | EP29: 66 | EQ29: 20
A30: China | B30: CHN | C30: Asia & Pacific | D30: Upper middle-income | E30: 29191.097 | F30: 1422585000 | G30: 65.73886 | H30: CN | I30: 24 | J30: 64.374153 | K30: 67.833059 | L30: 66.601562 | M30: 64.146664 | N30: 12 | O30: 6 | P30: 50 | Q30: 30 | R30: 89.232335 | S30: 52.294437 | T30: 51.595687 | U30: 91.616109 | V30: 50.000633 | W30: 61.882436 | X30: 78.078397 | Y30: 46.988269 | Z30: 74.738018 | AA30: 54.157043 | AB30: 67.624324 | AC30: 70.658625 | AD30: 1 | AE30: 15 | AF30: 22 | AG30: 1 | AH30: 25 | AI30: 21 | AJ30: 36 | AK30: 106 | AL30: 38 | AM30: 17 | AN30: 60 | AO30: 48 | AP30: 78.96131 | AQ30: 63.785271 | AR30: 100 | AS30: 100 | AT30: 93.997383 | AU30: 98.650047 | AV30: n/a | AW30: 4.5888745 | AX30: n/a | AY30: 100 | AZ30: n/a | BA30: 59.75 | BB30: 69.201639 | BC30: 25.835422 | BD30: 100 | BE30: n/a | BF30: 79.46371 | BG30: 95.384615 | BH30: n/a | BI30: 21.597879 | BJ30: 24.304299 | BK30: 85.76636 | BL30: 68.333995 | BM30: 91.068442 | BN30: 54.01677 | BO30: n/a | BP30: 40.562095 | BQ30: 58.370839 | BR30: 90.059893 | BS30: n/a | BT30: 85.804459 | BU30: 33.30691 | BV30: 30.625 | BW30: 83.856804 | BX30: 75 | BY30: 12.152634 | BZ30: 92.752857 | CA30: 77.120741 | CB30: 67.167657 | CC30: 61.910818 | CD30: 42.642024 | CE30: 100 | CF30: n/a | CG30: 19.829105 | CH30: 59.450402 | CI30: 67.708333 | CJ30: 68.877551 | CK30: 82.550922 | CL30: 100 | CM30: 100 | CN30: 68.181818 | CO30: 51.560818 | CP30: 25.783731 | CQ30: 38 | CR30: 66 | CS30: 1 | CT30: 1 | CU30: 3 | CV30: 41 | CW30: n/a | CX30: 62 | CY30: n/a | CZ30: 1 | DA30: n/a | DB30: 33 | DC30: 3 | DD30: 33 | DE30: 1 | DF30: n/a | DG30: 31 | DH30: 34 | DI30: n/a | DJ30: 102 | DK30: 26 | DL30: 3 | DM30: 2 | DN30: 11 | DO30: 26 | DP30: n/a | DQ30: 14 | DR30: 68 | DS30: 60 | DT30: n/a | DU30: 10 | DV30: 91 | DW30: 119 | DX30: 7 | DY30: 72 | DZ30: 124 | EA30: 12 | EB30: 55 | EC30: 40 | ED30: 43 | EE30: 19 | EF30: 1 | EG30: n/a | EH30: 49 | EI30: 66 | EJ30: 72 | EK30: 64 | EL30: 28 | EM30: 1 | EN30: 1 | EO30: 93 | EP30: 108 | EQ30: 116
A31: Spain | B31: ESP | C31: Europe | D31: High-income | E31: 56887.928 | F31: 47912000 | G31: 65.424994 | H31: ES | I31: 25 | J31: 58.276973 | K31: 55.534094 | L31: 81.694094 | M31: 66.194815 | N31: 23 | O31: 21 | P31: 22 | Q31: 25 | R31: 84.394847 | S31: 42.103747 | T31: 48.332323 | U31: 59.901449 | V31: 52.563917 | W31: 54.136915 | X31: 83.060563 | Y31: 79.148919 | Z31: 82.8728 | AA31: 40.5318 | AB31: 72.935448 | AC31: 85.117196 | AD31: 6 | AE31: 31 | AF31: 27 | AG31: 26 | AH31: 21 | AI31: 27 | AJ31: 23 | AK31: 22 | AL31: 16 | AM31: 37 | AN31: 41 | AO31: 9 | AP31: 88.628158 | AQ31: 90.889158 | AR31: 56.294279 | AS31: 98.421053 | AT31: 72.136438 | AU31: 100 | AV31: 35.867929 | AW31: 24.90121 | AX31: 70.527621 | AY31: 37.118229 | AZ31: 71.905408 | BA31: 43 | BB31: 22.240075 | BC31: 56.183809 | BD31: 38.771606 | BE31: 51.698074 | BF31: 87.588619 | BG31: 100 | BH31: 21.448945 | BI31: 88.096613 | BJ31: 18.681769 | BK31: 63.232911 | BL31: 40.244376 | BM31: 88.621407 | BN31: 78.3955 | BO31: 26.060215 | BP31: 23.470538 | BQ31: 83.035204 | BR31: 99.688236 | BS31: n/a | BT31: 66.458249 | BU31: 59.589569 | BV31: 83.125 | BW31: 65.203398 | BX31: 100 | BY31: 87.826628 | BZ31: 79.707998 | CA31: 99.399915 | CB31: 69.510487 | CC31: n/a | CD31: 13.43917 | CE31: 74.961004 | CF31: 46.027453 | CG31: 27.699575 | CH31: 71.626452 | CI31: 63.802083 | CJ31: 75.510204 | CK31: 91.245412 | CL31: 100 | CM31: 57.901906 | CN31: 100 | CO31: 86.114101 | CP31: 92.905554 | CQ31: 13 | CR31: 27 | CS31: 16 | CT31: 48 | CU31: 61 | CV31: 1 | CW31: 31 | CX31: 30 | CY31: 34 | CZ31: 21 | DA31: 37 | DB31: 55 | DC31: 21 | DD31: 2 | DE31: 25 | DF31: 63 | DG31: 6 | DH31: 1 | DI31: 33 | DJ31: 16 | DK31: 29 | DL31: 12 | DM31: 14 | DN31: 22 | DO31: 3 | DP31: 85 | DQ31: 28 | DR31: 31 | DS31: 16 | DT31: n/a | DU31: 24 | DV31: 38 | DW31: 34 | DX31: 30 | DY31: 1 | DZ31: 17 | EA31: 33 | EB31: 3 | EC31: 20 | ED31: n/a | EE31: 27 | EF31: 15 | EG31: 54 | EH31: 31 | EI31: 35 | EJ31: 82 | EK31: 42 | EL31: 9 | EM31: 1 | EN31: 28 | EO31: 1 | EP31: 28 | EQ31: 13
A32: United Arab Emirates | B32: ARE | C32: Arab States | D32: High-income | E32: 84402.77 | F32: 10642000 | G32: 62.601984 | H32: AE | I32: 26 | J32: 60.24853 | K32: 57.122626 | L32: 70.238323 | M32: 62.798459 | N32: 17 | O32: 19 | P32: 42 | Q32: 34 | R32: 84.897333 | S32: 27.73795 | T32: 68.110306 | U32: 66.368377 | V32: 37.827837 | W32: 67.171665 | X32: 65.329908 | Y32: 67.051399 | Z32: 78.333661 | AA32: 38.418734 | AB32: 84.572106 | AC32: 65.404538 | AD32: 5 | AE32: 54 | AF32: 6 | AG32: 16 | AH32: 41 | AI32: 11 | AJ32: 55 | AK32: 50 | AL32: 28 | AM32: 42 | AN32: 11 | AO32: 61 | AP32: 86.250968 | AQ32: 100 | AR32: 39.363266 | AS32: 100 | AT32: 83.769762 | AU32: 100 | AV32: 14.259897 | AW32: 10.236831 | AX32: 77.28331 | AY32: 9.1717617 | AZ32: 99.137383 | BA32: 79.5 | BB32: n/a | BC32: 25.693536 | BD32: 31.609919 | BE32: 84.796581 | BF32: 99.232829 | BG32: 98.461538 | BH32: 17.741015 | BI32: n/a | BJ32: 35.109637 | BK32: 51.302453 | BL32: 27.071421 | BM32: 89.926733 | BN32: 57.541897 | BO32: 97.730499 | BP32: 23.487533 | BQ32: 67.245852 | BR32: 100 | BS32: n/a | BT32: 28.743872 | BU32: 68.313829 | BV32: 75.625 | BW32: 81.882246 | BX32: 100 | BY32: 9.4359187 | BZ32: 76.809141 | CA32: 90.265381 | CB32: 67.926462 | CC32: n/a | CD32: 4.9931181 | CE32: 64.059015 | CF32: 72.284171 | CG32: 12.338631 | CH32: 78.172475 | CI32: 89.84375 | CJ32: 93.367347 | CK32: 78.032835 | CL32: 100 | CM32: 36.992149 | CN32: 74.545455 | CO32: 54.89774 | CP32: 90.365615 | CQ32: 22 | CR32: 1 | CS32: 43 | CT32: 1 | CU32: 15 | CV32: 1 | CW32: 50 | CX32: 44 | CY32: 12 | CZ32: 48 | DA32: 3 | DB32: 10 | DC32: n/a | DD32: 34 | DE32: 33 | DF32: 7 | DG32: 2 | DH32: 16 | DI32: 36 | DJ32: n/a | DK32: 18 | DL32: 29 | DM32: 28 | DN32: 16 | DO32: 20 | DP32: 2 | DQ32: 27 | DR32: 59 | DS32: 1 | DT32: n/a | DU32: 61 | DV32: 30 | DW32: 59 | DX32: 9 | DY32: 1 | DZ32: 125 | EA32: 37 | EB32: 29 | EC32: 31 | ED32: n/a | EE32: 37 | EF32: 37 | EG32: 20 | EH32: 66 | EI32: 21 | EJ32: 15 | EK32: 7 | EL32: 33 | EM32: 1 | EN32: 46 | EO32: 72 | EP32: 105 | EQ32: 19
A33: Lithuania | B33: LTU | C33: Europe | D33: High-income | E33: 57201.425 | F33: 2854000 | G33: 62.597012 | H33: LT | I33: 27 | J33: 51.426433 | K33: 52.873634 | L33: 84.172392 | M33: 61.915588 | N33: 37 | O33: 28 | P33: 16 | Q33: 38 | R33: 79.469999 | S33: 36.570579 | T33: 38.23872 | U33: 62.580644 | V33: 46.339799 | W33: 49.700458 | X33: 81.392968 | Y33: 87.673546 | Z33: 83.450662 | AA33: 38.751955 | AB33: 69.192762 | AC33: 77.802048 | AD33: 21 | AE33: 44 | AF33: 49 | AG33: 22 | AH33: 28 | AI33: 35 | AJ33: 31 | AK33: 7 | AL33: 14 | AM33: 41 | AN33: 51 | AO33: 33 | AP33: 84.892078 | AQ33: 95.517528 | AR33: 25.543867 | AS33: 99.947368 | AT33: 75.919156 | AU33: 95 | AV33: 37.530726 | AW33: 26.565412 | AX33: 80.228387 | AY33: 1.9577892 | AZ33: 78.902742 | BA33: 61.75 | BB33: 7.3760819 | BC33: 4.9260564 | BD33: 16.572613 | BE33: 71.994487 | BF33: 77.306222 | BG33: 99.739538 | BH33: 47.290359 | BI33: 75.293049 | BJ33: 30.315788 | BK33: 33.410561 | BL33: n/a | BM33: 86.032411 | BN33: 46.646117 | BO33: n/a | BP33: 16.422845 | BQ33: 92.614502 | BR33: 91.269324 | BS33: n/a | BT33: 60.295077 | BU33: 75.712376 | BV33: 99.0625 | BW33: 71.805212 | BX33: 100 | BY33: 91.78764 | BZ33: 82.606856 | CA33: 89.895447 | CB33: 77.849683 | CC33: n/a | CD33: 5.5013806 | CE33: 47.614405 | CF33: 73.760009 | CG33: 28.132027 | CH33: 79.736372 | CI33: 59.635417 | CJ33: 68.877551 | CK33: 67.535445 | CL33: 88.888889 | CM33: 57.82787 | CN33: 90.909091 | CO33: 86.221744 | CP33: 63.610085 | CQ33: 26 | CR33: 19 | CS33: 81 | CT33: 25 | CU33: 39 | CV33: 44 | CW33: 29 | CX33: 29 | CY33: 7 | CZ33: 84 | DA33: 24 | DB33: 29 | DC33: 34 | DD33: 97 | DE33: 60 | DF33: 29 | DG33: 41 | DH33: 10 | DI33: 11 | DJ33: 35 | DK33: 21 | DL33: 100 | DM33: n/a | DN33: 26 | DO33: 35 | DP33: n/a | DQ33: 38 | DR33: 12 | DS33: 56 | DT33: n/a | DU33: 34 | DV33: 20 | DW33: 2 | DX33: 27 | DY33: 1 | DZ33: 9 | EA33: 29 | EB33: 30 | EC33: 4 | ED33: n/a | EE33: 35 | EF33: 82 | EG33: 16 | EH33: 30 | EI33: 16 | EJ33: 87 | EK33: 64 | EL33: 58 | EM33: 58 | EN33: 30 | EO33: 28 | EP33: 27 | EQ33: 63
A34: Italy | B34: ITA | C34: Europe | D34: High-income | E34: 63125.675 | F34: 59499000 | G34: 62.478647 | H34: IT | I34: 28 | J34: 55.133967 | K34: 53.523589 | L34: 78.536455 | M34: 62.720579 | N34: 30 | O34: 24 | P34: 28 | Q34: 35 | R34: 75.14813 | S34: 41.40228 | T34: 48.851491 | U34: 57.921489 | V34: 51.436998 | W34: 51.212279 | X34: 82.45763 | Y34: 79.961747 | Z34: 73.189988 | AA34: 36.875948 | AB34: 67.824967 | AC34: 83.460821 | AD34: 43 | AE34: 33 | AF34: 26 | AG34: 36 | AH34: 23 | AI34: 34 | AJ34: 26 | AK34: 20 | AL34: 45 | AM34: 48 | AN34: 59 | AO34: 16 | AP34: 82.283699 | AQ34: 82.188685 | AR34: 43.209447 | AS34: 100 | AT34: 73.206948 | AU34: 70 | AV34: 19.850511 | AW34: 26.568378 | AX34: 66.897989 | AY34: 52.29224 | AZ34: 77.914051 | BA34: 41 | BB34: 28.898849 | BC34: 47.593064 | BD34: 46.271741 | BE34: 59.100995 | BF34: 75.448014 | BG34: 98.461538 | BH34: 10.325157 | BI34: 84.913768 | BJ34: 9.5820036 | BK34: 64.608658 | BL34: 46.643562 | BM34: 71.413963 | BN34: 52.76786 | BO34: 60.079455 | BP34: 20.58784 | BQ34: 83.199389 | BR34: 100 | BS34: n/a | BT34: 64.1735 | BU34: 58.345031 | BV34: 100 | BW34: 61.994603 | BX34: 100 | BY34: 79.4691 | BZ34: 63.764283 | CA34: 91.635992 | CB34: 64.169689 | CC34: n/a | CD34: 15.00843 | CE34: 77.817732 | CF34: 44.759924 | CG34: 9.9177043 | CH34: 70.487042 | CI34: 51.692708 | CJ34: 73.214286 | CK34: 89.376018 | CL34: 100 | CM34: 57.672879 | CN34: 96.363636 | CO34: 88.912809 | CP34: 81.787917 | CQ34: 33 | CR34: 43 | CS34: 36 | CT34: 1 | CU34: 54 | CV34: 55 | CW34: 43 | CX34: 28 | CY34: 57 | CZ34: 14 | DA34: 26 | DB34: 60 | DC34: 15 | DD34: 12 | DE34: 14 | DF34: 45 | DG34: 48 | DH34: 16 | DI34: 38 | DJ34: 19 | DK34: 50 | DL34: 10 | DM34: 11 | DN34: 61 | DO34: 28 | DP34: 28 | DQ34: 34 | DR34: 30 | DS34: 1 | DT34: n/a | DU34: 28 | DV34: 42 | DW34: 1 | DX34: 38 | DY34: 1 | DZ34: 28 | EA34: 61 | EB34: 27 | EC34: 62 | ED34: n/a | EE34: 26 | EF34: 11 | EG34: 56 | EH34: 76 | EI34: 37 | EJ34: 104 | EK34: 54 | EL34: 14 | EM34: 1 | EN34: 31 | EO34: 15 | EP34: 17 | EQ34: 30
A35: Czechia | B35: CZE | C35: Europe | D35: High-income | E35: 59853.135 | F35: 10810000 | G35: 62.316352 | H35: CZ | I35: 29 | J35: 56.248875 | K35: 47.088139 | L35: 79.41065 | M35: 66.517744 | N35: 29 | O35: 42 | P35: 25 | Q35: 24 | R35: 77.076331 | S35: 46.071728 | T35: 45.598565 | U35: 49.240626 | V35: 44.957592 | W35: 47.066199 | X35: 87.498322 | Y35: 77.604576 | Z35: 73.129052 | AA35: 36.576711 | AB35: 83.85345 | AC35: 79.123072 | AD35: 34 | AE35: 25 | AF35: 35 | AG35: 73 | AH35: 31 | AI35: 44 | AJ35: 15 | AK35: 26 | AL35: 46 | AM35: 51 | AN35: 12 | AO35: 29 | AP35: 81.37159 | AQ35: 87.320729 | AR35: 27.977739 | AS35: 98.947368 | AT35: 68.131636 | AU35: 98.708923 | AV35: 62.688736 | AW35: 43.20006 | AX35: 73.432056 | AY35: 4.9660587 | AZ35: 77.827088 | BA35: 55 | BB35: 26.371951 | BC35: 23.19522 | BD35: 17.162838 | BE35: 69.528451 | BF35: 78.896428 | BG35: n/a | BH35: 31.374786 | BI35: 95.144342 | BJ35: 10.250652 | BK35: 48.287892 | BL35: 26.147483 | BM35: 63.983831 | BN35: 59.484491 | BO35: 35.96231 | BP35: 28.834163 | BQ35: 90.883513 | BR35: 85.502981 | BS35: n/a | BT35: 86.108473 | BU35: 74.87271 | BV35: 79.375 | BW35: 62.466585 | BX35: 75 | BY35: 96.308586 | BZ35: 56.517139 | CA35: 96.414265 | CB35: 66.455753 | CC35: n/a | CD35: 8.4277497 | CE35: 61.040467 | CF35: 53.816316 | CG35: 23.02231 | CH35: 78.529937 | CI35: 87.5 | CJ35: 95.153061 | CK35: 75.907764 | CL35: 100 | CM35: 63.60933 | CN35: 90.909091 | CO35: 74.811625 | CP35: 74.32448 | CQ35: 35 | CR35: 36 | CS35: 76 | CT35: 43 | CU35: 82 | CV35: 40 | CW35: 15 | CX35: 20 | CY35: 23 | CZ35: 66 | DA35: 27 | DB35: 36 | DC35: 17 | DD35: 43 | DE35: 58 | DF35: 31 | DG35: 33 | DH35: n/a | DI35: 24 | DJ35: 2 | DK35: 47 | DL35: 40 | DM35: 30 | DN35: 76 | DO35: 18 | DP35: 65 | DQ35: 21 | DR35: 14 | DS35: 69 | DT35: n/a | DU35: 9 | DV35: 21 | DW35: 47 | DX35: 36 | DY35: 72 | DZ35: 5 | EA35: 73 | EB35: 12 | EC35: 43 | ED35: n/a | EE35: 31 | EF35: 45 | EG35: 44 | EH35: 43 | EI35: 20 | EJ35: 23 | EK35: 5 | EL35: 39 | EM35: 1 | EN35: 15 | EO35: 28 | EP35: 66 | EQ35: 43
A36: Hong Kong, China | B36: HKG | C36: Asia & Pacific | D36: High-income | E36: 78918.785 | F36: 7443000 | G36: 61.925289 | H36: HK | I36: 30 | J36: 63.574352 | K36: 47.725228 | L36: 73.746058 | M36: 62.655518 | N36: 13 | O36: 36 | P36: 36 | Q36: 36 | R36: 85.797425 | S36: 47.995429 | T36: 56.930204 | U36: 63.233688 | V36: 42.539739 | W36: 37.402257 | X36: 83.178747 | Y36: 63.902377 | Z36: 74.157049 | AA36: 47.614633 | AB36: 52.916597 | AC36: 87.435325 | AD36: 3 | AE36: 19 | AF36: 16 | AG36: 18 | AH36: 36 | AI36: 73 | AJ36: 22 | AK36: 59 | AL36: 41 | AM36: 24 | AN36: 93 | AO36: 3 | AP36: 100 | AQ36: 84.439885 | AR36: 35.607821 | AS36: 94.736842 | AT36: 100 | AU36: 100 | AV36: n/a | AW36: 44.425503 | AX36: 84.339366 | AY36: 15.221417 | AZ36: 83.933968 | BA36: 74.75 | BB36: 40.57715 | BC36: 28.459697 | BD36: 21.872639 | BE36: 76.288784 | BF36: 91.53964 | BG36: n/a | BH36: n/a | BI36: 56.154486 | BJ36: n/a | BK36: 46.89109 | BL36: 24.57364 | BM36: n/a | BN36: 57.488519 | BO36: n/a | BP36: 17.315994 | BQ36: 96.320496 | BR36: n/a | BS36: n/a | BT36: 70.036997 | BU36: 82.376171 | BV36: 72.8125 | BW36: 67.384753 | BX36: n/a | BY36: 33.036085 | BZ36: n/a | CA36: 83.941319 | CB36: 64.37278 | CC36: n/a | CD36: 66.114349 | CE36: 60.233641 | CF36: 59.890732 | CG36: 4.2198075 | CH36: 49.84361 | CI36: 55.989583 | CJ36: n/a | CK36: n/a | CL36: n/a | CM36: 75.631153 | CN36: 88.181818 | CO36: 98.493003 | CP36: n/a | CQ36: 1 | CR36: 39 | CS36: 52 | CT36: 63 | CU36: 1 | CV36: 1 | CW36: n/a | CX36: 19 | CY36: 4 | CZ36: 39 | DA36: 18 | DB36: 15 | DC36: 7 | DD36: 27 | DE36: 44 | DF36: 20 | DG36: 5 | DH36: n/a | DI36: n/a | DJ36: 60 | DK36: n/a | DL36: 44 | DM36: 33 | DN36: n/a | DO36: 21 | DP36: n/a | DQ36: 37 | DR36: 8 | DS36: n/a | DT36: n/a | DU36: 21 | DV36: 12 | DW36: 68 | DX36: 28 | DY36: n/a | DZ36: 109 | EA36: n/a | EB36: 42 | EC36: 59 | ED36: n/a | EE36: 12 | EF36: 48 | EG36: 36 | EH36: 96 | EI36: 84 | EJ36: 98 | EK36: n/a | EL36: n/a | EM36: n/a | EN36: 5 | EO36: 34 | EP36: 2 | EQ36: n/a
A37: Malta | B37: MLT | C37: Europe | D37: High-income | E37: 78710.887 | F37: 533000 | G37: 61.724847 | H37: MT | I37: 31 | J37: 50.478828 | K37: 55.459063 | L37: 75.82232 | M37: 65.139178 | N37: 39 | O37: 22 | P37: 33 | Q37: 27 | R37: 67.668366 | S37: 37.988511 | T37: 45.779607 | U37: 55.889553 | V37: 64.714828 | W37: 45.772809 | X37: 73.265906 | Y37: 77.477058 | Z37: 76.723996 | AA37: 37.662976 | AB37: 75.552194 | AC37: 82.202364 | AD37: 66 | AE37: 39 | AF37: 33 | AG37: 42 | AH37: 6 | AI37: 51 | AJ37: 45 | AK37: 27 | AL37: 33 | AM37: 45 | AN37: 33 | AO37: 22 | AP37: 88.382506 | AQ37: 82.634776 | AR37: 6.6280517 | AS37: 100 | AT37: 60.696496 | AU37: n/a | AV37: 29.926397 | AW37: 50.251232 | AX37: 71.471512 | AY37: 0.30490279 | AZ37: 61.498325 | BA37: 53.5 | BB37: n/a | BC37: 22.340497 | BD37: 2.2126137 | BE37: 58.823261 | BF37: 70.379259 | BG37: 92.143077 | BH37: n/a | BI37: 88.096613 | BJ37: 41.333043 | BK37: n/a | BL37: n/a | BM37: 84.952058 | BN37: 40.346555 | BO37: 48.258322 | BP37: 9.534303 | BQ37: 67.672391 | BR37: 92.089397 | BS37: n/a | BT37: 60.035931 | BU37: 59.429281 | BV37: 90.625 | BW37: 80.217777 | BX37: 100 | BY37: 57.113231 | BZ37: 72.460855 | CA37: 82.165407 | CB37: 75.545725 | CC37: n/a | CD37: 47.464303 | CE37: 33.926375 | CF37: 59.72377 | CG37: 9.537457 | CH37: 68.275246 | CI37: 77.213542 | CJ37: 72.44898 | CK37: 89.886611 | CL37: 100 | CM37: 50.30231 | CN37: 87.272727 | CO37: 98.385361 | CP37: 85.698118 | CQ37: 15 | CR37: 42 | CS37: 115 | CT37: 1 | CU37: 114 | CV37: n/a | CW37: 34 | CX37: 17 | CY37: 29 | CZ37: 111 | DA37: 62 | DB37: 38 | DC37: n/a | DD37: 45 | DE37: 112 | DF37: 46 | DG37: 61 | DH37: 49 | DI37: n/a | DJ37: 16 | DK37: 14 | DL37: n/a | DM37: n/a | DN37: 30 | DO37: 45 | DP37: 38 | DQ37: 58 | DR37: 58 | DS37: 54 | DT37: n/a | DU37: 35 | DV37: 39 | DW37: 16 | DX37: 14 | DY37: 1 | DZ37: 79 | EA37: 46 | EB37: 46 | EC37: 6 | ED37: n/a | EE37: 16 | EF37: 118 | EG37: 37 | EH37: 79 | EI37: 46 | EJ37: 54 | EK37: 57 | EL37: 12 | EM37: 1 | EN37: 38 | EO37: 37 | EP37: 3 | EQ37: 25
A38: Portugal | B38: PRT | C38: Europe | D38: High-income | E38: 49753.185 | F38: 10431000 | G38: 61.537048 | H38: PT | I38: 32 | J38: 56.97263 | K38: 45.996308 | L38: 77.747852 | M38: 65.431403 | N38: 25 | O38: 45 | P38: 29 | Q38: 26 | R38: 76.321849 | S38: 47.179184 | T38: 47.416856 | U38: 56.619279 | V38: 34.433414 | W38: 46.936232 | X38: 76.491026 | Y38: 85.84381 | Z38: 70.908719 | AA38: 36.746951 | AB38: 74.730617 | AC38: 84.816641 | AD38: 38 | AE38: 23 | AF38: 29 | AG38: 39 | AH38: 51 | AI38: 45 | AJ38: 37 | AK38: 12 | AL38: 50 | AM38: 49 | AN38: 37 | AO38: 11 | AP38: 60.869339 | AQ38: 81.091168 | AR38: 41.56684 | AS38: 100 | AT38: 75.433992 | AU38: 98.969757 | AV38: 46.523026 | AW38: 55.924817 | AX38: 70.334645 | AY38: 15.934249 | AZ38: 76.635942 | BA38: 52.75 | BB38: 12.348052 | BC38: 47.93343 | BD38: 15.776039 | BE38: 74.226541 | BF38: 76.441549 | BG38: 95.089231 | BH38: 21.563035 | BI38: 59.22741 | BJ38: 12.402614 | BK38: 46.006956 | BL38: 20.096678 | BM38: 74.464937 | BN38: 47.321776 | BO38: 39.421134 | BP38: 26.537081 | BQ38: 82.672684 | BR38: 99.827535 | BS38: n/a | BT38: 46.97286 | BU38: 61.130891 | BV38: 94.375 | BW38: 73.713158 | BX38: 100 | BY38: 100 | BZ38: 62.314854 | CA38: 82.014945 | CB38: 68.39636 | CC38: n/a | CD38: 6.8523769 | CE38: 59.141643 | CF38: 56.235225 | CG38: 24.758558 | CH38: 61.505809 | CI38: 82.682292 | CJ38: 74.234694 | CK38: 85.772808 | CL38: 100 | CM38: 58.024934 | CN38: 100 | CO38: 88.159311 | CP38: 86.164639 | CQ38: 76 | CR38: 45 | CS38: 38 | CT38: 1 | CU38: 41 | CV38: 38 | CW38: 24 | CX38: 15 | CY38: 38 | CZ38: 38 | DA38: 32 | DB38: 39 | DC38: 25 | DD38: 10 | DE38: 63 | DF38: 24 | DG38: 45 | DH38: 37 | DI38: 32 | DJ38: 55 | DK38: 42 | DL38: 48 | DM38: 41 | DN38: 54 | DO38: 33 | DP38: 57 | DQ38: 23 | DR38: 33 | DS38: 13 | DT38: n/a | DU38: 49 | DV38: 36 | DW38: 5 | DX38: 24 | DY38: 1 | DZ38: 1 | EA38: 65 | EB38: 47 | EC38: 28 | ED38: n/a | EE38: 32 | EF38: 50 | EG38: 39 | EH38: 40 | EI38: 58 | EJ38: 35 | EK38: 50 | EL38: 24 | EM38: 1 | EN38: 27 | EO38: 1 | EP38: 18 | EQ38: 24
A39: Slovenia | B39: SVN | C39: Europe | D39: High-income | E39: 57716.483 | F39: 2118000 | G39: 60.808955 | H39: SI | I39: 33 | J39: 52.897827 | K39: 44.985642 | L39: 78.74413 | M39: 66.608221 | N39: 34 | O39: 49 | P39: 27 | Q39: 23 | R39: 78.568632 | S39: 36.873288 | T39: 43.251561 | U39: 46.48883 | V39: 39.25331 | W39: 49.214787 | X39: 82.909164 | Y39: 75.08165 | Z39: 78.241576 | AA39: 30.361647 | AB39: 87.908463 | AC39: 81.554552 | AD39: 27 | AE39: 43 | AF39: 40 | AG39: 82 | AH39: 40 | AI39: 37 | AJ39: 24 | AK39: 31 | AL39: 29 | AM39: 71 | AN39: 6 | AO39: 23 | AP39: 98.052579 | AQ39: 81.771668 | AR39: 20.583283 | AS39: 99.473684 | AT39: 71.530577 | AU39: 100 | AV39: 39.040218 | AW39: 29.082665 | AX39: 77.268013 | AY39: 2.1022563 | AZ39: 76.73947 | BA39: 51.5 | BB39: 38.477961 | BC39: 6.288812 | BD39: 6.4558641 | BE39: 72.146158 | BF39: 79.572351 | BG39: n/a | BH39: 27.780947 | BI39: 92.984554 | BJ39: 14.662645 | BK39: 40.292585 | BL39: 9.0734548 | BM39: 83.633498 | BN39: n/a | BO39: 30.44251 | BP39: 33.568351 | BQ39: 89.720928 | BR39: 95.763014 | BS39: n/a | BT39: 63.243549 | BU39: 60.531932 | BV39: 88.75 | BW39: 64.25365 | BX39: 75 | BY39: 86.872667 | BZ39: 76.809141 | CA39: 89.042492 | CB39: 68.873095 | CC39: n/a | CD39: 11.872331 | CE39: 44.949429 | CF39: 49.972068 | CG39: 14.652762 | CH39: 78.909741 | CI39: 93.359375 | CJ39: 97.704082 | CK39: 85.208462 | CL39: 100 | CM39: 60.806251 | CN39: 95.454545 | CO39: 80.624327 | CP39: 78.666168 | CQ39: 3 | CR39: 44 | CS39: 90 | CT39: 29 | CU39: 64 | CV39: 1 | CW39: 28 | CX39: 26 | CY39: 13 | CZ39: 81 | DA39: 31 | DB39: 41 | DC39: 9 | DD39: 91 | DE39: 88 | DF39: 27 | DG39: 30 | DH39: n/a | DI39: 26 | DJ39: 6 | DK39: 37 | DL39: 65 | DM39: 53 | DN39: 32 | DO39: n/a | DP39: 76 | DQ39: 17 | DR39: 15 | DS39: 44 | DT39: n/a | DU39: 29 | DV39: 37 | DW39: 22 | DX39: 33 | DY39: 72 | DZ39: 18 | EA39: 37 | EB39: 31 | EC39: 25 | ED39: n/a | EE39: 29 | EF39: 88 | EG39: 50 | EH39: 60 | EI39: 19 | EJ39: 10 | EK39: 2 | EL39: 25 | EM39: 1 | EN39: 21 | EO39: 20 | EP39: 43 | EQ39: 34
A40: Saudi Arabia | B40: SAU | C40: Arab States | D40: High-income | E40: 74668.069 | F40: 33264000 | G40: 60.201982 | H40: SA | I40: 34 | J40: 56.604284 | K40: 52.970444 | L40: 76.194334 | M40: 55.038865 | N40: 27 | O40: 27 | P40: 31 | Q40: 55 | R40: 83.637093 | S40: 26.442718 | T40: 59.733042 | U40: 69.309076 | V40: 29.512882 | W40: 60.089374 | X40: 71.391587 | Y40: 76.384884 | Z40: 80.806532 | AA40: 37.582251 | AB40: 79.279473 | AC40: 48.254872 | AD40: 7 | AE40: 60 | AF40: 12 | AG40: 10 | AH40: 69 | AI40: 22 | AJ40: 47 | AK40: 30 | AL40: 20 | AM40: 46 | AN40: 23 | AO40: 110 | AP40: 73.807058 | AQ40: 92.219046 | AR40: 48.450487 | AS40: 100 | AT40: 87.345966 | AU40: 100 | AV40: 3.27153 | AW40: 1.902744 | AX40: 64.94498 | AY40: 35.651619 | AZ40: 95.385072 | BA40: 61.5 | BB40: n/a | BC40: 22.314054 | BD40: 60.815636 | BE40: 81.047572 | BF40: 100 | BG40: 96.809954 | BH40: 7.8722191 | BI40: 21.370533 | BJ40: 9.6653607 | BK40: 59.681977 | BL40: 27.333657 | BM40: 98.790919 | BN40: 45.838784 | BO40: 86.905432 | BP40: 8.8223601 | BQ40: 49.612039 | BR40: 100 | BS40: n/a | BT40: 64.562721 | BU40: 55.167883 | BV40: 92.5 | BW40: 76.977398 | BX40: 100 | BY40: 57.279137 | BZ40: 95.651714 | CA40: 86.992595 | CB40: 67.926462 | CC40: 72.655358 | CD40: 5.7557437 | CE40: 72.749032 | CF40: 68.011627 | CG40: 3.8126014 | CH40: 74.620197 | CI40: 87.369792 | CJ40: n/a | CK40: 72.417387 | CL40: 86.666667 | CM40: 20.61117 | CN40: 58.181818 | CO40: 50.269107 | CP40: 41.248123 | CQ40: 53 | CR40: 24 | CS40: 23 | CT40: 1 | CU40: 8 | CV40: 1 | CW40: 90 | CX40: 82 | CY40: 64 | CZ40: 22 | DA40: 8 | DB40: 30 | DC40: n/a | DD40: 46 | DE40: 6 | DF40: 11 | DG40: 1 | DH40: 33 | DI40: 39 | DJ40: 103 | DK40: 49 | DL40: 16 | DM40: 27 | DN40: 4 | DO40: 38 | DP40: 6 | DQ40: 61 | DR40: 85 | DS40: 1 | DT40: n/a | DU40: 26 | DV40: 47 | DW40: 11 | DX40: 18 | DY40: 1 | DZ40: 78 | EA40: 7 | EB40: 37 | EC40: 31 | ED40: 25 | EE40: 34 | EF40: 18 | EG40: 25 | EH40: 101 | EI40: 29 | EJ40: 25 | EK40: n/a | EL40: 42 | EM40: 63 | EN40: 66 | EO40: 107 | EP40: 109 | EQ40: 95
A41: Poland | B41: POL | C41: Europe | D41: High-income | E41: 55340.224 | F41: 38763000 | G41: 59.404688 | H41: PL | I41: 35 | J41: 49.936897 | K41: 47.510318 | L41: 75.207111 | M41: 64.964425 | N41: 41 | O41: 40 | P41: 34 | Q41: 29 | R41: 78.593985 | S41: 37.597635 | T41: 33.619071 | U41: 62.659513 | V41: 35.22107 | W41: 44.650371 | X41: 80.317551 | Y41: 69.01508 | Z41: 76.288702 | AA41: 39.682569 | AB41: 75.781831 | AC41: 79.428874 | AD41: 26 | AE41: 42 | AF41: 68 | AG41: 20 | AH41: 47 | AI41: 57 | AJ41: 34 | AK41: 45 | AL41: 36 | AM41: 39 | AN41: 32 | AO41: 27 | AP41: 77.430661 | AQ41: 79.536716 | AR41: 44.95357 | AS41: 100 | AT41: 69.642961 | AU41: 100 | AV41: 41.317035 | AW41: 19.798734 | AX41: 71.552254 | AY41: 17.722516 | AZ41: 67.279782 | BA41: 37.25 | BB41: 9.8688155 | BC41: 20.077688 | BD41: 40.172594 | BE41: 56.303541 | BF41: 76.687708 | BG41: 99.688769 | BH41: 40.444952 | BI41: 53.426333 | BJ41: 4.4543659 | BK41: 55.016742 | BL41: 27.986837 | BM41: 76.385029 | BN41: n/a | BO41: 33.024925 | BP41: 24.541159 | BQ41: 85.575584 | BR41: 92.234709 | BS41: 86.172332 | BT41: 57.28758 | BU41: 61.752428 | BV41: 82.1875 | BW41: 40.455254 | BX41: 100 | BY41: 60.680216 | BZ41: 73.910284 | CA41: 81.727296 | CB41: 67.538805 | CC41: 81.978424 | CD41: 5.7562552 | CE41: 71.690395 | CF41: 54.184644 | CG41: 27.098981 | CH41: 76.251117 | CI41: 71.09375 | CJ41: 88.010204 | CK41: 71.99105 | CL41: 100 | CM41: 64.091313 | CN41: 90.909091 | CO41: 80.624327 | CP41: 64.181527 | CQ41: 43 | CR41: 48 | CS41: 33 | CT41: 1 | CU41: 72 | CV41: 1 | CW41: 25 | CX41: 35 | CY41: 28 | CZ41: 37 | DA41: 44 | DB41: 71 | DC41: 29 | DD41: 53 | DE41: 23 | DF41: 54 | DG41: 43 | DH41: 11 | DI41: 12 | DJ41: 65 | DK41: 66 | DL41: 23 | DM41: 26 | DN41: 50 | DO41: n/a | DP41: 73 | DQ41: 26 | DR41: 25 | DS41: 52 | DT41: 3 | DU41: 39 | DV41: 34 | DW41: 39 | DX41: 74 | DY41: 1 | DZ41: 72 | EA41: 42 | EB41: 48 | EC41: 38 | ED41: 10 | EE41: 33 | EF41: 20 | EG41: 43 | EH41: 35 | EI41: 25 | EJ41: 61 | EK41: 15 | EL41: 44 | EM41: 1 | EN41: 14 | EO41: 28 | EP41: 43 | EQ41: 60
A42: Bahrain | B42: BHR | C42: Arab States | D42: High-income | E42: 69270.719 | F42: 1570000 | G42: 58.674997 | H42: BH | I42: 36 | J42: 45.873859 | K42: 53.05904 | L42: 77.58218 | M42: 58.18491 | N42: 55 | O42: 26 | P42: 30 | Q42: 47 | R42: 70.308557 | S42: 18.154036 | T42: 49.158984 | U42: 66.479796 | V42: 36.435861 | W42: 56.261464 | X42: 84.44917 | Y42: 71.637976 | Z42: 76.659395 | AA42: 44.187846 | AB42: 72.799278 | AC42: 57.567606 | AD42: 61 | AE42: 88 | AF42: 25 | AG42: 15 | AH42: 44 | AI42: 25 | AJ42: 20 | AK42: 37 | AL42: 34 | AM42: 30 | AN42: 43 | AO42: 88 | AP42: 60.348552 | AQ42: 74.442837 | AR42: 12.476085 | AS42: 100 | AT42: 74.583868 | AU42: 100 | AV42: 8.6646208 | AW42: 3.1293972 | AX42: 59.504939 | AY42: 1.3171871 | AZ42: 63.635255 | BA42: n/a | BB42: n/a | BC42: 34.682713 | BD42: 9.6309096 | BE42: 72.254804 | BF42: 87.110393 | BG42: 96.923077 | BH42: n/a | BI42: 81.730922 | BJ42: 24.757476 | BK42: 38.079869 | BL42: 1.175176 | BM42: 88.336281 | BN42: 18.773547 | BO42: 61.674565 | BP42: n/a | BQ42: 71.375641 | BR42: 97.5227 | BS42: n/a | BT42: n/a | BU42: 69.204552 | BV42: 76.5625 | BW42: 76.296741 | BX42: 100 | BY42: 36.126089 | BZ42: 89.853999 | CA42: 72.197723 | CB42: 67.926462 | CC42: n/a | CD42: n/a | CE42: 43.851277 | CF42: 61.795497 | CG42: 26.916763 | CH42: 61.885612 | CI42: 86.328125 | CJ42: n/a | CK42: 67.568917 | CL42: 91.111111 | CM42: n/a | CN42: 53.636364 | CO42: 25.511302 | CP42: 95.99919 | CQ42: 78 | CR42: 54 | CS42: 109 | CT42: 1 | CU42: 47 | CV42: 1 | CW42: 58 | CX42: 70 | CY42: 81 | CZ42: 92 | DA42: 57 | DB42: n/a | DC42: n/a | DD42: 22 | DE42: 79 | DF42: 26 | DG42: 8 | DH42: 28 | DI42: n/a | DJ42: 24 | DK42: 24 | DL42: 76 | DM42: 94 | DN42: 23 | DO42: 77 | DP42: 24 | DQ42: n/a | DR42: 49 | DS42: 32 | DT42: n/a | DU42: n/a | DV42: 28 | DW42: 54 | DX42: 19 | DY42: 1 | DZ42: 105 | EA42: 18 | EB42: 65 | EC42: 31 | ED42: n/a | EE42: n/a | EF42: 89 | EG42: 32 | EH42: 36 | EI42: 57 | EJ42: 29 | EK42: n/a | EL42: 57 | EM42: 53 | EN42: n/a | EO42: 110 | EP42: 119 | EQ42: 8
A43: Latvia | B43: LVA | C43: Europe | D43: High-income | E43: 44105.521 | F43: 1882000 | G43: 58.454388 | H43: LV | I43: 37 | J43: 46.152038 | K43: 47.681605 | L43: 79.334008 | M43: 60.649902 | N43: 50 | O43: 38 | P43: 26 | Q43: 40 | R43: 73.981853 | S43: 36.030527 | T43: 28.443735 | U43: 54.587031 | V43: 44.456334 | W43: 44.00145 | X43: 76.000534 | Y43: 82.601054 | Z43: 79.400438 | AA43: 33.974165 | AB43: 68.919643 | AC43: 79.055899 | AD43: 48 | AE43: 45 | AF43: 90 | AG43: 50 | AH43: 32 | AI43: 59 | AJ43: 38 | AK43: 16 | AL43: 25 | AM43: 58 | AN43: 52 | AO43: 30 | AP43: 72.566535 | AQ43: 90.23542 | AR43: 22.831914 | AS43: 94.736842 | AT43: 63.520406 | AU43: 100 | AV43: 39.527317 | AW43: 24.494128 | AX43: 78.653442 | AY43: 1.4472201 | AZ43: 58.749314 | BA43: 44.75 | BB43: 2.4403325 | BC43: 7.8352919 | BD43: 15.845465 | BE43: 50.409463 | BF43: 81.640768 | BG43: 99.825538 | BH43: 25.213919 | BI43: 79.684807 | BJ43: 20.040829 | BK43: 33.643366 | BL43: n/a | BM43: 77.039497 | BN43: 47.480041 | BO43: 38.482143 | BP43: 13.004118 | BQ43: 82.554604 | BR43: 79.129141 | BS43: n/a | BT43: 66.317855 | BU43: 71.562805 | BV43: 81.25 | BW43: 60.627968 | BX43: 100 | BY43: 99.564496 | BZ43: 76.809141 | CA43: 90.80432 | CB43: 70.587852 | CC43: n/a | CD43: 4.2624609 | CE43: 41.285766 | CF43: 55.492572 | CG43: 34.855863 | CH43: 65.840036 | CI43: 70.963542 | CJ43: 73.979592 | CK43: 65.93111 | CL43: 88.888889 | CM43: 60.604933 | CN43: 100 | CO43: 82.669537 | CP43: 57.00936 | CQ43: 55 | CR43: 31 | CS43: 87 | CT43: 63 | CU43: 105 | CV43: 1 | CW43: 27 | CX43: 31 | CY43: 10 | CZ43: 90 | DA43: 69 | DB43: 53 | DC43: 46 | DD43: 87 | DE43: 62 | DF43: 65 | DG43: 19 | DH43: 6 | DI43: 28 | DJ43: 29 | DK43: 28 | DL43: 99 | DM43: n/a | DN43: 47 | DO43: 32 | DP43: 60 | DQ43: 45 | DR43: 34 | DS43: 78 | DT43: n/a | DU43: 25 | DV43: 23 | DW43: 41 | DX43: 39 | DY43: 1 | DZ43: 2 | EA43: 37 | EB43: 28 | EC43: 13 | ED43: n/a | EE43: 38 | EF43: 96 | EG43: 40 | EH43: 24 | EI43: 49 | EJ43: 62 | EK43: 53 | EL43: 67 | EM43: 58 | EN43: 22 | EO43: 1 | EP43: 39 | EQ43: 72
A44: Malaysia | B44: MYS | C44: Asia & Pacific | D44: Upper middle-income | E44: 43664.705 | F44: 35126000 | G44: 57.371296 | H44: MY | I44: 38 | J44: 50.614993 | K44: 53.138835 | L44: 69.790482 | M44: 55.940871 | N44: 38 | O44: 25 | P44: 44 | Q44: 50 | R44: 77.839586 | S44: 27.261484 | T44: 46.743908 | U44: 69.250589 | V44: 32.629421 | W44: 57.536496 | X44: 73.780248 | Y44: 68.333443 | Z44: 67.257757 | AA44: 40.643761 | AB44: 73.06753 | AC44: 54.111323 | AD44: 31 | AE44: 56 | AF44: 31 | AG44: 11 | AH44: 56 | AI44: 24 | AJ44: 44 | AK44: 46 | AL44: 56 | AM44: 35 | AN44: 40 | AO44: 95 | AP44: 63.253892 | AQ44: 76.734625 | AR44: 47.197781 | AS44: 92.631579 | AT44: 87.21964 | AU44: 100 | AV44: 7.2768888 | AW44: 5.2676096 | AX44: 62.152348 | AY44: 34.34909 | AZ44: 71.757708 | BA44: 78.75 | BB44: 8.441283 | BC44: 28.026643 | BD44: 47.953365 | BE44: 57.520754 | BF44: 77.682084 | BG44: 93.846154 | BH44: n/a | BI44: 55.699794 | BJ44: 2.1596127 | BK44: 49.33346 | BL44: 23.32482 | BM44: 67.271809 | BN44: 71.20048 | BO44: 76.768276 | BP44: 14.905419 | BQ44: 71.831793 | BR44: 98.584614 | BS44: 62.608571 | BT44: 62.096014 | BU44: 58.767009 | BV44: 73.75 | BW44: 59.6894 | BX44: 100 | BY44: 49.460805 | BZ44: 68.112569 | CA44: 67.779165 | CB44: 66.546178 | CC44: 66.593117 | CD44: 3.4837408 | CE44: 68.63735 | CF44: 79.24832 | CG44: 11.205632 | CH44: 60.210009 | CI44: 97.265625 | CJ44: 56.887755 | CK44: 66.56616 | CL44: 91.111111 | CM44: 27.698004 | CN44: 42.727273 | CO44: 69.214209 | CP44: 62.500499 | CQ44: 71 | CR44: 50 | CS44: 27 | CT44: 78 | CU44: 9 | CV44: 1 | CW44: 62 | CX44: 58 | CY44: 72 | CZ44: 23 | DA44: 39 | DB44: 12 | DC44: 30 | DD44: 29 | DE44: 10 | DF44: 49 | DG44: 38 | DH44: 39 | DI44: n/a | DJ44: 61 | DK44: 80 | DL44: 32 | DM44: 35 | DN44: 68 | DO44: 8 | DP44: 15 | DQ44: 42 | DR44: 47 | DS44: 25 | DT44: 14 | DU44: 30 | DV44: 41 | DW44: 64 | DX44: 40 | DY44: 1 | DZ44: 89 | EA44: 53 | EB44: 71 | EC44: 42 | ED44: 36 | EE44: 41 | EF44: 28 | EG44: 12 | EH44: 70 | EI44: 62 | EJ44: 2 | EK44: 86 | EL44: 62 | EM44: 53 | EN44: 56 | EO44: 116 | EP44: 82 | EQ44: 65
A45: Cyprus | B45: CYP | C45: Europe | D45: High-income | E45: 65304.132 | F45: 1345000 | G45: 56.285335 | H45: CY | I45: 39 | J45: 49.090088 | K45: 40.661601 | L45: 73.069667 | M45: 62.319985 | N45: 42 | O45: 68 | P45: 37 | Q45: 37 | R45: 70.611808 | S45: 45.42464 | T45: 31.233814 | U45: 53.339541 | V45: 33.412927 | W45: 35.232335 | X45: 83.328182 | Y45: 62.516198 | Z45: 73.36462 | AA45: 46.73067 | AB45: 64.208815 | AC45: 76.02047 | AD45: 59 | AE45: 26 | AF45: 77 | AG45: 55 | AH45: 54 | AI45: 81 | AJ45: 21 | AK45: 65 | AL45: 44 | AM45: 25 | AN45: 69 | AO45: 38 | AP45: 66.487703 | AQ45: 97.698178 | AR45: 13.632458 | AS45: 100 | AT45: 75.240702 | AU45: n/a | AV45: 40.587673 | AW45: 39.11829 | AX45: 100 | AY45: 1.9925989 | AZ45: 51.725292 | BA45: 31.25 | BB45: n/a | BC45: 10.72615 | BD45: 3.8350282 | BE45: 57.09705 | BF45: 69.095545 | BG45: 99.077385 | BH45: 37.592698 | BI45: 71.386675 | BJ45: 27.261694 | BK45: 34.145039 | BL45: 0.85829958 | BM45: 78.543328 | BN45: n/a | BO45: 16.515342 | BP45: 10.638335 | BQ45: 99.129772 | BR45: 97.613147 | BS45: n/a | BT45: 53.241626 | BU45: 61.703998 | BV45: 80.625 | BW45: 44.972027 | BX45: 50 | BY45: 75.279967 | BZ45: 68.112569 | CA45: 81.663981 | CB45: 70.317311 | CC45: n/a | CD45: 2.9477046 | CE45: 37.244304 | CF45: n/a | CG45: 100 | CH45: 59.919571 | CI45: 47.916667 | CJ45: 79.591837 | CK45: 89.988577 | CL45: 100 | CM45: 27.31215 | CN45: 95.454545 | CO45: 87.405813 | CP45: 87.818741 | CQ45: 64 | CR45: 10 | CS45: 106 | CT45: 1 | CU45: 43 | CV45: n/a | CW45: 26 | CX45: 22 | CY45: 1 | CZ45: 83 | DA45: 77 | DB45: 89 | DC45: n/a | DD45: 80 | DE45: 103 | DF45: 52 | DG45: 64 | DH45: 14 | DI45: 16 | DJ45: 36 | DK45: 23 | DL45: 97 | DM45: 98 | DN45: 42 | DO45: n/a | DP45: 101 | DQ45: 53 | DR45: 2 | DS45: 31 | DT45: n/a | DU45: 42 | DV45: 35 | DW45: 45 | DX45: 60 | DY45: 107 | DZ45: 41 | EA45: 53 | EB45: 49 | EC45: 15 | ED45: n/a | EE45: 42 | EF45: 110 | EG45: n/a | EH45: 1 | EI45: 65 | EJ45: 109 | EK45: 33 | EL45: 11 | EM45: 1 | EN45: 58 | EO45: 20 | EP45: 20 | EQ45: 21
A46: Viet Nam | B46: VNM | C46: Asia & Pacific | D46: Lower middle-income | E46: 17688.249 | F46: 100352000 | G46: 55.995794 | H46: VN | I46: 40 | J46: 52.024243 | K46: 47.249884 | L46: 61.588521 | M46: 63.120526 | N46: 35 | O46: 41 | P46: 60 | Q46: 33 | R46: 82.437571 | S46: 39.454367 | T46: 34.180792 | U46: 69.530724 | V46: 25.656994 | W46: 46.561935 | X46: 80.597592 | Y46: 51.115331 | Z46: 53.052641 | AA46: 43.092012 | AB46: 79.697944 | AC46: 66.571621 | AD46: 12 | AE46: 37 | AF46: 66 | AG46: 9 | AH46: 83 | AI46: 46 | AJ46: 32 | AK46: 92 | AL46: 88 | AM46: 34 | AN46: 21 | AO46: 56 | AP46: 70.234185 | AQ46: 74.474467 | AR46: 72.148995 | AS46: 99.210526 | AT46: 84.900414 | AU46: 93.656837 | AV46: 16.009399 | AW46: 2.7718909 | AX46: 82.936216 | AY46: 56.099962 | AZ46: 76.556225 | BA46: 38.5 | BB46: 2.6493515 | BC46: 19.01759 | BD46: 45.091926 | BE46: 64.648559 | BF46: 74.536257 | BG46: 93.846154 | BH46: n/a | BI46: 38.421491 | BJ46: 2.227766 | BK46: 47.344041 | BL46: 14.634677 | BM46: 64.883724 | BN46: 36.463175 | BO46: 78.285282 | BP46: 6.6155578 | BQ46: 69.692117 | BR46: 99.688236 | BS46: 100 | BT46: 53.010016 | BU46: 32.653769 | BV46: 47.1875 | BW46: 52.71589 | BX46: 100 | BY46: 23.019494 | BZ46: 57.966568 | CA46: 27.731426 | CB46: 59.550474 | CC46: 66.962096 | CD46: n/a | CE46: 70.286758 | CF46: 54.804205 | CG46: 4.1850738 | CH46: 69.079535 | CI46: 100 | CJ46: 68.622449 | CK46: 71.406145 | CL46: 73.333333 | CM46: 53.995728 | CN46: 82.727273 | CO46: 73.842842 | CP46: 38.107948 | CQ46: 57 | CR46: 53 | CS46: 4 | CT46: 40 | CU46: 11 | CV46: 46 | CW46: 46 | CX46: 72 | CY46: 6 | CZ46: 13 | DA46: 33 | DB46: 66 | DC46: 44 | DD46: 56 | DE46: 17 | DF46: 38 | DG46: 52 | DH46: 39 | DI46: n/a | DJ46: 83 | DK46: 78 | DL46: 42 | DM46: 47 | DN46: 74 | DO46: 49 | DP46: 13 | DQ46: 64 | DR46: 53 | DS46: 16 | DT46: 1 | DU46: 43 | DV46: 92 | DW46: 101 | DX46: 49 | DY46: 1 | DZ46: 117 | EA46: 71 | EB46: 115 | EC46: 79 | ED46: 35 | EE46: n/a | EF46: 24 | EG46: 42 | EH46: 98 | EI46: 44 | EJ46: 1 | EK46: 66 | EL46: 45 | EM46: 81 | EN46: 35 | EO46: 51 | EP46: 71 | EQ46: 100
A47: Hungary | B47: HUN | C47: Europe | D47: High-income | E47: 48156.868 | F47: 9686000 | G47: 55.257145 | H47: HU | I47: 41 | J47: 48.31009 | K47: 42.141877 | L47: 72.288456 | M47: 58.288157 | N47: 45 | O47: 60 | P47: 40 | Q47: 46 | R47: 77.513894 | S47: 32.614564 | T47: 34.80181 | U47: 54.742461 | V47: 33.991779 | W47: 37.691392 | X47: 79.597265 | Y47: 70.926581 | Z47: 66.341522 | AA47: 33.340927 | AB47: 64.12135 | AC47: 77.402195 | AD47: 33 | AE47: 47 | AF47: 62 | AG47: 49 | AH47: 52 | AI47: 71 | AJ47: 35 | AK47: 39 | AL47: 58 | AM47: 60 | AN47: 70 | AO47: 35 | AP47: 86.069202 | AQ47: 80.424399 | AR47: 35.126668 | AS47: 95.789474 | AT47: 67.673624 | AU47: 100 | AV47: 28.569266 | AW47: 27.950428 | AX47: 66.968109 | AY47: 6.9704543 | AZ47: 71.836044 | BA47: 28.25 | BB47: 20.948735 | BC47: 18.172463 | BD47: 16.643656 | BE47: 40.762441 | BF47: 78.277759 | BG47: 98.610308 | BH47: 39.41814 | BI47: 63.543689 | BJ47: 12.528416 | BK47: 43.524737 | BL47: 16.370274 | BM47: 65.636843 | BN47: n/a | BO47: 25.658934 | BP47: 21.778398 | BQ47: 87.926445 | BR47: 86.361562 | BS47: n/a | BT47: 64.503786 | BU47: 50.193952 | BV47: 86.875 | BW47: 55.618702 | BX47: 100 | BY47: 61.945251 | BZ47: 52.168853 | CA47: 78.791509 | CB47: 68.064205 | CC47: n/a | CD47: 17.698744 | CE47: 57.934914 | CF47: 42.124499 | CG47: 15.605549 | CH47: 59.316354 | CI47: 56.901042 | CJ47: 82.653061 | CK47: 69.640249 | CL47: 97.777778 | CM47: 57.854998 | CN47: 90.909091 | CO47: 79.978471 | CP47: 63.954658 | CQ47: 24 | CR47: 47 | CS47: 53 | CT47: 60 | CU47: 87 | CV47: 1 | CW47: 35 | CX47: 27 | CY47: 56 | CZ47: 55 | DA47: 38 | DB47: 98 | DC47: 22 | DD47: 61 | DE47: 59 | DF47: 81 | DG47: 34 | DH47: 15 | DI47: 14 | DJ47: 46 | DK47: 40 | DL47: 58 | DM47: 45 | DN47: 72 | DO47: n/a | DP47: 88 | DQ47: 33 | DR47: 20 | DS47: 67 | DT47: n/a | DU47: 27 | DV47: 55 | DW47: 27 | DX47: 46 | DY47: 1 | DZ47: 66 | EA47: 77 | EB47: 53 | EC47: 30 | ED47: n/a | EE47: 25 | EF47: 52 | EG47: 60 | EH47: 58 | EI47: 67 | EJ47: 93 | EK47: 26 | EL47: 53 | EM47: 42 | EN47: 29 | EO47: 28 | EP47: 47 | EQ47: 62
A48: Costa Rica | B48: CRI | C48: The Americas | D48: High-income | E48: 31485.04 | F48: 5106000 | G48: 54.75972 | H48: CR | I48: 42 | J48: 42.824687 | K48: 43.615131 | L48: 67.46591 | M48: 65.133151 | N48: 67 | O48: 54 | P48: 49 | Q48: 28 | R48: 63.604897 | S48: 19.550918 | T48: 45.318245 | U48: 54.229155 | V48: 43.809105 | W48: 32.807133 | X48: 53.883219 | Y48: 74.48365 | Z48: 74.030862 | AA48: 40.53994 | AB48: 80.974164 | AC48: 73.88535 | AD48: 78 | AE48: 84 | AF48: 37 | AG48: 51 | AH48: 34 | AI48: 87 | AJ48: 66 | AK48: 32 | AL48: 42 | AM48: 36 | AN48: 18 | AO48: 43 | AP48: 58.288321 | AQ48: 59.216959 | AR48: 29.757837 | AS48: 73.684211 | AT48: 74.387639 | AU48: 86.294418 | AV48: 13.000996 | AW48: 6.372815 | AX48: 58.266719 | AY48: 0.56314021 | AZ48: 68.058196 | BA48: 48.25 | BB48: n/a | BC48: 19.646539 | BD48: 6.6581037 | BE48: 66.895406 | BF48: 77.531013 | BG48: 96.958 | BH48: 23.103252 | BI48: 88.437632 | BJ48: n/a | BK48: 38.638887 | BL48: 4.3507967 | BM48: 66.517487 | BN48: 30.930688 | BO48: 28.537741 | BP48: 5.2426152 | BQ48: 61.182934 | BR48: 70.052947 | BS48: 61.226147 | BT48: 23.070845 | BU48: 55.830452 | BV48: 83.125 | BW48: 56.855579 | BX48: 100 | BY48: 76.607217 | BZ48: 71.011426 | CA48: 62.591645 | CB48: 69.927494 | CC48: 92.592883 | CD48: 0.39200393 | CE48: 47.866763 | CF48: 64.004204 | CG48: 49.896788 | CH48: 89.678284 | CI48: 91.666667 | CJ48: 43.877551 | CK48: 79.277529 | CL48: 100 | CM48: 27.382634 | CN48: 88.181818 | CO48: 91.38859 | CP48: 77.176713 | CQ48: 82 | CR48: 73 | CS48: 70 | CT48: 100 | CU48: 48 | CV48: 49 | CW48: 51 | CX48: 53 | CY48: 85 | CZ48: 104 | DA48: 43 | DB48: 48 | DC48: n/a | DD48: 54 | DE48: 87 | DF48: 36 | DG48: 39 | DH48: 27 | DI48: 31 | DJ48: 15 | DK48: n/a | DL48: 72 | DM48: 64 | DN48: 71 | DO48: 60 | DP48: 79 | DQ48: 69 | DR48: 66 | DS48: 87 | DT48: 15 | DU48: 67 | DV48: 46 | DW48: 38 | DX48: 43 | DY48: 1 | DZ48: 36 | EA48: 49 | EB48: 78 | EC48: 16 | ED48: 3 | EE48: 61 | EF48: 81 | EG48: 28 | EH48: 13 | EI48: 6 | EJ48: 14 | EK48: 102 | EL48: 32 | EM48: 1 | EN48: 57 | EO48: 34 | EP48: 10 | EQ48: 38
A49: Slovakia | B49: SVK | C49: Europe | D49: High-income | E49: 47596.544 | F49: 5518000 | G49: 54.674568 | H49: SK | I49: 43 | J49: 46.984012 | K49: 39.977383 | L49: 76.119061 | M49: 55.617816 | N49: 49 | O49: 69 | P49: 32 | Q49: 52 | R49: 78.469714 | S49: 28.862984 | T49: 33.619338 | U49: 43.97096 | V49: 33.580053 | W49: 42.381138 | X49: 85.815843 | Y49: 70.603228 | Z49: 71.938114 | AA49: 23.221623 | AB49: 70.348469 | AC49: 73.283357 | AD49: 28 | AE49: 53 | AF49: 67 | AG49: 94 | AH49: 53 | AI49: 63 | AJ49: 19 | AK49: 42 | AL49: 49 | AM49: 102 | AN49: 48 | AO49: 44 | AP49: 87.680987 | AQ49: 88.959105 | AR49: 29.947358 | AS49: 94.736842 | AT49: 69.493995 | AU49: 100 | AV49: 20.887202 | AW49: 22.379623 | AX49: 68.748036 | AY49: 3.4370748 | AZ49: n/a | BA49: 49.25 | BB49: 25.624362 | BC49: 25.983652 | BD49: 10.006044 | BE49: 43.973361 | BF49: 77.933474 | BG49: n/a | BH49: n/a | BI49: 69.003406 | BJ49: 9.6746064 | BK49: 41.290916 | BL49: 14.351283 | BM49: 65.073808 | BN49: 57.127464 | BO49: 30.98698 | BP49: 16.336298 | BQ49: 85.986089 | BR49: 93.327514 | BS49: n/a | BT49: 78.133927 | BU49: 57.291178 | BV49: 78.4375 | BW49: 53.983852 | BX49: 75 | BY49: 88.303608 | BZ49: 68.112569 | CA49: 83.895945 | CB49: 63.805827 | CC49: n/a | CD49: 4.2342618 | CE49: 52.202221 | CF49: n/a | CG49: 13.228385 | CH49: 66.152815 | CI49: 59.895833 | CJ49: 100 | CK49: 69.993515 | CL49: 100 | CM49: 49.780883 | CN49: 81.818182 | CO49: 73.412271 | CP49: 76.24418 | CQ49: 16 | CR49: 33 | CS49: 69 | CT49: 63 | CU49: 73 | CV49: 1 | CW49: 41 | CX49: 32 | CY49: 46 | CZ49: 75 | DA49: n/a | DB49: 44 | DC49: 18 | DD49: 32 | DE49: 76 | DF49: 78 | DG49: 36 | DH49: n/a | DI49: n/a | DJ49: 39 | DK49: 48 | DL49: 62 | DM49: 48 | DN49: 73 | DO49: 22 | DP49: 75 | DQ49: 39 | DR49: 24 | DS49: 48 | DT49: n/a | DU49: 17 | DV49: 44 | DW49: 49 | DX49: 48 | DY49: 72 | DZ49: 15 | EA49: 53 | EB49: 43 | EC49: 66 | ED49: n/a | EE49: 39 | EF49: 71 | EG49: n/a | EH49: 63 | EI49: 48 | EJ49: 86 | EK49: 1 | EL49: 52 | EM49: 1 | EN49: 39 | EO49: 56 | EP49: 74 | EQ49: 40
A50: Thailand | B50: THA | C50: Asia & Pacific | D50: Upper middle-income | E50: 26358.583 | F50: 71702000 | G50: 54.539157 | H50: TH | I50: 44 | J50: 48.069151 | K50: 45.924789 | L50: 69.55081 | M50: 54.611879 | N50: 46 | O50: 46 | P50: 46 | Q50: 58 | R50: 76.747478 | S50: 26.575278 | T50: 40.884698 | U50: 68.35777 | V50: 21.322529 | W50: 48.09407 | X50: 68.721892 | Y50: 63.558142 | Z50: 76.372395 | AA50: 31.339937 | AB50: 76.379027 | AC50: 56.116673 | AD50: 36 | AE50: 59 | AF50: 44 | AG50: 13 | AH50: 103 | AI50: 40 | AJ50: 51 | AK50: 60 | AL50: 35 | AM50: 68 | AN50: 29 | AO50: 89 | AP50: 66.713306 | AQ50: 52.461374 | AR50: 60.837593 | AS50: 94.736842 | AT50: 85.832572 | AU50: 99.903179 | AV50: 5.0757387 | AW50: 2.8685327 | AX50: 65.94039 | AY50: 32.416449 | AZ50: 77.065122 | BA50: 54.5 | BB50: 7.5418451 | BC50: 24.431823 | BD50: 56.887576 | BE50: 56.712641 | BF50: 73.523372 | BG50: 86.30749 | BH50: n/a | BI50: 40.012913 | BJ50: 0.7851573 | BK50: n/a | BL50: 23.169517 | BM50: 71.252752 | BN50: 53.441695 | BO50: 49.488448 | BP50: 18.193384 | BQ50: 64.856587 | BR50: 99.061351 | BS50: 57.565646 | BT50: 53.403985 | BU50: 46.188722 | BV50: 76.875 | BW50: 43.213092 | BX50: 100 | BY50: 51.513895 | BZ50: 73.910284 | CA50: 88.74873 | CB50: 63.860203 | CC50: 78.970366 | CD50: 0.34761526 | CE50: 71.069959 | CF50: 52.925006 | CG50: 1.0171684 | CH50: 66.175156 | CI50: 88.932292 | CJ50: 75.255102 | CK50: 72.804161 | CL50: 100 | CM50: 23.39181 | CN50: 68.181818 | CO50: 69.106566 | CP50: 27.572996 | CQ50: 63 | CR50: 81 | CS50: 11 | CT50: 63 | CU50: 10 | CV50: 36 | CW50: 75 | CX50: 71 | CY50: 58 | CZ50: 26 | DA50: 28 | DB50: 37 | DC50: 32 | DD50: 38 | DE50: 8 | DF50: 53 | DG50: 54 | DH50: 57 | DI50: n/a | DJ50: 80 | DK50: 90 | DL50: n/a | DM50: 36 | DN50: 62 | DO50: 27 | DP50: 37 | DQ50: 35 | DR50: 60 | DS50: 21 | DT50: 18 | DU50: 41 | DV50: 63 | DW50: 53 | DX50: 66 | DY50: 1 | DZ50: 86 | EA50: 42 | EB50: 32 | EC50: 64 | ED50: 16 | EE50: 62 | EF50: 21 | EG50: 46 | EH50: 122 | EI50: 47 | EJ50: 19 | EK50: 44 | EL50: 41 | EM50: 1 | EN50: 65 | EO50: 93 | EP50: 83 | EQ50: 114
A51: India | B51: IND | C51: Asia & Pacific | D51: Lower middle-income | E51: 12100.965 | F51: 1438070000 | G51: 54.429209 | H51: IN | I51: 45 | J51: 53.073727 | K51: 48.812405 | L51: 56.617055 | M51: 59.213648 | N51: 33 | O51: 34 | P51: 73 | Q51: 42 | R51: 75.745078 | S51: 44.267136 | T51: 39.208967 | U51: 50.702042 | V51: 50.004371 | W51: 45.730802 | X51: 47.917532 | Y51: 64.796843 | Z51: 57.13679 | AA51: 56.536569 | AB51: 61.193922 | AC51: 59.910453 | AD51: 40 | AE51: 30 | AF51: 47 | AG51: 68 | AH51: 24 | AI51: 52 | AJ51: 78 | AK51: 56 | AL51: 80 | AM51: 14 | AN51: 77 | AO51: 83 | AP51: 65.726021 | AQ51: 73.790832 | AR51: 80.027042 | AS51: 95.052632 | AT51: 96.409755 | AU51: 43.464189 | AV51: 5.5194936 | AW51: 1.0949056 | AX51: 70.454146 | AY51: 100 | AZ51: 68.487607 | BA51: 64.25 | BB51: 1.0211713 | BC51: 23.07709 | BD51: 92.028205 | BE51: 21.598633 | BF51: 31.00979 | BG51: 72.307692 | BH51: 36.565887 | BI51: 41.263317 | BJ51: 12.433924 | BK51: 100 | BL51: 46.320243 | BM51: 78.154738 | BN51: 48.860666 | BO51: 45.812337 | BP51: 10.095467 | BQ51: 57.126886 | BR51: 98.188878 | BS51: 18.291014 | BT51: 18.063352 | BU51: 38.80077 | BV51: 81.25 | BW51: 64.053725 | BX51: 100 | BY51: 39.879718 | BZ51: 63.764283 | CA51: 49.039751 | CB51: 34.744247 | CC51: 80.998881 | CD51: 1.4108982 | CE51: 92.023288 | CF51: 32.712089 | CG51: 100 | CH51: 25.223414 | CI51: 87.239583 | CJ51: 95.663265 | CK51: 46.574272 | CL51: 62.222222 | CM51: n/a | CN51: 62.727273 | CO51: 71.905274 | CP51: 27.975402 | CQ51: 66 | CR51: 55 | CS51: 2 | CT51: 62 | CU51: 2 | CV51: 65 | CW51: 70 | CX51: 93 | CY51: 36 | CZ51: 1 | DA51: 42 | DB51: 26 | DC51: 48 | DD51: 44 | DE51: 2 | DF51: 108 | DG51: 101 | DH51: 70 | DI51: 17 | DJ51: 78 | DK51: 41 | DL51: 1 | DM51: 12 | DN51: 44 | DO51: 31 | DP51: 42 | DQ51: 55 | DR51: 71 | DS51: 29 | DT51: 48 | DU51: 75 | DV51: 78 | DW51: 41 | DX51: 34 | DY51: 1 | DZ51: 101 | EA51: 61 | EB51: 95 | EC51: 96 | ED51: 12 | EE51: 49 | EF51: 3 | EG51: 70 | EH51: 1 | EI51: 106 | EJ51: 26 | EK51: 3 | EL51: 104 | EM51: 94 | EN51: n/a | EO51: 102 | EP51: 79 | EQ51: 112
A52: Ukraine | B52: UKR | C52: Europe | D52: Upper middle-income | E52: 20903.942 | F52: 37733000 | G52: 54.300282 | H52: UA | I52: 46 | J52: 44.84676 | K52: 46.661275 | L52: 69.679654 | M52: 56.013439 | N52: 59 | O52: 43 | P52: 45 | Q52: 49 | R52: 68.806665 | S52: 31.127001 | T52: 34.606615 | U52: 68.716015 | V52: 23.072641 | W52: 48.195168 | X52: 71.339431 | Y52: 58.420826 | Z52: 79.278706 | AA52: 51.932946 | AB52: 55.509174 | AC52: 60.598199 | AD52: 63 | AE52: 49 | AF52: 63 | AG52: 12 | AH52: 93 | AI52: 39 | AJ52: 48 | AK52: 74 | AL52: 26 | AM52: 19 | AN52: 91 | AO52: 78 | AP52: 74.784465 | AQ52: 52.363864 | AR52: 59.044893 | AS52: 52.631579 | AT52: 75.022749 | AU52: 98.992439 | AV52: 20.101891 | AW52: 5.4307211 | AX52: 74.50647 | AY52: 24.468923 | AZ52: 65.044155 | BA52: 40.5 | BB52: 0.077552076 | BC52: 32.804752 | BD52: n/a | BE52: 73.68726 | BF52: 63.744771 | BG52: n/a | BH52: n/a | BI52: n/a | BJ52: 7.1758221 | BK52: 44.786308 | BL52: 17.255793 | BM52: 98.238712 | BN52: 55.394937 | BO52: 34.083576 | BP52: 5.0634465 | BQ52: 74.126902 | BR52: 80.701681 | BS52: n/a | BT52: 59.18971 | BU52: 35.561138 | BV52: 61.25 | BW52: 33.990626 | BX52: 100 | BY52: 61.302364 | BZ52: 100 | CA52: 76.846876 | CB52: 56.081307 | CC52: 84.186643 | CD52: 1.9192595 | CE52: 61.576794 | CF52: 70.578562 | CG52: 73.657167 | CH52: 31.724754 | CI52: 57.942708 | CJ52: 95.408163 | CK52: 58.311954 | CL52: 91.111111 | CM52: 42.251942 | CN52: 78.181818 | CO52: 57.588805 | CP52: 37.629349 | CQ52: 50 | CR52: 82 | CS52: 12 | CT52: 109 | CU52: 45 | CV52: 37 | CW52: 42 | CX52: 57 | CY52: 18 | CZ52: 34 | DA52: 52 | DB52: 61 | DC52: 55 | DD52: 25 | DE52: n/a | DF52: 25 | DG52: 71 | DH52: n/a | DI52: n/a | DJ52: n/a | DK52: 59 | DL52: 53 | DM52: 44 | DN52: 5 | DO52: 23 | DP52: 71 | DQ52: 70 | DR52: 46 | DS52: 75 | DT52: n/a | DU52: 36 | DV52: 85 | DW52: 80 | DX52: 80 | DY52: 1 | DZ52: 68 | EA52: 1 | EB52: 57 | EC52: 83 | ED52: 7 | EE52: 47 | EF52: 44 | EG52: 22 | EH52: 5 | EI52: 100 | EJ52: 92 | EK52: 4 | EL52: 85 | EM52: 53 | EN52: 42 | EO52: 62 | EP52: 101 | EQ52: 102
A53: Serbia | B53: SRB | C53: Europe | D53: Upper middle-income | E53: 32741.865 | F53: 6773000 | G53: 54.153166 | H53: RS | I53: 47 | J53: 40.171786 | K53: 43.468892 | L53: 69.151112 | M53: 63.820874 | N53: 78 | O53: 55 | P53: 47 | Q53: 31 | R53: 68.63631 | S53: 27.417044 | T53: 24.462005 | U53: 58.377857 | V53: 30.054194 | W53: 41.974625 | X53: 67.039229 | Y53: 68.212358 | Z53: 72.20175 | AA53: 54.314611 | AB53: 71.510782 | AC53: 65.637229 | AD53: 65 | AE53: 55 | AF53: 99 | AG53: 35 | AH53: 66 | AI53: 64 | AJ53: 53 | AK53: 47 | AL53: 48 | AM53: 16 | AN53: 44 | AO53: 59 | AP53: 69.504718 | AQ53: 70.254041 | AR53: 31.080105 | AS53: 97.578947 | AT53: 74.763738 | AU53: n/a | AV53: 26.31455 | AW53: 6.2880094 | AX53: 70.36671 | AY53: 6.6989075 | AZ53: 61.181069 | BA53: 31.25 | BB53: 2.9480166 | BC53: 2.4689343 | BD53: 13.765623 | BE53: 44.329322 | BF53: 76.954945 | BG53: 98.461538 | BH53: n/a | BI53: 57.745909 | BJ53: 3.7599887 | BK53: 48.475004 | BL53: 10.235874 | BM53: 82.431636 | BN53: n/a | BO53: 29.699528 | BP53: 13.792712 | BQ53: 76.25594 | BR53: 96.17356 | BS53: 56.383468 | BT53: 39.343947 | BU53: 45.679669 | BV53: 79.0625 | BW53: 33.967899 | BX53: 100 | BY53: 82.351721 | BZ53: 88.40457 | CA53: 70.322067 | CB53: 57.403762 | CC53: 72.676601 | CD53: n/a | CE53: 49.709988 | CF53: n/a | CG53: 58.919234 | CH53: 74.754245 | CI53: 68.098958 | CJ53: 77.040816 | CK53: 66.317472 | CL53: 82.222222 | CM53: 43.512092 | CN53: 90.909091 | CO53: 63.078579 | CP53: 47.876086 | CQ53: 59 | CR53: 57 | CS53: 64 | CT53: 56 | CU53: 46 | CV53: n/a | CW53: 37 | CX53: 54 | CY53: 37 | CZ53: 58 | DA53: 63 | DB53: 89 | DC53: 42 | DD53: 111 | DE53: 67 | DF53: 77 | DG53: 42 | DH53: 16 | DI53: n/a | DJ53: 57 | DK53: 72 | DL53: 38 | DM53: 52 | DN53: 36 | DO53: n/a | DP53: 77 | DQ53: 44 | DR53: 41 | DS53: 41 | DT53: 20 | DU53: 53 | DV53: 64 | DW53: 48 | DX53: 81 | DY53: 1 | DZ53: 23 | EA53: 19 | EB53: 69 | EC53: 81 | ED53: 24 | EE53: n/a | EF53: 74 | EG53: n/a | EH53: 9 | EI53: 28 | EJ53: 69 | EK53: 39 | EL53: 64 | EM53: 69 | EN53: 41 | EO53: 28 | EP53: 95 | EQ53: 83
A54: Uruguay | B54: URY | C54: The Americas | D54: High-income | E54: 37190.134 | F54: 3388000 | G54: 54.038317 | H54: UY | I54: 48 | J54: 45.359588 | K54: 43.904205 | L54: 65.452215 | M54: 61.43726 | N54: 57 | O54: 53 | P54: 53 | Q54: 39 | R54: 74.039974 | S54: 25.186085 | T54: 36.852704 | U54: 50.239107 | V54: 31.944513 | W54: 49.528995 | X54: 65.891507 | Y54: 71.812885 | Z54: 58.652253 | AA54: 35.215925 | AB54: 75.834929 | AC54: 73.260926 | AD54: 47 | AE54: 63 | AF54: 56 | AG54: 69 | AH54: 59 | AI54: 36 | AJ54: 54 | AK54: 36 | AL54: 76 | AM54: 55 | AN54: 31 | AO54: 45 | AP54: 79.277703 | AQ54: 90.389839 | AR54: 34.130481 | AS54: 75.789474 | AT54: 64.652349 | AU54: 100 | AV54: 18.337796 | AW54: 10.765401 | AX54: 71.124811 | AY54: 0.51633311 | AZ54: 65.735836 | BA54: 27 | BB54: n/a | BC54: 17.822276 | BD54: 9.3917374 | BE54: 59.164952 | BF54: 80.948298 | BG54: 98.32489 | BH54: 3.3656589 | BI54: 79.912153 | BJ54: 6.3240079 | BK54: 37.606001 | BL54: 3.9358893 | BM54: 85.949399 | BN54: 67.891077 | BO54: 34.490113 | BP54: 9.7853914 | BQ54: 67.985283 | BR54: 93.631009 | BS54: n/a | BT54: 36.058229 | BU54: 59.122778 | BV54: 45.3125 | BW54: 65.184932 | BX54: 100 | BY54: 89.444214 | BZ54: 85.505713 | CA54: 64.615108 | CB54: 69.880232 | CC54: 14.607959 | CD54: 0.7349625 | CE54: 45.378875 | CF54: 50.130509 | CG54: 44.619353 | CH54: 75.983021 | CI54: 87.109375 | CJ54: 58.673469 | CK54: 70.151314 | CL54: 100 | CM54: 36.166592 | CN54: 83.636364 | CO54: 85.791173 | CP54: 74.899147 | CQ54: 37 | CR54: 29 | CS54: 57 | CT54: 98 | CU54: 103 | CV54: 1 | CW54: 45 | CX54: 43 | CY54: 30 | CZ54: 107 | DA54: 48 | DB54: 102 | DC54: n/a | DD54: 62 | DE54: 82 | DF54: 44 | DG54: 26 | DH54: 21 | DI54: 45 | DJ54: 28 | DK54: 61 | DL54: 80 | DM54: 67 | DN54: 28 | DO54: 15 | DP54: 69 | DQ54: 56 | DR54: 57 | DS54: 47 | DT54: n/a | DU54: 55 | DV54: 40 | DW54: 102 | DX54: 31 | DY54: 1 | DZ54: 13 | EA54: 22 | EB54: 75 | EC54: 17 | ED54: 77 | EE54: 54 | EF54: 87 | EG54: 49 | EH54: 16 | EI54: 26 | EJ54: 27 | EK54: 83 | EL54: 50 | EM54: 1 | EN54: 47 | EO54: 47 | EP54: 29 | EQ54: 41
A55: Indonesia | B55: IDN | C55: Asia & Pacific | D55: Upper middle-income | E55: 17633.888 | F55: 281190000 | G55: 53.749828 | H55: ID | I55: 49 | J55: 56.969718 | K55: 47.686577 | L55: 57.767676 | M55: 52.575339 | N55: 26 | O55: 37 | P55: 70 | Q55: 71 | R55: 83.567708 | S55: 39.851496 | T55: 47.489951 | U55: 59.290111 | V55: 30.479202 | W55: 53.29042 | X55: 56.755655 | Y55: 53.393528 | Z55: 63.153845 | AA55: 39.724287 | AB55: 67.965086 | AC55: 50.036644 | AD55: 8 | AE55: 36 | AF55: 28 | AG55: 29 | AH55: 64 | AI55: 30 | AJ55: 62 | AK55: 83 | AL55: 67 | AM55: 38 | AN55: 58 | AO55: 106 | AP55: 73.851297 | AQ55: 86.461931 | AR55: 66.91319 | AS55: 95.526316 | AT55: 91.848328 | AU55: 86.805183 | AV55: 4.6322575 | AW55: 1.7376624 | AX55: 65.914486 | AY55: 87.121577 | AZ55: 83.935923 | BA55: 62.75 | BB55: 0.64803352 | BC55: 42.625849 | BD55: 64.314366 | BE55: 80.049942 | BF55: 52.991945 | BG55: 93.846154 | BH55: 5.248146 | BI55: 37.739452 | BJ55: 1.8888884 | BK55: 61.543763 | BL55: 20.744703 | BM55: 76.354952 | BN55: 42.165751 | BO55: 90.300673 | BP55: 4.3403056 | BQ55: 64.297725 | BR55: 100 | BS55: 32.915674 | BT55: 29.809222 | BU55: 49.77027 | BV55: 19.375 | BW55: 62.194002 | BX55: 100 | BY55: 35.62837 | BZ55: 78.25857 | CA55: 55.52951 | CB55: 53.71022 | CC55: 65.117078 | CD55: 0.021611843 | CE55: 80.275721 | CF55: 71.299438 | CG55: 7.3003777 | CH55: 52.658624 | CI55: 87.760417 | CJ55: 71.683673 | CK55: 55.268761 | CL55: 44.444444 | CM55: 13.055111 | CN55: 57.272727 | CO55: 77.825619 | CP55: 59.541792 | CQ55: 52 | CR55: 37 | CS55: 6 | CT55: 61 | CU55: 5 | CV55: 48 | CW55: 80 | CX55: 85 | CY55: 59 | CZ55: 8 | DA55: 17 | DB55: 28 | DC55: 52 | DD55: 19 | DE55: 5 | DF55: 13 | DG55: 86 | DH55: 39 | DI55: 42 | DJ55: 84 | DK55: 82 | DL55: 13 | DM55: 40 | DN55: 51 | DO55: 43 | DP55: 4 | DQ55: 75 | DR55: 61 | DS55: 1 | DT55: 39 | DU55: 60 | DV55: 56 | DW55: 123 | DX55: 37 | DY55: 1 | DZ55: 106 | EA55: 35 | EB55: 86 | EC55: 87 | ED55: 40 | EE55: 78 | EF55: 8 | EG55: 21 | EH55: 82 | EI55: 79 | EJ55: 22 | EK55: 59 | EL55: 91 | EM55: 100 | EN55: 72 | EO55: 108 | EP55: 58 | EQ55: 70
A56: Qatar | B56: QAT | C56: Arab States | D56: High-income | E56: 122283.22 | F56: 2979000 | G56: 53.668917 | H56: QA | I56: 50 | J56: 51.562683 | K56: 45.700006 | L56: 64.295585 | M56: 53.117395 | N56: 36 | O56: 47 | P56: 56 | Q56: 67 | R56: 77.568737 | S56: 17.676848 | T56: 59.442464 | U56: 69.563342 | V56: 15.640233 | W56: 51.896445 | X56: 74.475072 | Y56: 62.619231 | Z56: 55.792452 | AA56: 43.732502 | AB56: 71.167329 | AC56: 44.452354 | AD56: 32 | AE56: 92 | AF56: 13 | AG56: 8 | AH56: 123 | AI56: 32 | AJ56: 42 | AK56: 64 | AL56: 85 | AM56: 32 | AN56: 45 | AO56: 117 | AP56: 87.605063 | AQ56: 94.658988 | AR56: 12.526721 | AS56: 100 | AT56: 70.621653 | AU56: 100 | AV56: 4.4056056 | AW56: 3.3770157 | AX56: 61.2871 | AY56: 1.63767 | AZ56: 83.097807 | BA56: 71 | BB56: n/a | BC56: 24.229584 | BD56: 9.4121606 | BE56: 84.379754 | BF56: 87.538375 | BG56: 96.923077 | BH56: n/a | BI56: n/a | BJ56: 2.4478484 | BK56: 39.519623 | BL56: 4.9532259 | BM56: 71.786913 | BN56: 40.425836 | BO56: 84.72555 | BP56: 10.647483 | BQ56: 48.950144 | BR56: 100 | BS56: n/a | BT56: n/a | BU56: 66.678457 | BV56: 49.6875 | BW56: 73.202618 | BX56: 75 | BY56: 48.527582 | BZ56: 44.932289 | CA56: n/a | CB56: 66.652614 | CC56: n/a | CD56: n/a | CE56: 55.713425 | CF56: 65.490773 | CG56: 9.9933085 | CH56: 69.571046 | CI56: n/a | CJ56: 71.173469 | CK56: 74.353754 | CL56: 91.111111 | CM56: 34.973949 | CN56: 6.3636364 | CO56: 43.918192 | CP56: 93.996167 | CQ56: 17 | CR56: 21 | CS56: 108 | CT56: 1 | CU56: 67 | CV56: 1 | CW56: 81 | CX56: 68 | CY56: 76 | CZ56: 89 | DA56: 19 | DB56: 17 | DC56: n/a | DD56: 39 | DE56: 81 | DF56: 8 | DG56: 7 | DH56: 28 | DI56: n/a | DJ56: n/a | DK56: 77 | DL56: 69 | DM56: 62 | DN56: 58 | DO56: 44 | DP56: 8 | DQ56: 52 | DR56: 89 | DS56: 1 | DT56: n/a | DU56: n/a | DV56: 31 | DW56: 97 | DX56: 25 | DY56: 72 | DZ56: 91 | EA56: 87 | EB56: n/a | EC56: 41 | ED56: n/a | EE56: n/a | EF56: 60 | EG56: 27 | EH56: 75 | EI56: 41 | EJ56: n/a | EK56: 60 | EL56: 40 | EM56: 53 | EN56: 49 | EO56: 126 | EP56: 115 | EQ56: 12
A57: Brazil | B57: BRA | C57: The Americas | D57: Upper middle-income | E57: 23309.631 | F57: 211141000 | G57: 53.643451 | H57: BR | I57: 51 | J57: 45.986087 | K57: 44.277842 | L57: 70.847422 | M57: 53.462451 | N57: 53 | O57: 52 | P57: 41 | Q57: 63 | R57: 66.816806 | S57: 37.896523 | T57: 33.244932 | U57: 46.418963 | V57: 41.112838 | W57: 45.301727 | X57: 68.500537 | Y57: 69.832483 | Z57: 74.209245 | AA57: 29.985593 | AB57: 64.241249 | AC57: 66.160511 | AD57: 71 | AE57: 40 | AF57: 70 | AG57: 83 | AH57: 39 | AI57: 54 | AJ57: 52 | AK57: 43 | AL57: 40 | AM57: 75 | AN57: 68 | AO57: 58 | AP57: 68.827942 | AQ57: 58.216356 | AR57: 73.52417 | AS57: 61.315789 | AT57: 79.209 | AU57: 59.807579 | AV57: 12.442017 | AW57: 6.7575304 | AX57: 70.567086 | AY57: 61.819457 | AZ57: 62.322176 | BA57: 39 | BB57: 2.1887382 | BC57: 29.468814 | BD57: 42.39883 | BE57: 26.305088 | BF57: 71.390107 | BG57: 92.000788 | BH57: 0 | BI57: 51.221076 | BJ57: 7.6649461 | BK57: 57.709987 | BL57: 47.855342 | BM57: 88.72848 | BN57: 46.333062 | BO57: 28.169004 | BP57: 17.976363 | BQ57: 71.233709 | BR57: 95.848577 | BS57: 59.200348 | BT57: 47.719516 | BU57: 34.809127 | BV57: 92.5 | BW57: 45.494929 | BX57: 100 | BY57: 76.358358 | BZ57: 85.505713 | CA57: 76.671317 | CB57: 64.897052 | CC57: 69.762897 | CD57: 1.0471942 | CE57: 80.364531 | CF57: 26.881646 | CG57: 11.649001 | CH57: 72.252011 | CI57: 76.302083 | CJ57: 29.081633 | CK57: 59.257675 | CL57: 100 | CM57: 24.796023 | CN57: 78.181818 | CO57: 74.811625 | CP57: 73.705155 | CQ57: 61 | CR57: 75 | CS57: 3 | CT57: 107 | CU57: 26 | CV57: 59 | CW57: 53 | CX57: 51 | CY57: 33 | CZ57: 10 | DA57: 60 | DB57: 64 | DC57: 47 | DD57: 26 | DE57: 19 | DF57: 104 | DG57: 60 | DH57: 51 | DI57: 47 | DJ57: 67 | DK57: 55 | DL57: 18 | DM57: 9 | DN57: 21 | DO57: 37 | DP57: 81 | DQ57: 36 | DR57: 50 | DS57: 43 | DT57: 16 | DU57: 47 | DV57: 88 | DW57: 11 | DX57: 59 | DY57: 1 | DZ57: 38 | EA57: 22 | EB57: 58 | EC57: 55 | ED57: 30 | EE57: 53 | EF57: 7 | EG57: 83 | EH57: 68 | EI57: 33 | EJ57: 55 | EK57: 109 | EL57: 82 | EM57: 1 | EN57: 62 | EO57: 62 | EP57: 66 | EQ57: 47
A58: Romania | B58: ROU | C58: Europe | D58: High-income | E58: 48847.461 | F58: 19118000 | G58: 53.162763 | H58: RO | I58: 52 | J58: 43.997184 | K58: 39.188017 | L58: 65.66965 | M58: 63.796204 | N58: 61 | O58: 71 | P58: 52 | Q58: 32 | R58: 74.723234 | S58: 27.164904 | T58: 30.103413 | U58: 54.204816 | V58: 26.694461 | W58: 36.664773 | X58: 75.780893 | Y58: 66.989763 | Z58: 54.238293 | AA58: 44.533087 | AB58: 75.92241 | AC58: 70.933114 | AD58: 45 | AE58: 57 | AF58: 85 | AG58: 52 | AH58: 78 | AI58: 76 | AJ58: 39 | AK58: 51 | AL58: 87 | AM58: 28 | AN58: 30 | AO58: 47 | AP58: 94.04021 | AQ58: 64.522801 | AR58: 47.592667 | AS58: 98.105263 | AT58: 69.355231 | AU58: n/a | AV58: 19.498337 | AW58: 9.6998313 | AX58: 68.545442 | AY58: 10.916007 | AZ58: 66.123375 | BA58: 31.25 | BB58: 5.5481157 | BC58: 17.492162 | BD58: 23.240658 | BE58: 57.511393 | BF58: 72.700394 | BG58: 98.461538 | BH58: 19.110097 | BI58: 44.952007 | BJ58: 5.3120296 | BK58: 44.027672 | BL58: 12.486134 | BM58: 58.466573 | BN58: 40.303963 | BO58: 39.827922 | BP58: 8.0606325 | BQ58: 82.243875 | BR58: 89.930023 | BS58: 86.629646 | BT58: 44.32003 | BU58: 50.208748 | BV58: 90.625 | BW58: 48.397521 | BX58: 75 | BY58: 70.717545 | BZ58: 66.66314 | CA58: 38.452585 | CB58: 66.372606 | CC58: 45.464839 | CD58: 2.2561794 | CE58: 64.546277 | CF58: 55.27511 | CG58: 56.054781 | CH58: 73.793566 | CI58: 78.515625 | CJ58: 84.693878 | CK58: 66.222201 | CL58: 95.555556 | CM58: 37.451269 | CN58: 86.363636 | CO58: 90.635091 | CP58: 43.009365 | CQ58: 7 | CR58: 63 | CS58: 25 | CT58: 52 | CU58: 77 | CV58: n/a | CW58: 44 | CX58: 45 | CY58: 48 | CZ58: 47 | DA58: 47 | DB58: 89 | DC58: 38 | DD58: 64 | DE58: 43 | DF58: 50 | DG58: 56 | DH58: 16 | DI58: 35 | DJ58: 71 | DK58: 63 | DL58: 56 | DM58: 49 | DN58: 81 | DO58: 46 | DP58: 53 | DQ58: 62 | DR58: 35 | DS58: 61 | DT58: 2 | DU58: 50 | DV58: 54 | DW58: 16 | DX58: 54 | DY58: 72 | DZ58: 47 | EA58: 58 | EB58: 108 | EC58: 44 | ED58: 56 | EE58: 45 | EF58: 33 | EG58: 41 | EH58: 10 | EI58: 32 | EJ58: 51 | EK58: 22 | EL58: 65 | EM58: 46 | EN58: 45 | EO58: 40 | EP58: 13 | EQ58: 92
A59: Croatia | B59: HRV | C59: Europe | D59: High-income | E59: 51453.311 | F59: 3896000 | G59: 53.075753 | H59: HR | I59: 53 | J59: 41.818628 | K59: 41.669151 | L59: 74.565334 | M59: 54.249898 | N59: 71 | O59: 63 | P59: 35 | Q59: 61 | R59: 73.501331 | S59: 29.456631 | T59: 22.497923 | U59: 49.980993 | V59: 32.328814 | W59: 42.697645 | X59: 72.120774 | Y59: 73.660933 | Z59: 77.914296 | AA59: 28.027131 | AB59: 56.316194 | AC59: 78.406369 | AD59: 50 | AE59: 52 | AF59: 104 | AG59: 70 | AH59: 57 | AI59: 62 | AJ59: 46 | AK59: 34 | AL59: 30 | AM59: 84 | AN59: 89 | AO59: 32 | AP59: 88.69299 | AQ59: 90.258774 | AR59: 18.660022 | AS59: 98.894737 | AT59: 71.000133 | AU59: n/a | AV59: 30.427542 | AW59: 16.694241 | AX59: 67.150273 | AY59: 3.5544682 | AZ59: 58.933939 | BA59: 25.25 | BB59: 2.5152337 | BC59: 3.2925182 | BD59: 15.609106 | BE59: 38.157395 | BF59: 75.675299 | BG59: 99.128308 | BH59: 21.334855 | BI59: 66.957859 | BJ59: 8.3444602 | BK59: 43.499692 | BL59: 10.513246 | BM59: 84.777613 | BN59: 37.708339 | BO59: 26.505554 | BP59: 21.799073 | BQ59: 82.885051 | BR59: 85.919562 | BS59: 69.884245 | BT59: 49.79424 | BU59: 58.34174 | BV59: 88.75 | BW59: 42.677045 | BX59: 100 | BY59: 78.535877 | BZ59: 91.303428 | CA59: 85.275703 | CB59: 56.641853 | CC59: 78.4362 | CD59: 1.8236851 | CE59: 49.48495 | CF59: 31.361552 | CG59: 29.438336 | CH59: 58.310992 | CI59: 30.46875 | CJ59: 83.928571 | CK59: 76.409108 | CL59: 100 | CM59: 56.424219 | CN59: 90.909091 | CO59: 85.25296 | CP59: 62.078415 | CQ59: 12 | CR59: 30 | CS59: 94 | CT59: 46 | CU59: 66 | CV59: n/a | CW59: 33 | CX59: 38 | CY59: 55 | CZ59: 74 | DA59: 68 | DB59: 105 | DC59: 45 | DD59: 107 | DE59: 64 | DF59: 87 | DG59: 47 | DH59: 13 | DI59: 34 | DJ59: 42 | DK59: 53 | DL59: 59 | DM59: 51 | DN59: 31 | DO59: 48 | DP59: 83 | DQ59: 32 | DR59: 32 | DS59: 68 | DT59: 8 | DU59: 45 | DV59: 43 | DW59: 22 | DX59: 69 | DY59: 1 | DZ59: 30 | EA59: 15 | EB59: 38 | EC59: 82 | ED59: 17 | EE59: 48 | EF59: 75 | EG59: 74 | EH59: 29 | EI59: 70 | EJ59: 117 | EK59: 25 | EL59: 34 | EM59: 1 | EN59: 34 | EO59: 28 | EP59: 33 | EQ59: 66
A60: Greece | B60: GRC | C60: Europe | D60: High-income | E60: 44985.382 | F60: 10243000 | G60: 52.975226 | H60: GR | I60: 54 | J60: 46.098929 | K60: 41.163709 | L60: 72.522716 | M60: 52.11555 | N60: 52 | O60: 65 | P60: 39 | Q60: 75 | R60: 72.952029 | S60: 31.737995 | T60: 33.606763 | U60: 46.080975 | V60: 31.30758 | W60: 46.102571 | X60: 81.64638 | Y60: 65.629901 | Z60: 70.291868 | AA60: 28.475718 | AB60: 51.659501 | AC60: 76.211431 | AD60: 53 | AE60: 48 | AF60: 69 | AG60: 85 | AH60: 61 | AI60: 48 | AJ60: 29 | AK60: 54 | AL60: 51 | AM60: 82 | AN60: 94 | AO60: 37 | AP60: 75.859061 | AQ60: 89.582012 | AR60: 22.776308 | AS60: 99.473684 | AT60: 77.069079 | AU60: n/a | AV60: 24.651491 | AW60: 21.96972 | AX60: 60.350345 | AY60: 19.980423 | AZ60: 60.142684 | BA60: 23.5 | BB60: 4.2258075 | BC60: 46.55856 | BD60: 18.778406 | BE60: 53.594699 | BF60: 77.495578 | BG60: n/a | BH60: 34.45522 | BI60: 57.509583 | BJ60: 8.8528658 | BK60: 44.214564 | BL60: 14.653307 | BM60: 77.686746 | BN60: 43.609021 | BO60: 39.650187 | BP60: 23.46433 | BQ60: 77.805036 | BR60: 96.625465 | BS60: n/a | BT60: 70.508639 | BU60: 56.716017 | BV60: 83.125 | BW60: 43.213092 | BX60: 75 | BY60: 70.095396 | BZ60: 65.213711 | CA60: 84.618176 | CB60: 61.043716 | CC60: n/a | CD60: 3.8307665 | CE60: 57.680886 | CF60: 42.616235 | CG60: 9.774986 | CH60: 56.210903 | CI60: 19.791667 | CJ60: 75.510204 | CK60: 82.441665 | CL60: 93.333333 | CM60: 40.984385 | CN60: 100 | CO60: 84.391819 | CP60: 65.605704 | CQ60: 47 | CR60: 32 | CS60: 88 | CT60: 29 | CU60: 35 | CV60: n/a | CW60: 39 | CX60: 33 | CY60: 79 | CZ60: 35 | DA60: 65 | DB60: 108 | DC60: 40 | DD60: 15 | DE60: 54 | DF60: 60 | DG60: 40 | DH60: n/a | DI60: 19 | DJ60: 58 | DK60: 51 | DL60: 55 | DM60: 46 | DN60: 45 | DO60: 40 | DP60: 56 | DQ60: 29 | DR60: 39 | DS60: 36 | DT60: n/a | DU60: 20 | DV60: 45 | DW60: 34 | DX60: 66 | DY60: 72 | DZ60: 50 | EA60: 59 | EB60: 40 | EC60: 75 | ED60: n/a | EE60: 40 | EF60: 53 | EG60: 59 | EH60: 77 | EI60: 78 | EJ60: 120 | EK60: 42 | EL60: 29 | EM60: 50 | EN60: 43 | EO60: 1 | EP60: 35 | EQ60: 58
A61: Bulgaria | B61: BGR | C61: Europe | D61: High-income | E61: 42477.288 | F61: 6796000 | G61: 52.941194 | H61: BG | I61: 55 | J61: 46.114181 | K61: 44.488135 | L61: 68.639804 | M61: 52.522657 | N61: 51 | O61: 51 | P61: 48 | Q61: 72 | R61: 73.026853 | S61: 31.052907 | T61: 34.262783 | U61: 57.341891 | V61: 28.634377 | W61: 47.488136 | X61: 63.448846 | Y61: 76.458326 | Z61: 66.012238 | AA61: 38.302755 | AB61: 57.413431 | AC61: 61.851784 | AD61: 51 | AE61: 50 | AF61: 65 | AG61: 38 | AH61: 72 | AI61: 42 | AJ61: 58 | AK61: 29 | AL61: 59 | AM61: 43 | AN61: 87 | AO61: 69 | AP61: 74.055551 | AQ61: 75.776943 | AR61: 36.90244 | AS61: 99.947368 | AT61: 78.451961 | AU61: n/a | AV61: 36.256336 | AW61: 15.81949 | AX61: 68.347071 | AY61: 3.7887328 | AZ61: 72.030561 | BA61: 46.5 | BB61: 3.4070845 | BC61: 15.113487 | BD61: 16.215877 | BE61: 47.892685 | BF61: 67.727617 | BG61: 97.531385 | BH61: n/a | BI61: 45.531512 | BJ61: 15.731724 | BK61: 41.219809 | BL61: 12.054463 | BM61: 72.655526 | BN61: 52.676602 | BO61: 52.2118 | BP61: 12.408614 | BQ61: 87.263855 | BR61: 69.430397 | BS61: 56.44185 | BT61: 40.659282 | BU61: 52.435841 | BV61: 88.75 | BW61: 59.231051 | BX61: 100 | BY61: 81.874741 | BZ61: 65.213711 | CA61: 72.770585 | CB61: 64.311874 | CC61: 61.752784 | CD61: 2.7975855 | CE61: 52.255567 | CF61: 52.953096 | CG61: 45.204771 | CH61: 51.251117 | CI61: 60.416667 | CJ61: 59.94898 | CK61: 61.196038 | CL61: 84.444444 | CM61: 31.771123 | CN61: 86.363636 | CO61: 68.353068 | CP61: 37.394175 | CQ61: 51 | CR61: 51 | CS61: 48 | CT61: 25 | CU61: 28 | CV61: n/a | CW61: 30 | CX61: 39 | CY61: 51 | CZ61: 73 | DA61: 36 | DB61: 50 | DC61: 41 | DD61: 71 | DE61: 61 | DF61: 69 | DG61: 67 | DH61: 25 | DI61: n/a | DJ61: 70 | DK61: 36 | DL61: 63 | DM61: 50 | DN61: 57 | DO61: 29 | DP61: 33 | DQ61: 48 | DR61: 21 | DS61: 90 | DT61: 19 | DU61: 52 | DV61: 51 | DW61: 22 | DX61: 41 | DY61: 1 | DZ61: 26 | EA61: 59 | EB61: 64 | EC61: 61 | ED61: 44 | EE61: 44 | EF61: 70 | EG61: 45 | EH61: 15 | EI61: 81 | EJ61: 85 | EK61: 80 | EL61: 78 | EM61: 68 | EN61: 50 | EO61: 40 | EP61: 86 | EQ61: 103
A62: Russian Federation | B62: RUS | C62: CIS | D62: High-income | E62: 49048.991 | F62: 145441000 | G62: 52.013781 | H62: RU | I62: 56 | J62: 43.939304 | K62: 51.761554 | L62: 61.262545 | M62: 51.091722 | N62: 62 | O62: 32 | P62: 63 | Q62: 79 | R62: 78.652905 | S62: 29.599633 | T62: 23.565373 | U62: 80.894965 | V62: 28.513665 | W62: 45.876032 | X62: 75.112145 | Y62: 36.277441 | Z62: 72.398051 | AA62: 30.620329 | AB62: 61.995849 | AC62: 60.658986 | AD62: 25 | AE62: 51 | AF62: 100 | AG62: 2 | AH62: 73 | AI62: 50 | AJ62: 41 | AK62: 117 | AL62: 47 | AM62: 70 | AN62: 76 | AO62: 77 | AP62: 82.964218 | AQ62: 78.050153 | AR62: 65.630726 | AS62: 84.210526 | AT62: 82.408904 | AU62: n/a | AV62: 12.736234 | AW62: 11.211272 | AX62: 69.8096 | AY62: 24.641425 | AZ62: n/a | BA62: 48.75 | BB62: 0.91806466 | BC62: 21.028054 | BD62: 66.163898 | BE62: n/a | BF62: 76.520998 | BG62: 100 | BH62: n/a | BI62: n/a | BJ62: 0 | BK62: 60.408172 | BL62: 25.132824 | BM62: 73.123519 | BN62: 49.997873 | BO62: n/a | BP62: 14.506705 | BQ62: 81.91916 | BR62: 90.537135 | BS62: n/a | BT62: 52.880139 | BU62: 14.148961 | BV62: 22.1875 | BW62: 49.623533 | BX62: 75 | BY62: 20.427209 | BZ62: 62.314854 | CA62: 87.591433 | CB62: 67.287866 | CC62: n/a | CD62: 2.8199967 | CE62: 84.0261 | CF62: n/a | CG62: 5.0148915 | CH62: 59.986595 | CI62: 59.635417 | CJ62: 76.530612 | CK62: 56.200459 | CL62: 97.777778 | CM62: 59.561149 | CN62: 60.909091 | CO62: 45.10226 | CP62: 56.349111 | CQ62: 31 | CR62: 49 | CS62: 9 | CT62: 91 | CU62: 17 | CV62: n/a | CW62: 52 | CX62: 42 | CY62: 41 | CZ62: 33 | DA62: n/a | DB62: 47 | DC62: 49 | DD62: 49 | DE62: 4 | DF62: n/a | DG62: 44 | DH62: 1 | DI62: n/a | DJ62: n/a | DK62: 92 | DL62: 15 | DM62: 32 | DN62: 56 | DO62: 30 | DP62: n/a | DQ62: 43 | DR62: 36 | DS62: 58 | DT62: n/a | DU62: 44 | DV62: 124 | DW62: 121 | DX62: 52 | DY62: 72 | DZ62: 121 | EA62: 65 | EB62: 35 | EC62: 39 | ED62: n/a | EE62: 43 | EF62: 4 | EG62: n/a | EH62: 94 | EI62: 64 | EJ62: 87 | EK62: 41 | EL62: 89 | EM62: 42 | EN62: 24 | EO62: 105 | EP62: 112 | EQ62: 73
A63: Chile | B63: CHL | C63: The Americas | D63: High-income | E63: 35286.468 | F63: 19659000 | G63: 51.865645 | H63: CL | I63: 57 | J63: 44.006108 | K63: 39.028148 | L63: 69.951874 | M63: 54.47645 | N63: 60 | O63: 73 | P63: 43 | Q63: 59 | R63: 71.633758 | S63: 22.368691 | T63: 38.015875 | U63: 52.557509 | V63: 25.023574 | W63: 39.50336 | X63: 65.298397 | Y63: 70.734847 | Z63: 73.822379 | AA63: 26.618386 | AB63: 68.04039 | AC63: 68.770574 | AD63: 54 | AE63: 73 | AF63: 50 | AG63: 60 | AH63: 85 | AI63: 67 | AJ63: 56 | AK63: 40 | AL63: 43 | AM63: 92 | AN63: 57 | AO63: 52 | AP63: 77.89149 | AQ63: 65.880749 | AR63: 45.39067 | AS63: 89.473684 | AT63: 79.532196 | AU63: n/a | AV63: 9.9331847 | AW63: 9.3524624 | AX63: 63.958174 | AY63: 6.2309444 | AZ63: 65.651748 | BA63: 38.5 | BB63: 0.66265665 | BC63: 47.249097 | BD63: 34.394303 | BE63: 47.540022 | BF63: 81.530738 | BG63: 93.846154 | BH63: 5.4763263 | BI63: n/a | BJ63: 4.6054331 | BK63: 48.536444 | BL63: 21.928845 | BM63: 83.300249 | BN63: 46.938549 | BO63: 21.695442 | BP63: 6.0792002 | BQ63: 75.588856 | BR63: 64.242912 | BS63: n/a | BT63: 56.063424 | BU63: 65.394465 | BV63: 68.125 | BW63: 49.95568 | BX63: 100 | BY63: 70.199088 | BZ63: 82.606856 | CA63: 97.530366 | CB63: 67.70233 | CC63: 47.449966 | CD63: 2.0347508 | CE63: 61.847573 | CF63: 38.388825 | CG63: 4.2023935 | CH63: 69.280608 | CI63: 69.661458 | CJ63: 51.020408 | CK63: 79.337798 | CL63: 100 | CM63: 40.135241 | CN63: 70.909091 | CO63: 77.179763 | CP63: 73.716398 | CQ63: 41 | CR63: 62 | CS63: 30 | CT63: 83 | CU63: 24 | CV63: n/a | CW63: 55 | CX63: 46 | CY63: 67 | CZ63: 61 | DA63: 49 | DB63: 66 | DC63: 51 | DD63: 13 | DE63: 28 | DF63: 71 | DG63: 21 | DH63: 39 | DI63: 41 | DJ63: n/a | DK63: 65 | DL63: 37 | DM63: 38 | DN63: 33 | DO63: 34 | DP63: 92 | DQ63: 66 | DR63: 43 | DS63: 92 | DT63: n/a | DU63: 40 | DV63: 33 | DW63: 73 | DX63: 51 | DY63: 1 | DZ63: 49 | EA63: 29 | EB63: 9 | EC63: 36 | ED63: 55 | EE63: 46 | EF63: 42 | EG63: 64 | EH63: 97 | EI63: 43 | EJ63: 65 | EK63: 93 | EL63: 31 | EM63: 1 | EN63: 44 | EO63: 84 | EP63: 59 | EQ63: 46
A64: Mauritius | B64: MUS | C64: Africa | D64: Upper middle-income | E64: 33023.741 | F64: 1274000 | G64: 51.791654 | H64: MU | I64: 58 | J64: 40.591433 | K64: 45.648693 | L64: 62.461133 | M64: 58.465358 | N64: 76 | O64: 48 | P64: 59 | Q64: 45 | R64: 67.13111 | S64: 20.12431 | T64: 34.518881 | U64: 51.304526 | V64: 55.69012 | W64: 29.951432 | X64: 61.849249 | Y64: 61.355345 | Z64: 64.178805 | AA64: 30.202698 | AB64: 63.645976 | AC64: 81.5474 | AD64: 69 | AE64: 80 | AF64: 64 | AG64: 66 | AH64: 17 | AI64: 90 | AJ64: 60 | AK64: 69 | AL64: 64 | AM64: 74 | AN64: 72 | AO64: 24 | AP64: 65.024882 | AQ64: 54.728623 | AR64: 23.341825 | AS64: 94.736842 | AT64: 64.954485 | AU64: 100 | AV64: 7.3440152 | AW64: 8.4796172 | AX64: 64.178314 | AY64: 0.49529179 | AZ64: 55.649459 | BA64: 35 | BB64: n/a | BC64: 12.907183 | BD64: 3.9682886 | BE64: 40.618666 | BF64: 69.359579 | BG64: 91.271572 | BH64: n/a | BI64: 66.72608 | BJ64: 100 | BK64: n/a | BL64: 0.34427929 | BM64: 50.712816 | BN64: n/a | BO64: 35.537248 | BP64: 3.6042317 | BQ64: 61.708995 | BR64: 100 | BS64: n/a | BT64: 23.838753 | BU64: 68.866553 | BV64: 63.4375 | BW64: 43.365245 | BX64: 100 | BY64: 31.107424 | BZ64: 37.685146 | CA64: 76.99074 | CB64: 61.124232 | CC64: 80.915103 | CD64: n/a | CE64: 33.956595 | CF64: 38.215234 | CG64: 18.436265 | CH64: 57.46202 | CI64: 67.317708 | CJ64: 66.836735 | CK64: 65.479663 | CL64: 68.888889 | CM64: n/a | CN64: 84.545455 | CO64: 89.558665 | CP64: 72.187273 | CQ64: 68 | CR64: 77 | CS64: 86 | CT64: 63 | CU64: 101 | CV64: 1 | CW64: 61 | CX64: 50 | CY64: 66 | CZ64: 108 | DA64: 72 | DB64: 78 | DC64: n/a | DD64: 74 | DE64: 101 | DF64: 82 | DG64: 63 | DH64: 52 | DI64: n/a | DJ64: 43 | DK64: 1 | DL64: n/a | DM64: 111 | DN64: 92 | DO64: n/a | DP64: 67 | DQ64: 80 | DR64: 64 | DS64: 1 | DT64: n/a | DU64: 65 | DV64: 29 | DW64: 78 | DX64: 65 | DY64: 1 | DZ64: 112 | EA64: 98 | EB64: 56 | EC64: 74 | ED64: 13 | EE64: n/a | EF64: 117 | EG64: 65 | EH64: 51 | EI64: 76 | EJ64: 74 | EK64: 68 | EL64: 69 | EM64: 86 | EN64: n/a | EO64: 45 | EP64: 15 | EQ64: 49
A65: Oman | B65: OMN | C65: Arab States | D65: High-income | E65: 42211.199 | F65: 5049000 | G65: 51.611439 | H65: OM | I65: 59 | J65: 43.654411 | K65: 42.051625 | L65: 66.299308 | M65: 54.44041 | N65: 65 | O65: 61 | P65: 51 | Q65: 60 | R65: 70.150315 | S65: 19.862506 | T65: 40.950412 | U65: 62.126219 | V65: 19.520821 | W65: 44.507836 | X65: 55.495775 | Y65: 62.812382 | Z65: 80.589766 | AA65: 39.459797 | AB65: 74.768398 | AC65: 49.093035 | AD65: 62 | AE65: 82 | AF65: 43 | AG65: 23 | AH65: 109 | AI65: 58 | AJ65: 65 | AK65: 63 | AL65: 21 | AM65: 40 | AN65: 36 | AO65: 107 | AP65: 61.497815 | AQ65: 66.186164 | AR65: 20.224393 | AS65: 100 | AT65: 72.993516 | AU65: 100 | AV65: 3.0221423 | AW65: 1.0700205 | AX65: 69.572017 | AY65: 5.7858451 | AZ65: 69.969781 | BA65: 50 | BB65: n/a | BC65: 2.8814547 | BD65: 6.8030255 | BE65: 74.531565 | BF65: 71.78567 | BG65: 95.384615 | BH65: n/a | BI65: n/a | BJ65: 10.770507 | BK65: 45.084003 | BL65: 2.7079516 | BM65: 76.869864 | BN65: 14.983996 | BO65: 80.471173 | BP65: 5.7063086 | BQ65: 45.300911 | BR65: 96.398562 | BS65: n/a | BT65: 24.787852 | BU65: 53.102516 | BV65: 81.25 | BW65: 55.590772 | BX65: 100 | BY65: 24.118623 | BZ65: 63.764283 | CA65: 85.219594 | CB65: 73.375189 | CC65: 100 | CD65: n/a | CE65: 51.147912 | CF65: 63.948655 | CG65: 3.2828259 | CH65: 65.616622 | CI65: 89.322917 | CJ65: n/a | CK65: 63.962912 | CL65: 77.777778 | CM65: n/a | CN65: 21.818182 | CO65: 43.918192 | CP65: 85.307686 | CQ65: 75 | CR65: 60 | CS65: 91 | CT65: 1 | CU65: 55 | CV65: 1 | CW65: 93 | CX65: 94 | CY65: 43 | CZ65: 63 | DA65: 41 | DB65: 42 | DC65: n/a | DD65: 110 | DE65: 85 | DF65: 23 | DG65: 59 | DH65: 34 | DI65: n/a | DJ65: n/a | DK65: 45 | DL65: 52 | DM65: 73 | DN65: 48 | DO65: 81 | DP65: 9 | DQ65: 67 | DR65: 95 | DS65: 38 | DT65: n/a | DU65: 63 | DV65: 49 | DW65: 41 | DX65: 47 | DY65: 1 | DZ65: 116 | EA65: 61 | EB65: 39 | EC65: 7 | ED65: 1 | EE65: n/a | EF65: 73 | EG65: 29 | EH65: 104 | EI65: 50 | EJ65: 18 | EK65: n/a | EL65: 74 | EM65: 76 | EN65: n/a | EO65: 124 | EP65: 115 | EQ65: 27
A66: Turkiye | B66: TUR | C66: Europe | D66: Upper middle-income | E66: 43786.195 | F66: 87271000 | G66: 51.274282 | H66: TR | I66: 60 | J66: 50.218249 | K66: 44.982408 | L66: 63.751496 | M66: 46.144977 | N66: 40 | O66: 50 | P66: 58 | Q66: 94 | R66: 80.313679 | S66: 38.644306 | T66: 31.696761 | U66: 51.239052 | V66: 31.470372 | W66: 52.237799 | X66: 74.301475 | Y66: 59.345013 | Z66: 57.607998 | AA66: 29.756732 | AB66: 34.591879 | AC66: 74.08632 | AD66: 17 | AE66: 38 | AF66: 75 | AG66: 67 | AH66: 60 | AI66: 31 | AJ66: 43 | AK66: 72 | AL66: 78 | AM66: 76 | AN66: 119 | AO66: 41 | AP66: 84.446244 | AQ66: 62.540067 | AR66: 51.215278 | AS66: 98.947368 | AT66: 84.733115 | AU66: 100 | AV66: 6.1799212 | AW66: 9.0067722 | AX66: 73.378302 | AY66: 66.012229 | AZ66: 65.586986 | BA66: 27.5 | BB66: 5.6123853 | BC66: 28.087674 | BD66: 46.942444 | BE66: 35.946438 | BF66: 70.163634 | BG66: 95.384615 | BH66: 7.7581289 | BI66: 44.218816 | BJ66: 2.1766436 | BK66: 56.62863 | BL66: 22.857398 | BM66: 90.679852 | BN66: n/a | BO66: 43.688778 | BP66: 22.344767 | BQ66: 75.021776 | BR66: 100 | BS66: 74.599367 | BT66: 47.584758 | BU66: 36.484976 | BV66: 85.9375 | BW66: 43.153691 | BX66: 100 | BY66: 31.148901 | BZ66: 85.505713 | CA66: 66.440927 | CB66: 53.989388 | CC66: 24.495967 | CD66: 5.3421515 | CE66: 77.436715 | CF66: 29.400922 | CG66: 6.8471375 | CH66: 44.727435 | CI66: 0 | CJ66: 47.193878 | CK66: 70.902526 | CL66: 91.111111 | CM66: 51.443398 | CN66: 74.545455 | CO66: 84.391819 | CP66: 80.818104 | CQ66: 29 | CR66: 70 | CS66: 18 | CT66: 43 | CU66: 12 | CV66: 1 | CW66: 67 | CX66: 47 | CY66: 24 | CZ66: 9 | DA66: 50 | DB66: 101 | DC66: 37 | DD66: 28 | DE66: 12 | DF66: 91 | DG66: 62 | DH66: 34 | DI66: 40 | DJ66: 74 | DK66: 79 | DL66: 21 | DM66: 37 | DN66: 13 | DO66: n/a | DP66: 46 | DQ66: 31 | DR66: 45 | DS66: 1 | DT66: 7 | DU66: 48 | DV66: 84 | DW66: 30 | DX66: 68 | DY66: 1 | DZ66: 111 | EA66: 22 | EB66: 72 | EC66: 86 | ED66: 71 | EE66: 36 | EF66: 12 | EG66: 76 | EH66: 84 | EI66: 89 | EJ66: 124 | EK66: 97 | EL66: 46 | EM66: 53 | EN66: 37 | EO66: 72 | EP66: 35 | EQ66: 32
A67: Georgia | B67: GEO | C67: Europe | D67: Upper middle-income | E67: 31089.681 | F67: 3807000 | G67: 51.112501 | H67: GE | I67: 61 | J67: 43.7278 | K67: 43.209354 | L67: 65.171207 | M67: 52.341645 | N67: 64 | O67: 57 | P67: 54 | Q67: 74 | R67: 73.774219 | S67: 24.801875 | T67: 32.607307 | U67: 59.660297 | V67: 32.058866 | W67: 37.9089 | X67: 62.389572 | Y67: 74.045507 | Z67: 59.07854 | AA67: 37.018635 | AB67: 64.600248 | AC67: 55.40605 | AD67: 49 | AE67: 66 | AF67: 73 | AG67: 27 | AH67: 58 | AI67: 70 | AJ67: 59 | AK67: 33 | AL67: 74 | AM67: 47 | AN67: 67 | AO67: 93 | AP67: 80.299086 | AQ67: 55.956619 | AR67: 36.728308 | AS67: 99.473684 | AT67: 70.187614 | AU67: 100 | AV67: 27.819599 | AW67: 5.0966427 | AX67: 65.57677 | AY67: 0.71448914 | AZ67: 64.238133 | BA67: 30 | BB67: n/a | BC67: 3.5837878 | BD67: 8.8522431 | BE67: 48.477297 | BF67: 81.311649 | BG67: 100 | BH67: n/a | BI67: 61.1561 | BJ67: n/a | BK67: 34.244074 | BL67: 0.77642307 | BM67: 47.693122 | BN67: 34.329516 | BO67: 65.711904 | BP67: 3.9010586 | BQ67: 69.34624 | BR67: 90.47993 | BS67: 59.193627 | BT67: 30.538493 | BU67: 65.916139 | BV67: 87.8125 | BW67: 45.905782 | BX67: 100 | BY67: 70.593115 | BZ67: 53.618282 | CA67: 63.314967 | CB67: 68.952437 | CC67: 50.428476 | CD67: 1.0900054 | CE67: 43.52509 | CF67: 63.56139 | CG67: 39.898055 | CH67: 47.810545 | CI67: 78.125 | CJ67: 74.234694 | CK67: 61.495707 | CL67: 73.333333 | CM67: 18.711143 | CN67: 82.727273 | CO67: 76.318622 | CP67: 14.400992 | CQ67: 36 | CR67: 76 | CS67: 49 | CT67: 29 | CU67: 69 | CV67: 1 | CW67: 36 | CX67: 60 | CY67: 62 | CZ67: 101 | DA67: 55 | DB67: 94 | DC67: n/a | DD67: 103 | DE67: 83 | DF67: 68 | DG67: 22 | DH67: 1 | DI67: n/a | DJ67: 52 | DK67: n/a | DL67: 96 | DM67: 100 | DN67: 94 | DO67: 54 | DP67: 22 | DQ67: 78 | DR67: 55 | DS67: 59 | DT67: 17 | DU67: 59 | DV67: 32 | DW67: 25 | DX67: 58 | DY67: 1 | DZ67: 48 | EA67: 76 | EB67: 77 | EC67: 24 | ED67: 52 | EE67: 52 | EF67: 90 | EG67: 31 | EH67: 21 | EI67: 86 | EJ67: 52 | EK67: 50 | EL67: 77 | EM67: 81 | EN67: 67 | EO67: 51 | EP67: 60 | EQ67: 124
A68: Armenia | B68: ARM | C68: CIS | D68: Upper middle-income | E68: 23954.238 | F68: 2943000 | G68: 50.851488 | H68: AM | I68: 62 | J68: 44.983741 | K68: 38.414374 | L68: 61.388214 | M68: 58.619622 | N68: 58 | O68: 74 | P68: 62 | Q68: 43 | R68: 71.424174 | S68: 25.122117 | T68: 38.404932 | U68: 52.850968 | V68: 28.922447 | W68: 33.469708 | X68: 43.306403 | Y68: 63.017356 | Z68: 77.840884 | AA68: 35.345568 | AB68: 66.514771 | AC68: 73.998527 | AD68: 55 | AE68: 64 | AF68: 48 | AG68: 58 | AH68: 71 | AI68: 85 | AJ68: 92 | AK68: 62 | AL68: 31 | AM68: 54 | AN68: 63 | AO68: 42 | AP68: 75.820118 | AQ68: 54.413327 | AR68: 30.591415 | AS68: 100 | AT68: 67.720184 | AU68: 100 | AV68: 24.057632 | AW68: 5.5574071 | AX68: 70.251249 | AY68: 0.62217872 | AZ68: 62.675322 | BA68: 46.25 | BB68: n/a | BC68: 6.2894731 | BD68: 6.3385364 | BE68: 47.809158 | BF68: 57.501326 | BG68: 99.75485 | BH68: n/a | BI68: 66.385061 | BJ68: 14.634053 | BK68: 34.072005 | BL68: 0.59866916 | BM68: 75.000301 | BN68: 18.318274 | BO68: 37.789727 | BP68: 2.7705298 | BQ68: 60.034116 | BR68: 44.682511 | BS68: 42.599482 | BT68: 25.909502 | BU68: 43.42043 | BV68: 76.5625 | BW68: 59.154035 | BX68: 75 | BY68: 60.949813 | BZ68: 84.056284 | CA68: 71.715328 | CB68: 77.499934 | CC68: 78.091988 | CD68: 0.14100009 | CE68: 39.601106 | CF68: 46.057121 | CG68: 55.583046 | CH68: 49.910634 | CI68: 70.572917 | CJ68: 91.326531 | CK68: 66.794992 | CL68: 73.333333 | CM68: n/a | CN68: 86.363636 | CO68: 75.457481 | CP68: 47.015594 | CQ68: 48 | CR68: 79 | CS68: 66 | CT68: 1 | CU68: 86 | CV68: 1 | CW68: 40 | CX68: 56 | CY68: 40 | CZ68: 103 | DA68: 58 | DB68: 51 | DC68: n/a | DD68: 90 | DE68: 89 | DF68: 70 | DG68: 79 | DH68: 9 | DI68: n/a | DJ68: 45 | DK68: 38 | DL68: 98 | DM68: 102 | DN68: 53 | DO68: 79 | DP68: 62 | DQ68: 85 | DR68: 67 | DS68: 108 | DT68: 29 | DU68: 62 | DV68: 71 | DW68: 54 | DX68: 42 | DY68: 72 | DZ68: 71 | EA68: 27 | EB68: 66 | EC68: 5 | ED68: 18 | EE68: 71 | EF68: 100 | EG68: 53 | EH68: 11 | EI68: 83 | EJ68: 63 | EK68: 12 | EL68: 60 | EM68: 81 | EN68: n/a | EO68: 40 | EP68: 64 | EQ68: 84
A69: Colombia | B69: COL | C69: The Americas | D69: Upper middle-income | E69: 22396.001 | F69: 52321000 | G69: 49.674015 | H69: CO | I69: 63 | J69: 43.743634 | K69: 47.609534 | L69: 54.510762 | M69: 52.832129 | N69: 63 | O69: 39 | P69: 78 | Q69: 68 | R69: 67.305039 | S69: 24.606817 | T69: 39.319046 | U69: 63.140744 | V69: 34.718269 | W69: 44.969588 | X69: 41.992329 | Y69: 66.424871 | Z69: 55.115087 | AA69: 29.113008 | AB69: 59.149345 | AC69: 70.234035 | AD69: 67 | AE69: 67 | AF69: 46 | AG69: 19 | AH69: 50 | AI69: 55 | AJ69: 98 | AK69: 53 | AL69: 86 | AM69: 81 | AN69: 84 | AO69: 49 | AP69: 59.192206 | AQ69: 62.975041 | AR69: 50.111133 | AS69: 100 | AT69: 84.383905 | AU69: 47.16795 | AV69: 8.9740791 | AW69: 15.300988 | AX69: 61.698095 | AY69: 12.454107 | AZ69: 67.103899 | BA69: 38.75 | BB69: n/a | BC69: 12.10324 | BD69: 31.192549 | BE69: 56.1833 | BF69: 72.34905 | BG69: 92.838076 | BH69: n/a | BI69: 76.274616 | BJ69: 4.1072387 | BK69: n/a | BL69: 23.772954 | BM69: 70.176008 | BN69: 67.920588 | BO69: 39.722783 | BP69: 2.0589707 | BQ69: 56.527686 | BR69: 58.821382 | BS69: 36.172376 | BT69: 16.447871 | BU69: 44.756726 | BV69: 77.5 | BW69: 47.507613 | BX69: 100 | BY69: 62.360017 | BZ69: 72.460855 | CA69: 38.964276 | CB69: 72.296651 | CC69: 36.738569 | CD69: 0.30069472 | CE69: 66.778366 | CF69: 37.0648 | CG69: 12.308173 | CH69: 61.304736 | CI69: 69.401042 | CJ69: 23.214286 | CK69: 70.270226 | CL69: 100 | CM69: 26.235572 | CN69: 77.272727 | CO69: 90.850377 | CP69: 73.154932 | CQ69: 80 | CR69: 68 | CS69: 20 | CT69: 1 | CU69: 13 | CV69: 63 | CW69: 57 | CX69: 40 | CY69: 73 | CZ69: 45 | DA69: 45 | DB69: 65 | DC69: n/a | DD69: 78 | DE69: 34 | DF69: 55 | DG69: 58 | DH69: 47 | DI69: n/a | DJ69: 33 | DK69: 68 | DL69: n/a | DM69: 34 | DN69: 65 | DO69: 14 | DP69: 54 | DQ69: 92 | DR69: 72 | DS69: 99 | DT69: 35 | DU69: 81 | DV69: 68 | DW69: 51 | DX69: 55 | DY69: 1 | DZ69: 65 | EA69: 46 | EB69: 107 | EC69: 10 | ED69: 61 | EE69: 65 | EF69: 31 | EG69: 67 | EH69: 67 | EI69: 59 | EJ69: 66 | EK69: 110 | EL69: 49 | EM69: 1 | EN69: 61 | EO69: 68 | EP69: 12 | EQ69: 48
A70: Montenegro | B70: MNE | C70: Europe | D70: Upper middle-income | E70: 34407.847 | F70: 634000 | G70: 49.203183 | H70: ME | I70: 64 | J70: 45.822625 | K70: 38.168046 | L70: 60.043604 | M70: 52.778457 | N70: 56 | O70: 75 | P70: 65 | Q70: 69 | R70: 55.848437 | S70: 52.566843 | T70: 29.052594 | U70: 55.682422 | V70: 34.814201 | W70: 24.007514 | X70: 46.564419 | Y70: 68.107519 | Z70: 65.458876 | AA70: 30.269188 | AB70: 66.218409 | AC70: 61.847772 | AD70: 97 | AE70: 13 | AF70: 87 | AG70: 44 | AH70: 49 | AI70: 104 | AJ70: 84 | AK70: 48 | AL70: 60 | AM70: 72 | AN70: 64 | AO70: 70 | AP70: 33.980368 | AQ70: 74.585367 | AR70: 14.097104 | AS70: 90 | AT70: 66.579346 | AU70: n/a | AV70: 30.53833 | AW70: 100 | AX70: 79.391758 | AY70: 0.33728484 | AZ70: n/a | BA70: 33.5 | BB70: n/a | BC70: 24.605189 | BD70: 2.9246109 | BE70: n/a | BF70: 66.377424 | BG70: 97.745232 | BH70: n/a | BI70: 71.045656 | BJ70: n/a | BK70: 32.147806 | BL70: 1.2491411 | BM70: 42.423696 | BN70: n/a | BO70: n/a | BP70: 5.5913315 | BQ70: 70.606144 | BR70: 69.753349 | BS70: 25.309936 | BT70: 20.588246 | BU70: 51.592623 | BV70: 86.875 | BW70: 34.649814 | BX70: 100 | BY70: 67.420158 | BZ70: 47.820567 | CA70: 62.287292 | CB70: 69.800828 | CC70: 81.926816 | CD70: n/a | CE70: 25.961422 | CF70: n/a | CG70: 34.576955 | CH70: 58.467382 | CI70: 68.229167 | CJ70: 73.214286 | CK70: 70.703074 | CL70: 82.222222 | CM70: 27.790522 | CN70: 78.181818 | CO70: 80.301399 | CP70: 40.012476 | CQ70: 114 | CR70: 52 | CS70: 105 | CT70: 82 | CU70: 95 | CV70: n/a | CW70: 32 | CX70: 1 | CY70: 8 | CZ70: 109 | DA70: n/a | DB70: 85 | DC70: n/a | DD70: 37 | DE70: 108 | DF70: n/a | DG70: 68 | DH70: 24 | DI70: n/a | DJ70: 37 | DK70: n/a | DL70: 104 | DM70: 90 | DN70: 99 | DO70: n/a | DP70: n/a | DQ70: 68 | DR70: 52 | DS70: 89 | DT70: 43 | DU70: 72 | DV70: 52 | DW70: 27 | DX70: 79 | DY70: 1 | DZ70: 53 | EA70: 83 | EB70: 79 | EC70: 18 | ED70: 11 | EE70: n/a | EF70: 124 | EG70: n/a | EH70: 25 | EI70: 69 | EJ70: 68 | EK70: 54 | EL70: 47 | EM70: 69 | EN70: 55 | EO70: 62 | EP70: 46 | EQ70: 96
A71: Kazakhstan | B71: KAZ | C71: CIS | D71: Upper middle-income | E71: 44777.865 | F71: 20330000 | G71: 49.056882 | H71: KZ | I71: 65 | J71: 38.932376 | K71: 41.084784 | L71: 61.401442 | M71: 54.808924 | N71: 81 | O71: 66 | P71: 61 | Q71: 56 | R71: 70.698649 | S71: 19.68563 | T71: 26.412851 | U71: 55.943062 | V71: 18.588437 | W71: 48.722854 | X71: 69.66057 | Y71: 37.074261 | Z71: 77.469495 | AA71: 29.439559 | AB71: 74.828263 | AC71: 60.158949 | AD71: 58 | AE71: 83 | AF71: 94 | AG71: 41 | AH71: 113 | AI71: 38 | AJ71: 49 | AK71: 115 | AL71: 32 | AM71: 78 | AN71: 35 | AO71: 82 | AP71: 86.381456 | AQ71: 64.395269 | AR71: 37.361661 | AS71: 58.947368 | AT71: 77.106138 | AU71: 100 | AV71: 5.3787857 | AW71: 2.5900772 | AX71: 64.507011 | AY71: 6.2666446 | AZ71: 41.779828 | BA71: 37 | BB71: n/a | BC71: 0.45872388 | BD71: 33.085532 | BE71: 22.157317 | BF71: 68.758322 | BG71: 99.771077 | BH71: n/a | BI71: 24.894398 | BJ71: 0.80634183 | BK71: 45.102295 | BL71: 3.550712 | BM71: 92.66491 | BN71: 54.054243 | BO71: 45.976304 | BP71: 2.19596 | BQ71: 71.202238 | BR71: 92.855185 | BS71: 65.524418 | BT71: 49.060438 | BU71: 43.878869 | BV71: 2.5 | BW71: 41.429182 | BX71: 75 | BY71: 22.563252 | BZ71: 84.056284 | CA71: 87.292624 | CB71: 64.765962 | CC71: 73.763112 | CD71: 0.48602462 | CE71: 63.840845 | CF71: 46.788412 | CG71: 6.6429542 | CH71: 69.660411 | CI71: 82.552083 | CJ71: 86.22449 | CK71: 58.320098 | CL71: 100 | CM71: 30.707163 | CN71: 64.545455 | CO71: 61.571582 | CP71: 67.623196 | CQ71: 20 | CR71: 64 | CS71: 47 | CT71: 108 | CU71: 34 | CV71: 1 | CW71: 72 | CX71: 74 | CY71: 65 | CZ71: 60 | DA71: 91 | DB71: 72 | DC71: n/a | DD71: 125 | DE71: 29 | DF71: 107 | DG71: 65 | DH71: 8 | DI71: n/a | DJ71: 100 | DK71: 89 | DL71: 51 | DM71: 71 | DN71: 10 | DO71: 25 | DP71: 41 | DQ71: 90 | DR71: 51 | DS71: 49 | DT71: 11 | DU71: 46 | DV71: 70 | DW71: 125 | DX71: 72 | DY71: 72 | DZ71: 118 | EA71: 27 | EB71: 36 | EC71: 56 | ED71: 23 | EE71: 60 | EF71: 38 | EG71: 52 | EH71: 87 | EI71: 40 | EJ71: 37 | EK71: 18 | EL71: 84 | EM71: 1 | EN71: 52 | EO71: 97 | EP71: 99 | EQ71: 55
A72: Philippines | B72: PHL | C72: Asia & Pacific | D72: Lower middle-income | E72: 12920.042 | F72: 114891000 | G72: 48.894878 | H72: PH | I72: 66 | J72: 40.77576 | K72: 49.164289 | L72: 50.218492 | M72: 55.420971 | N72: 74 | O72: 33 | P72: 92 | Q72: 53 | R72: 60.412673 | S72: 25.059045 | T72: 36.855563 | U72: 73.775791 | V72: 27.562639 | W72: 46.154438 | X72: 43.799402 | Y72: 59.537134 | Z72: 47.318938 | AA72: 44.088597 | AB72: 70.734454 | AC72: 51.439862 | AD72: 84 | AE72: 65 | AF72: 55 | AG72: 5 | AH72: 76 | AI72: 47 | AJ72: 90 | AK72: 71 | AL72: 104 | AM72: 31 | AN72: 46 | AO72: 99 | AP72: 67.835405 | AQ72: 33.287666 | AR72: n/a | AS72: 93.105263 | AT72: 72.743437 | AU72: 35.091593 | AV72: 4.9068512 | AW72: 0.82675625 | AX72: 67.818839 | AY72: 26.683735 | AZ72: 64.903932 | BA72: 61 | BB72: 0.68284139 | BC72: 20.835477 | BD72: 43.438873 | BE72: 76.924964 | BF72: 77.81625 | BG72: 96.923077 | BH72: n/a | BI72: 62.861196 | BJ72: 1.5803886 | BK72: n/a | BL72: 18.246332 | BM72: 76.591956 | BN72: 25.589162 | BO72: 77.441166 | BP72: 4.9954697 | BQ72: 38.691361 | BR72: 92.171252 | BS72: 13.20875 | BT72: 31.126244 | BU72: 46.338799 | BV72: 60.9375 | BW72: 25.788883 | BX72: 100 | BY72: 64.620489 | BZ72: 71.011426 | CA72: 25.266372 | CB72: 67.625387 | CC72: 25.372569 | CD72: 0.1222842 | CE72: 68.598584 | CF72: 66.561355 | CG72: 41.072165 | CH72: 63.605898 | CI72: 94.010417 | CJ72: 60.459184 | CK72: 48.714909 | CL72: 51.111111 | CM72: 6.2217402 | CN72: 69.090909 | CO72: 83.20775 | CP72: 43.366983 | CQ72: 62 | CR72: 111 | CS72: n/a | CT72: 76 | CU72: 57 | CV72: 70 | CW72: 76 | CX72: 100 | CY72: 52 | CZ72: 32 | DA72: 53 | DB72: 31 | DC72: 50 | DD72: 50 | DE72: 18 | DF72: 18 | DG72: 37 | DH72: 28 | DI72: n/a | DJ72: 47 | DK72: 84 | DL72: n/a | DM72: 42 | DN72: 49 | DO72: 66 | DP72: 14 | DQ72: 71 | DR72: 102 | DS72: 53 | DT72: 51 | DU72: 58 | DV72: 62 | DW72: 81 | DX72: 93 | DY72: 1 | DZ72: 59 | EA72: 49 | EB72: 118 | EC72: 37 | ED72: 69 | EE72: 74 | EF72: 29 | EG72: 26 | EH72: 20 | EI72: 55 | EJ72: 8 | EK72: 78 | EL72: 101 | EM72: 97 | EN72: 80 | EO72: 91 | EP72: 38 | EQ72: 91
A73: Mexico | B73: MEX | C73: The Americas | D73: Upper middle-income | E73: 25770.389 | F73: 129740000 | G73: 48.293415 | H73: MX | I73: 67 | J73: 40.552775 | K73: 42.651381 | L73: 53.131661 | M73: 56.837844 | N73: 77 | O73: 58 | P73: 81 | Q73: 48 | R73: 66.90622 | S73: 24.173949 | T73: 30.578156 | U73: 49.000662 | V73: 43.937827 | W73: 35.015654 | X73: 48.311345 | Y73: 62.022625 | Z73: 49.061012 | AA73: 28.46559 | AB73: 73.198902 | AC73: 68.849039 | AD73: 70 | AE73: 68 | AF73: 81 | AG73: 75 | AH73: 33 | AI73: 83 | AJ73: 76 | AK73: 67 | AL73: 101 | AM73: 83 | AN73: 39 | AO73: 51 | AP73: 54.892147 | AQ73: 87.967649 | AR73: 65.067646 | AS73: 86.315789 | AT73: 77.579358 | AU73: 29.614731 | AV73: 4.213991 | AW73: 3.8658525 | AX73: 61.645481 | AY73: 26.970472 | AZ73: 59.509094 | BA73: 39.75 | BB73: 7.4332872 | BC73: 15.620243 | BD73: 35.514351 | BE73: 40.046526 | BF73: 72.549304 | BG73: 93.698602 | BH73: 3.1945237 | BI73: 77.866039 | BJ73: 3.0912845 | BK73: 57.385793 | BL73: 37.408192 | BM73: 71.566752 | BN73: 43.043867 | BO73: 21.308681 | BP73: 4.1433147 | BQ73: 50.403932 | BR73: 82.893618 | BS73: 38.146202 | BT73: 21.801629 | BU73: 37.92444 | BV73: 47.5 | BW73: 40.781593 | BX73: 100 | BY73: 83.907092 | BZ73: 72.460855 | CA73: 39.50774 | CB73: 68.809202 | CC73: 15.466251 | CD73: 0.29725553 | CE73: 77.003769 | CF73: 35.347197 | CG73: 1.2141385 | CH73: 83.087578 | CI73: 82.682292 | CJ73: 49.744898 | CK73: 57.908777 | CL73: 88.888889 | CM73: 28.690653 | CN73: 83.636364 | CO73: 79.870829 | CP73: 77.507732 | CQ73: 87 | CR73: 35 | CS73: 10 | CT73: 89 | CU73: 29 | CV73: 75 | CW73: 83 | CX73: 66 | CY73: 74 | CZ73: 30 | DA73: 67 | DB73: 63 | DC73: 33 | DD73: 70 | DE73: 27 | DF73: 85 | DG73: 57 | DH73: 46 | DI73: 46 | DJ73: 31 | DK73: 74 | DL73: 19 | DM73: 16 | DN73: 60 | DO73: 41 | DP73: 93 | DQ73: 77 | DR73: 82 | DS73: 74 | DT73: 32 | DU73: 69 | DV73: 80 | DW73: 99 | DX73: 73 | DY73: 1 | DZ73: 22 | EA73: 46 | EB73: 106 | EC73: 26 | ED73: 75 | EE73: 66 | EF73: 13 | EG73: 69 | EH73: 120 | EI73: 10 | EJ73: 35 | EK73: 94 | EL73: 86 | EM73: 58 | EN73: 53 | EO73: 47 | EP73: 49 | EQ73: 37
A74: Argentina | B74: ARG | C74: The Americas | D74: Upper middle-income | E74: 31311.011 | F74: 45538000 | G74: 48.141053 | H74: AR | I74: 68 | J74: 40.821539 | K74: 37.582657 | L74: 58.372 | M74: 55.788016 | N74: 73 | O74: 78 | P74: 69 | Q74: 51 | R74: 68.643291 | S74: 22.909428 | T74: 30.911896 | U74: 38.818709 | V74: 35.928504 | W74: 38.000758 | X74: 48.833341 | Y74: 63.465643 | Z74: 62.817016 | AA74: 33.590639 | AB74: 68.874931 | AC74: 64.898476 | AD74: 64 | AE74: 71 | AF74: 79 | AG74: 99 | AH74: 45 | AI74: 69 | AJ74: 73 | AK74: 61 | AL74: 68 | AM74: 59 | AN74: 54 | AO74: 62 | AP74: 86.361185 | AQ74: 49.007371 | AR74: 48.485291 | AS74: 92.105263 | AT74: 73.519867 | AU74: 62.380772 | AV74: 15.861344 | AW74: 4.9071945 | AX74: 67.52655 | AY74: 3.3426259 | AZ74: 64.714476 | BA74: 34.5 | BB74: 2.7672497 | BC74: 21.665858 | BD74: 20.446303 | BE74: 55.218906 | BF74: 75.388293 | BG74: n/a | BH74: 4.2213349 | BI74: 67.067099 | BJ74: 2.1263628 | BK74: 53.18811 | BL74: 21.332444 | BM74: 75.516416 | BN74: 54.732366 | BO74: 12.360096 | BP74: 9.3941562 | BQ74: 69.287695 | BR74: 41.758305 | BS74: 42.732696 | BT74: 41.55467 | BU74: 30.153117 | BV74: 74.6875 | BW74: 34.947159 | BX74: 100 | BY74: 77.54044 | BZ74: 60.865425 | CA74: 79.345561 | CB74: 65.682806 | CC74: 45.37427 | CD74: 0.16447857 | CE74: 68.505754 | CF74: 44.050726 | CG74: 21.641598 | CH74: 70.084897 | CI74: 75.520833 | CJ74: 52.55102 | CK74: 69.487107 | CL74: 97.777778 | CM74: 23.74942 | CN74: 70 | CO74: 79.978471 | CP74: 73.954248 | CQ74: 21 | CR74: 83 | CS74: 22 | CT74: 79 | CU74: 52 | CV74: 56 | CW74: 48 | CX74: 61 | CY74: 53 | CZ74: 76 | DA74: 54 | DB74: 81 | DC74: 43 | DD74: 47 | DE74: 51 | DF74: 56 | DG74: 49 | DH74: n/a | DI74: 44 | DJ74: 41 | DK74: 81 | DL74: 24 | DM74: 39 | DN74: 52 | DO74: 24 | DP74: 105 | DQ74: 59 | DR74: 56 | DS74: 110 | DT74: 28 | DU74: 51 | DV74: 94 | DW74: 61 | DX74: 77 | DY74: 1 | DZ74: 33 | EA74: 67 | EB74: 50 | EC74: 51 | ED74: 57 | EE74: 70 | EF74: 30 | EG74: 57 | EH74: 47 | EI74: 39 | EJ74: 57 | EK74: 90 | EL74: 54 | EM74: 42 | EN74: 64 | EO74: 88 | EP74: 47 | EQ74: 45
A75: South Africa | B75: ZAF | C75: Africa | D75: Upper middle-income | E75: 16049.821 | F75: 63212000 | G75: 47.942217 | H75: ZA | I75: 69 | J75: 43.412393 | K75: 39.042006 | L75: 64.541103 | M75: 44.773365 | N75: 66 | O75: 72 | P75: 55 | Q75: 100 | R75: 66.579676 | S75: 26.650984 | T75: 37.006519 | U75: 37.361313 | V75: 41.616689 | W75: 38.148015 | X75: 61.319199 | Y75: 64.476874 | Z75: 67.827237 | AA75: 31.853301 | AB75: 37.960453 | AC75: 64.506342 | AD75: 73 | AE75: 58 | AF75: 54 | AG75: 102 | AH75: 38 | AI75: 68 | AJ75: 61 | AK75: 58 | AL75: 55 | AM75: 65 | AN75: 117 | AO75: 64 | AP75: 51.239261 | AQ75: 60.804402 | AR75: 46.274151 | AS75: 99.210526 | AT75: 75.370037 | AU75: n/a | AV75: 4.1294515 | AW75: 6.702087 | AX75: 62.527909 | AY75: 33.244488 | AZ75: 66.235185 | BA75: 51.75 | BB75: 4.3841401 | BC75: 25.65675 | BD75: 27.148995 | BE75: 29.269659 | BF75: 39.727504 | BG75: 86.153846 | BH75: 4.5065602 | BI75: 78.775423 | BJ75: 7.2432272 | BK75: 49.793177 | BL75: 30.654929 | BM75: 86.430625 | BN75: 30.631769 | BO75: 25.919779 | BP75: 9.6098869 | BQ75: 78.291468 | BR75: 83.475219 | BS75: 67.364878 | BT75: 16.145231 | BU75: 36.630426 | BV75: 77.5 | BW75: 44.815536 | BX75: 100 | BY75: 63.438407 | BZ75: 82.606856 | CA75: 60.101321 | CB75: n/a | CC75: 60.773535 | CD75: 1.2810063 | CE75: 65.55449 | CF75: 52.671563 | CG75: 7.9061463 | CH75: 43.632708 | CI75: 56.25 | CJ75: 0 | CK75: 27.9973 | CL75: 80 | CM75: n/a | CN75: 82.727273 | CO75: 44.779333 | CP75: 52.024843 | CQ75: 93 | CR75: 71 | CS75: 28 | CT75: 40 | CU75: 42 | CV75: n/a | CW75: 85 | CX75: 52 | CY75: 71 | CZ75: 24 | DA75: 46 | DB75: 40 | DC75: 39 | DD75: 35 | DE75: 40 | DF75: 98 | DG75: 98 | DH75: 58 | DI75: 43 | DJ75: 30 | DK75: 57 | DL75: 31 | DM75: 24 | DN75: 24 | DO75: 61 | DP75: 86 | DQ75: 57 | DR75: 38 | DS75: 73 | DT75: 10 | DU75: 82 | DV75: 83 | DW75: 51 | DX75: 61 | DY75: 1 | DZ75: 62 | EA75: 29 | EB75: 80 | EC75: n/a | ED75: 45 | EE75: 51 | EF75: 32 | EG75: 47 | EH75: 81 | EI75: 90 | EJ75: 97 | EK75: 113 | EL75: 123 | EM75: 72 | EN75: n/a | EO75: 51 | EP75: 113 | EQ75: 79
A76: Republic of Moldova | B76: MDA | C76: Europe | D76: Upper middle-income | E76: 19590.727 | F76: 3067000 | G76: 47.141732 | H76: MD | I76: 70 | J76: 37.294337 | K76: 37.568971 | L76: 58.952846 | M76: 54.750773 | N76: 83 | O76: 79 | P76: 68 | Q76: 57 | R76: 75.307663 | S76: 23.967742 | T76: 12.607606 | U76: 51.737094 | V76: 25.899441 | W76: 35.070378 | X76: 55.621784 | Y76: 69.780852 | Z76: 51.455901 | AA76: 31.627862 | AB76: 69.405503 | AC76: 63.218953 | AD76: 42 | AE76: 69 | AF76: 125 | AG76: 63 | AH76: 79 | AI76: 82 | AJ76: 64 | AK76: 44 | AL76: 91 | AM76: 67 | AN76: 49 | AO76: 65 | AP76: 62.871257 | AQ76: 80.90449 | AR76: 37.62569 | AS76: 99.473684 | AT76: 73.960884 | AU76: 97.009972 | AV76: 16.003311 | AW76: 3.9788288 | AX76: 75.708752 | AY76: 0.18007818 | AZ76: n/a | BA76: 19.5 | BB76: n/a | BC76: 5.7152117 | BD76: 5.3396969 | BE76: n/a | BF76: 51.410048 | BG76: 98.461538 | BH76: n/a | BI76: 43.309432 | BJ76: n/a | BK76: 31.71056 | BL76: 2.6783313 | BM76: 67.079318 | BN76: 34.694607 | BO76: n/a | BP76: 3.4372074 | BQ76: 76.531645 | BR76: 58.253076 | BS76: 68.031005 | BT76: 19.671411 | BU76: 44.86843 | BV76: 76.25 | BW76: n/a | BX76: 100 | BY76: 58.004977 | BZ76: 71.011426 | CA76: 50.425273 | CB76: n/a | CC76: 32.931004 | CD76: 0.54125754 | CE76: 35.200669 | CF76: n/a | CG76: 59.14166 | CH76: 57.171582 | CI76: 76.302083 | CJ76: 92.346939 | CK76: 57.138749 | CL76: 80 | CM76: 31.687172 | CN76: 86.363636 | CO76: 67.599569 | CP76: 54.450865 | CQ76: 72 | CR76: 46 | CS76: 46 | CT76: 29 | CU76: 50 | CV76: 43 | CW76: 47 | CX76: 64 | CY76: 14 | CZ76: 115 | DA76: n/a | DB76: 116 | DC76: n/a | DD76: 95 | DE76: 93 | DF76: n/a | DG76: 90 | DH76: 16 | DI76: n/a | DJ76: 76 | DK76: n/a | DL76: 105 | DM76: 75 | DN76: 69 | DO76: 52 | DP76: n/a | DQ76: 81 | DR76: 40 | DS76: 103 | DT76: 9 | DU76: 73 | DV76: 67 | DW76: 58 | DX76: n/a | DY76: 1 | DZ76: 74 | EA76: 49 | EB76: 92 | EC76: n/a | ED76: 64 | EE76: 57 | EF76: 116 | EG76: n/a | EH76: 8 | EI76: 77 | EJ76: 55 | EK76: 9 | EL76: 88 | EM76: 72 | EN76: 51 | EO76: 40 | EP76: 87 | EQ76: 76
A77: Jordan | B77: JOR | C77: Arab States | D77: Lower middle-income | E77: 11510.847 | F77: 11439000 | G77: 46.604504 | H77: JO | I77: 71 | J77: 45.945465 | K77: 46.408069 | L77: 53.235754 | M77: 40.828727 | N77: 54 | O77: 44 | P77: 80 | Q77: 108 | R77: 55.348739 | S77: 32.67393 | T77: 49.813727 | U77: 61.641578 | V77: 32.695581 | W77: 44.887048 | X77: 42.944513 | Y77: 57.93893 | Z77: 58.823818 | AA77: 26.995548 | AB77: 47.218495 | AC77: 48.272139 | AD77: 100 | AE77: 46 | AF77: 23 | AG77: 24 | AH77: 55 | AI77: 56 | AJ77: 93 | AK77: 76 | AL77: 75 | AM77: 90 | AN77: 103 | AO77: 109 | AP77: 44.016755 | AQ77: 44.319747 | AR77: 38.739279 | AS77: 99.473684 | AT77: 73.984338 | AU77: 31.55863 | AV77: 3.6810757 | AW77: 2.1560468 | AX77: 73.436043 | AY77: 51.422556 | AZ77: 76.838511 | BA77: 49.25 | BB77: n/a | BC77: 23.352671 | BD77: 21.626096 | BE77: 75.359435 | BF77: 57.273088 | BG77: 92.307692 | BH77: n/a | BI77: 80.707865 | BJ77: 6.5915328 | BK77: 42.182572 | BL77: 1.3003533 | BM77: 71.012139 | BN77: 25.984944 | BO77: 71.668782 | BP77: 10.882326 | BQ77: 42.781435 | BR77: 98.314766 | BS77: 14.113549 | BT77: 16.568303 | BU77: 47.676378 | BV77: 73.75 | BW77: 55.856408 | BX77: 75 | BY77: 37.411862 | BZ77: 59.415997 | CA77: 42.765506 | CB77: 61.7693 | CC77: 71.344469 | CD77: 0.59257423 | CE77: 45.463678 | CF77: 60.967311 | CG77: 0.95862844 | CH77: 23.458445 | CI77: 59.375 | CJ77: n/a | CK77: 70.425583 | CL77: 66.666667 | CM77: 9.048487 | CN77: 40.909091 | CO77: 72.658773 | CP77: 74.277746 | CQ77: 106 | CR77: 92 | CS77: 45 | CT77: 29 | CU77: 49 | CV77: 72 | CW77: 87 | CX77: 79 | CY77: 22 | CZ77: 15 | DA77: 29 | DB77: 44 | DC77: n/a | DD77: 42 | DE77: 45 | DF77: 22 | DG77: 80 | DH77: 48 | DI77: n/a | DJ77: 26 | DK77: 60 | DL77: 60 | DM77: 88 | DN77: 63 | DO77: 65 | DP77: 19 | DQ77: 51 | DR77: 96 | DS77: 27 | DT77: 49 | DU77: 79 | DV77: 59 | DW77: 64 | DX77: 45 | DY77: 72 | DZ77: 103 | EA77: 69 | EB77: 103 | EC77: 72 | ED77: 27 | EE77: 56 | EF77: 86 | EG77: 33 | EH77: 123 | EI77: 112 | EJ77: 89 | EK77: n/a | EL77: 48 | EM77: 89 | EN77: 78 | EO77: 118 | EP77: 76 | EQ77: 44
A78: Uzbekistan | B78: UZB | C78: CIS | D78: Lower middle-income | E78: 12558.992 | F78: 35652000 | G78: 46.472979 | H78: UZ | I78: 72 | J78: 40.725585 | K78: 37.831626 | L78: 57.325975 | M78: 50.00873 | N78: 75 | O78: 77 | P78: 71 | Q78: 82 | R78: 70.510193 | S78: 21.132841 | T78: 30.533721 | U78: 51.914266 | V78: 24.858792 | W78: 36.721821 | X78: 47.281835 | Y78: 49.335705 | Z78: 75.360385 | AA78: 22.399628 | AB78: 76.488035 | AC78: 51.138525 | AD78: 60 | AE78: 76 | AF78: 82 | AG78: 62 | AH78: 87 | AI78: 74 | AJ78: 82 | AK78: 101 | AL78: 37 | AM78: 107 | AN78: 28 | AO78: 100 | AP78: 59.203422 | AQ78: 33.512992 | AR78: 66.721731 | AS78: 84.210526 | AT78: 82.063648 | AU78: 97.348837 | AV78: 2.8794782 | AW78: 0.95607995 | AX78: 65.625683 | AY78: 15.070124 | AZ78: 57.943867 | BA78: n/a | BB78: n/a | BC78: 3.1235748 | BD78: 42.083104 | BE78: 44.966801 | BF78: 20.607161 | BG78: 100 | BH78: n/a | BI78: 24.667052 | BJ78: n/a | BK78: 48.468061 | BL78: 1.4412642 | BM78: 71.708714 | BN78: 36.181548 | BO78: 37.107825 | BP78: 1.8891968 | BQ78: 55.285431 | BR78: 87.024844 | BS78: 37.170737 | BT78: 9.6463272 | BU78: 27.793748 | BV78: 48.4375 | BW78: n/a | BX78: 100 | BY78: 21.111572 | BZ78: 68.112569 | CA78: 98.536164 | CB78: 60.152379 | CC78: 74.640428 | CD78: 0 | CE78: 57.490777 | CF78: n/a | CG78: 9.7081079 | CH78: 65.527256 | CI78: 95.442708 | CJ78: 72.44898 | CK78: 64.539302 | CL78: 88.888889 | CM78: 5.7897846 | CN78: 74.545455 | CO78: 44.67169 | CP78: 70.205456 | CQ78: 79 | CR78: 108 | CS78: 7 | CT78: 91 | CU78: 18 | CV78: 42 | CW78: 94 | CX78: 97 | CY78: 61 | CZ78: 40 | DA78: 70 | DB78: n/a | DC78: n/a | DD78: 108 | DE78: 21 | DF78: 76 | DG78: 106 | DH78: 1 | DI78: n/a | DJ78: 101 | DK78: n/a | DL78: 39 | DM78: 87 | DN78: 59 | DO78: 50 | DP78: 63 | DQ78: 93 | DR78: 73 | DS78: 65 | DT78: 33 | DU78: 93 | DV78: 100 | DW78: 98 | DX78: n/a | DY78: 1 | DZ78: 119 | EA78: 53 | EB78: 7 | EC78: 78 | ED78: 21 | EE78: 81 | EF78: 55 | EG78: n/a | EH78: 78 | EI78: 51 | EJ78: 6 | EK78: 57 | EL78: 73 | EM78: 58 | EN78: 81 | EO78: 72 | EP78: 114 | EQ78: 52
A79: Morocco | B79: MAR | C79: Arab States | D79: Lower middle-income | E79: 11437.148 | F79: 37713000 | G79: 46.38251 | H79: MA | I79: 73 | J79: 47.80072 | K79: 37.416303 | L79: 55.529704 | M79: 44.783313 | N79: 47 | O79: 80 | P79: 75 | Q79: 99 | R79: 65.315828 | S79: 41.789687 | T79: 36.296647 | U79: 47.481361 | V79: 29.165537 | W79: 35.602011 | X79: 42.206387 | Y79: 65.295999 | Z79: 59.086726 | AA79: 27.98141 | AB79: 50.626838 | AC79: 55.741691 | AD79: 74 | AE79: 32 | AF79: 58 | AG79: 78 | AH79: 70 | AI79: 78 | AJ79: 97 | AK79: 55 | AL79: 73 | AM79: 85 | AN79: 95 | AO79: 91 | AP79: 49.921808 | AQ79: 48.994872 | AR79: 43.843391 | AS79: 98.421053 | AT79: 79.743986 | AU79: 70.969856 | AV79: 5.1545412 | AW79: 1.5702733 | AX79: 60.433932 | AY79: 100 | AZ79: 54.732087 | BA79: 35 | BB79: n/a | BC79: 19.157852 | BD79: 31.946525 | BE79: 57.099786 | BF79: 56.263747 | BG79: 44.615385 | BH79: n/a | BI79: 62.520177 | BJ79: 3.8291558 | BK79: 46.799443 | BL79: 3.5133704 | BM79: 47.286486 | BN79: 12.314367 | BO79: 47.205179 | BP79: n/a | BQ79: 51.07934 | BR79: 96.988704 | BS79: 12.409508 | BT79: 8.3479954 | BU79: 40.621601 | BV79: 72.8125 | BW79: n/a | BX79: 75 | BY79: 72.749896 | BZ79: 40.584003 | CA79: 83.980941 | CB79: 60.522726 | CC79: 51.259232 | CD79: 0.31326713 | CE79: 56.75542 | CF79: 29.054372 | CG79: 25.80258 | CH79: 30.428954 | CI79: 65.625 | CJ79: n/a | CK79: 61.026281 | CL79: 75.555556 | CM79: 7.8905949 | CN79: 64.545455 | CO79: 78.579117 | CP79: 68.347637 | CQ79: 97 | CR79: 84 | CS79: 35 | CT79: 48 | CU79: 23 | CV79: 54 | CW79: 74 | CX79: 87 | CY79: 78 | CZ79: 1 | DA79: 73 | DB79: 78 | DC79: n/a | DD79: 55 | DE79: 32 | DF79: 51 | DG79: 81 | DH79: 87 | DI79: n/a | DJ79: 48 | DK79: 70 | DL79: 45 | DM79: 72 | DN79: 95 | DO79: 85 | DP79: 39 | DQ79: n/a | DR79: 79 | DS79: 35 | DT79: 52 | DU79: 96 | DV79: 73 | DW79: 68 | DX79: n/a | DY79: 72 | DZ79: 45 | EA79: 92 | EB79: 41 | EC79: 76 | ED79: 50 | EE79: 64 | EF79: 56 | EG79: 77 | EH79: 37 | EI79: 101 | EJ79: 78 | EK79: n/a | EL79: 79 | EM79: 79 | EN79: 79 | EO79: 97 | EP79: 52 | EQ79: 54
A80: Ecuador | B80: ECU | C80: The Americas | D80: Upper middle-income | E80: 16805.019 | F80: 17980000 | G80: 46.256771 | H80: EC | I80: 74 | J80: 34.913252 | K80: 41.958148 | L80: 55.417073 | M80: 52.738612 | N80: 88 | O80: 62 | P80: 76 | Q80: 70 | R80: 55.538673 | S80: 18.696999 | T80: 30.504084 | U80: 51.93093 | V80: 30.612729 | W80: 43.330784 | X80: 48.532538 | Y80: 52.407363 | Z80: 65.311318 | AA80: 16.28787 | AB80: 59.346059 | AC80: 82.581909 | AD80: 99 | AE80: 85 | AF80: 83 | AG80: 61 | AH80: 63 | AI80: 61 | AJ80: 74 | AK80: 86 | AL80: 61 | AM80: 122 | AN80: 82 | AO80: 21 | AP80: 55.803163 | AQ80: 39.111558 | AR80: 49.250965 | AS80: 82.789474 | AT80: 63.103577 | AU80: 43.173302 | AV80: 5.2023857 | AW80: 1.6057472 | AX80: 55.24025 | AY80: 12.739615 | AZ80: 48.160022 | BA80: 23.25 | BB80: n/a | BC80: 20.102232 | BD80: 11.043414 | BE80: 28.19057 | BF80: 74.643584 | BG80: 93.846154 | BH80: n/a | BI80: 83.322345 | BJ80: 2.7987289 | BK80: n/a | BL80: 5.7171123 | BM80: 86.173169 | BN80: 26.731333 | BO80: 17.087849 | BP80: n/a | BQ80: 49.748567 | BR80: 84.512968 | BS80: 42.999246 | BT80: 16.869374 | BU80: 24.255676 | BV80: 58.75 | BW80: 23.784355 | BX80: 100 | BY80: 55.246786 | BZ80: 86.955142 | CA80: 32.40373 | CB80: 72.847303 | CC80: 69.039097 | CD80: 0.12311087 | CE80: 53.956274 | CF80: 9.399786 | CG80: 1.6723076 | CH80: 60.433423 | CI80: 60.9375 | CJ80: 45.408163 | CK80: 67.926347 | CL80: 93.333333 | CM80: n/a | CN80: 84.545455 | CO80: 80.839612 | CP80: 71.387984 | CQ80: 85 | CR80: 100 | CS80: 21 | CT80: 95 | CU80: 107 | CV80: 66 | CW80: 73 | CX80: 86 | CY80: 92 | CZ80: 42 | DA80: 82 | DB80: 110 | DC80: n/a | DD80: 52 | DE80: 73 | DF80: 101 | DG80: 51 | DH80: 39 | DI80: n/a | DJ80: 21 | DK80: 75 | DL80: n/a | DM80: 58 | DN80: 25 | DO80: 64 | DP80: 100 | DQ80: n/a | DR80: 84 | DS80: 70 | DT80: 26 | DU80: 78 | DV80: 110 | DW80: 84 | DX80: 96 | DY80: 1 | DZ80: 80 | EA80: 21 | EB80: 111 | EC80: 9 | ED80: 31 | EE80: 73 | EF80: 63 | EG80: 101 | EH80: 114 | EI80: 60 | EJ80: 83 | EK80: 99 | EL80: 56 | EM80: 50 | EN80: n/a | EO80: 45 | EP80: 42 | EQ80: 51
A81: Azerbaijan | B81: AZE | C81: CIS | D81: Upper middle-income | E81: 26081.082 | F81: 10318000 | G81: 46.076794 | H81: AZ | I81: 75 | J81: 41.264716 | K81: 39.767376 | L81: 50.035178 | M81: 53.239906 | N81: 72 | O81: 70 | P81: 93 | Q81: 65 | R81: 71.118145 | S81: 16.911601 | T81: 35.764403 | U81: 53.749469 | V81: 34.906854 | W81: 30.645805 | X81: 47.671355 | Y81: 56.047139 | Z81: 46.387038 | AA81: 43.29011 | AB81: 55.988695 | AC81: 60.440912 | AD81: 57 | AE81: 94 | AF81: 60 | AG81: 53 | AH81: 48 | AI81: 89 | AJ81: 79 | AK81: 77 | AL81: 106 | AM81: 33 | AN81: 90 | AO81: 79 | AP81: 70.482456 | AQ81: 63.114159 | AR81: 41.380705 | AS81: 100 | AT81: 76.466369 | AU81: 75.265182 | AV81: 4.7848341 | AW81: 1.4457591 | AX81: 58.606346 | AY81: 2.8094647 | AZ81: n/a | BA81: 67 | BB81: n/a | BC81: 4.5288059 | BD81: 5.9816454 | BE81: n/a | BF81: 55.266762 | BG81: 100 | BH81: n/a | BI81: 61.724466 | BJ81: n/a | BK81: 41.159845 | BL81: 1.8362521 | BM81: 68.555479 | BN81: 20.60147 | BO81: n/a | BP81: 2.7804661 | BQ81: 50.547211 | BR81: 92.700161 | BS81: 34.140978 | BT81: 13.297071 | BU81: 39.505464 | BV81: 42.8125 | BW81: n/a | BX81: 100 | BY81: 41.870593 | BZ81: 46.381718 | CA81: 36.526768 | CB81: 53.213397 | CC81: 49.42627 | CD81: n/a | CE81: 52.418312 | CF81: 74.087307 | CG81: 3.3647113 | CH81: 36.081323 | CI81: 70.442708 | CJ81: n/a | CK81: 66.895412 | CL81: 68.888889 | CM81: 17.923248 | CN81: 78.181818 | CO81: 72.658773 | CP81: 77.110732 | CQ81: 56 | CR81: 67 | CS81: 39 | CT81: 1 | CU81: 38 | CV81: 52 | CW81: 78 | CX81: 90 | CY81: 84 | CZ81: 78 | DA81: n/a | DB81: 23 | DC81: n/a | DD81: 98 | DE81: 91 | DF81: n/a | DG81: 83 | DH81: 1 | DI81: n/a | DJ81: 49 | DK81: n/a | DL81: 64 | DM81: 84 | DN81: 66 | DO81: 73 | DP81: n/a | DQ81: 84 | DR81: 81 | DS81: 50 | DT81: 37 | DU81: 85 | DV81: 75 | DW81: 107 | DX81: n/a | DY81: 1 | DZ81: 98 | EA81: 85 | EB81: 110 | EC81: 88 | ED81: 53 | EE81: n/a | EF81: 68 | EG81: 15 | EH81: 103 | EI81: 97 | EJ81: 64 | EK81: n/a | EL81: 59 | EM81: 86 | EN81: 68 | EO81: 62 | EP81: 76 | EQ81: 39
A82: Dominican Republic | B82: DOM | C82: The Americas | D82: Upper middle-income | E82: 30537.613 | F82: 11331000 | G82: 46.00336 | H82: DO | I82: 76 | J82: 33.513664 | K82: 40.726419 | L82: 58.959993 | M82: 50.813364 | N82: 93 | O82: 67 | P82: 67 | Q82: 80 | R82: 61.108373 | S82: 13.990014 | T82: 25.442604 | U82: 51.503668 | V82: 27.244579 | W82: 43.431011 | X82: 42.751335 | Y82: 66.925171 | Z82: 67.203471 | AA82: 29.454067 | AB82: 67.332431 | AC82: 55.653593 | AD82: 82 | AE82: 102 | AF82: 98 | AG82: 65 | AH82: 77 | AI82: 60 | AJ82: 95 | AK82: 52 | AL82: 57 | AM82: 77 | AN82: 61 | AO82: 92 | AP82: 58.767942 | AQ82: 62.63844 | AR82: 31.398002 | AS82: 93.157895 | AT82: 68.002912 | AU82: 52.685051 | AV82: 4.3090152 | AW82: 2.0359614 | AX82: 49.500304 | AY82: 0.11477362 | AZ82: 46.364273 | BA82: 29 | BB82: n/a | BC82: 0.96353952 | BD82: 14.217178 | BE82: 35.989609 | BF82: 65.038655 | BG82: 90.769231 | BH82: n/a | BI82: 36.034357 | BJ82: n/a | BK82: 39.877653 | BL82: 5.8217261 | BM82: 56.746189 | BN82: 34.548019 | BO82: 38.998826 | BP82: n/a | BQ82: 41.427031 | BR82: 70.957937 | BS82: 36.232827 | BT82: 22.387547 | BU82: 46.512269 | BV82: 94.375 | BW82: 26.691717 | BX82: 100 | BY82: 67.046869 | BZ82: 63.764283 | CA82: 48.120976 | CB82: 69.179816 | CC82: 87.74881 | CD82: n/a | CE82: 54.458474 | CF82: 32.482002 | CG82: 1.4217251 | CH82: 57.774799 | CI82: 80.989583 | CJ82: 61.22449 | CK82: 65.241333 | CL82: 93.333333 | CM82: 5.3126136 | CN82: 80 | CO82: 90.635091 | CP82: 0 | CQ82: 81 | CR82: 69 | CS82: 63 | CT82: 75 | CU82: 85 | CV82: 62 | CW82: 82 | CX82: 80 | CY82: 99 | CZ82: 119 | DA82: 86 | DB82: 95 | DC82: n/a | DD82: 120 | DE82: 66 | DF82: 90 | DG82: 70 | DH82: 53 | DI82: n/a | DJ82: 89 | DK82: n/a | DL82: 67 | DM82: 57 | DN82: 84 | DO82: 53 | DP82: 59 | DQ82: n/a | DR82: 99 | DS82: 86 | DT82: 34 | DU82: 68 | DV82: 61 | DW82: 5 | DX82: 92 | DY82: 1 | DZ82: 54 | EA82: 61 | EB82: 97 | EC82: 21 | ED82: 5 | EE82: n/a | EF82: 62 | EG82: 71 | EH82: 117 | EI82: 74 | EJ82: 42 | EK82: 77 | EL82: 71 | EM82: 50 | EN82: 82 | EO82: 58 | EP82: 13 | EQ82: 126
A83: Kenya | B83: KEN | C83: Africa | D83: Lower middle-income | E83: 7556.076 | F83: 55339000 | G83: 45.767052 | H83: KE | I83: 77 | J83: 42.090895 | K83: 34.255201 | L83: 60.021107 | M83: 46.701004 | N83: 70 | O83: 90 | P83: 66 | Q83: 92 | R83: 66.664304 | S83: 17.962253 | T83: 41.646129 | U83: 44.134585 | V83: 24.217936 | W83: 34.413083 | X83: 53.129489 | Y83: 64.539453 | Z83: 62.394378 | AA83: 32.144406 | AB83: 45.446618 | AC83: 62.511988 | AD83: 72 | AE83: 90 | AF83: 42 | AG83: 93 | AH83: 88 | AI83: 84 | AJ83: 67 | AK83: 57 | AL83: 69 | AM83: 64 | AN83: 108 | AO83: 67 | AP83: 76.395492 | AQ83: 35.902188 | AR83: 47.727429 | AS83: 89.473684 | AT83: 83.822725 | AU83: n/a | AV83: 6.5716958 | AW83: 0.9496644 | AX83: 55.579242 | AY83: 8.7484095 | AZ83: 56.410849 | BA83: 60 | BB83: n/a | BC83: 8.5275363 | BD83: 18.29146 | BE83: 64.427945 | BF83: 19.783245 | BG83: 74.035692 | BH83: n/a | BI83: 42.059028 | BJ83: 8.2300547 | BK83: 43.892664 | BL83: 2.6899961 | BM83: 73.176454 | BN83: 10.836887 | BO83: 40.970183 | BP83: 12.668808 | BQ83: 48.056935 | BR83: 98.30803 | BS83: 42.962905 | BT83: 23.190086 | BU83: 32.448596 | BV83: 86.875 | BW83: 39.83157 | BX83: 100 | BY83: 63.542099 | BZ83: 49.269996 | CA83: 83.694549 | CB83: 40.02837 | CC83: 76.584597 | CD83: 0.076246622 | CE83: 56.223434 | CF83: 31.173442 | CG83: 41.104502 | CH83: 27.92672 | CI83: 52.734375 | CJ83: 64.540816 | CK83: 46.816699 | CL83: 40 | CM83: n/a | CN83: 76.363636 | CO83: 65.123789 | CP83: 52.09708 | CQ83: 46 | CR83: 105 | CS83: 24 | CT83: 83 | CU83: 14 | CV83: n/a | CW83: 64 | CX83: 98 | CY83: 89 | CZ83: 49 | DA83: 71 | DB83: 32 | DC83: n/a | DD83: 86 | DE83: 56 | DF83: 40 | DG83: 108 | DH83: 67 | DI83: n/a | DJ83: 77 | DK83: 54 | DL83: 57 | DM83: 74 | DN83: 55 | DO83: 88 | DP83: 50 | DQ83: 46 | DR83: 91 | DS83: 28 | DT83: 27 | DU83: 66 | DV83: 93 | DW83: 27 | DX83: 75 | DY83: 1 | DZ83: 61 | EA83: 81 | EB83: 44 | EC83: 93 | ED83: 19 | EE83: 75 | EF83: 57 | EG83: 75 | EH83: 19 | EI83: 104 | EJ83: 102 | EK83: 72 | EL83: 103 | EM83: 104 | EN83: n/a | EO83: 69 | EP83: 91 | EQ83: 78
A84: Kuwait | B84: KWT | C84: Arab States | D84: High-income | E84: 52866.096 | F84: 4839000 | G84: 45.531936 | H84: KW | I84: 78 | J84: 42.148522 | K84: 34.063242 | L84: 52.760129 | M84: 53.15585 | N84: 69 | O84: 91 | P84: 82 | Q84: 66 | R84: 71.41253 | S84: 18.289468 | T84: 36.74357 | U84: 58.766868 | V84: 14.834706 | W84: 28.588152 | X84: 50.212675 | Y84: 52.083993 | Z84: 55.98372 | AA84: 36.603183 | AB84: 82.003243 | AC84: 40.861124 | AD84: 56 | AE84: 87 | AF84: 57 | AG84: 31 | AH84: 124 | AI84: 96 | AJ84: 70 | AK84: 90 | AL84: 83 | AM84: 50 | AN84: 15 | AO84: 121 | AP84: 68.906043 | AQ84: 83.111238 | AR84: 3.7055233 | AS84: 100 | AT84: 72.752375 | AU84: 100 | AV84: 2.0804244 | AW84: 3.2297713 | AX84: 65.108018 | AY84: 2.7396576 | AZ84: 33.553388 | BA84: 42.5 | BB84: n/a | BC84: 34.177321 | BD84: 29.716127 | BE84: 30.346177 | BF84: 81.159016 | BG84: 93.846154 | BH84: n/a | BI84: n/a | BJ84: 3.604582 | BK84: 36.967176 | BL84: 3.9323599 | BM84: 56.274588 | BN84: n/a | BO84: 28.037079 | BP84: 1.4527887 | BQ84: 47.604285 | BR84: 52.821065 | BS84: n/a | BT84: n/a | BU84: 50.259321 | BV84: 55 | BW84: 38.642602 | BX84: 75 | BY84: 41.518042 | BZ84: 26.089716 | CA84: 73.162104 | CB84: 68.699339 | CC84: n/a | CD84: 0.25730777 | CE84: 52.269149 | CF84: 45.191692 | CG84: 48.694582 | CH84: 75.268097 | CI84: 89.84375 | CJ84: n/a | CK84: 79.792524 | CL84: 95.555556 | CM84: n/a | CN84: 10 | CO84: 28.740581 | CP84: 72.130027 | CQ84: 60 | CR84: 41 | CS84: 120 | CT84: 1 | CU84: 56 | CV84: 1 | CW84: 101 | CX84: 69 | CY84: 63 | CZ84: 80 | DA84: 98 | DB84: 56 | DC84: n/a | DD84: 23 | DE84: 39 | DF84: 96 | DG84: 24 | DH84: 39 | DI84: n/a | DJ84: n/a | DK84: 73 | DL84: 82 | DM84: 68 | DN84: 85 | DO84: n/a | DP84: 82 | DQ84: 98 | DR84: 92 | DS84: 104 | DT84: n/a | DU84: n/a | DV84: 53 | DW84: 86 | DX84: 76 | DY84: 72 | DZ84: 99 | EA84: 107 | EB84: 63 | EC84: 27 | ED84: n/a | EE84: 68 | EF84: 69 | EG84: 55 | EH84: 14 | EI84: 27 | EJ84: 15 | EK84: n/a | EL84: 30 | EM84: 46 | EN84: n/a | EO84: 125 | EP84: 118 | EQ84: 50
A85: Albania | B85: ALB | C85: Europe | D85: Upper middle-income | E85: 23327.052 | F85: 2812000 | G85: 45.414015 | H85: AL | I85: 79 | J85: 31.780649 | K85: 42.452788 | L85: 55.007923 | M85: 52.414701 | N85: 97 | O85: 59 | P85: 77 | Q85: 73 | R85: 64.184717 | S85: 17.150259 | T85: 14.006971 | U85: 46.07518 | V85: 29.88251 | W85: 51.400673 | X85: 47.612338 | Y85: 70.649575 | Z85: 46.761856 | AA85: 26.981177 | AB85: 68.884923 | AC85: 61.378003 | AD85: 77 | AE85: 93 | AF85: 120 | AG85: 86 | AH85: 67 | AI85: 33 | AJ85: 80 | AK85: 41 | AL85: 105 | AM85: 91 | AN85: 53 | AO85: 73 | AP85: 54.294274 | AQ85: 68.325618 | AR85: 30.38072 | AS85: 97.894737 | AT85: 61.943331 | AU85: 72.269623 | AV85: 8.2002366 | AW85: 5.8248968 | AX85: 53.152696 | AY85: 1.423205 | AZ85: n/a | BA85: 21.75 | BB85: n/a | BC85: 6.2639412 | BD85: 3.4386129 | BE85: 28.487924 | BF85: 55.451104 | BG85: 96.923077 | BH85: n/a | BI85: 56.268159 | BJ85: n/a | BK85: 29.675923 | BL85: 3.7034475 | BM85: 77.672309 | BN85: 43.986672 | BO85: 32.543038 | BP85: n/a | BQ85: 57.845446 | BR85: 83.787631 | BS85: 34.984163 | BT85: 13.832112 | BU85: 46.531456 | BV85: 83.125 | BW85: 48.539572 | BX85: 100 | BY85: 75.051846 | BZ85: 71.011426 | CA85: 29.342155 | CB85: 61.585807 | CC85: 25.108037 | CD85: n/a | CE85: 37.804824 | CF85: n/a | CG85: 16.15753 | CH85: 48.0563 | CI85: 77.734375 | CJ85: 85.714286 | CK85: 76.013901 | CL85: 64.444444 | CM85: 12.457062 | CN85: 87.272727 | CO85: 89.128095 | CP85: 48.863815 | CQ85: 89 | CR85: 58 | CS85: 67 | CT85: 54 | CU85: 108 | CV85: 53 | CW85: 60 | CX85: 55 | CY85: 94 | CZ85: 91 | DA85: n/a | DB85: 114 | DC85: n/a | DD85: 92 | DE85: 104 | DF85: 100 | DG85: 82 | DH85: 28 | DI85: n/a | DJ85: 59 | DK85: n/a | DL85: 110 | DM85: 70 | DN85: 46 | DO85: 39 | DP85: 74 | DQ85: n/a | DR85: 69 | DS85: 72 | DT85: 36 | DU85: 84 | DV85: 60 | DW85: 34 | DX85: 53 | DY85: 1 | DZ85: 42 | EA85: 49 | EB85: 114 | EC85: 73 | ED85: 70 | EE85: n/a | EF85: 109 | EG85: n/a | EH85: 56 | EI85: 85 | EJ85: 53 | EK85: 20 | EL85: 38 | EM85: 92 | EN85: 73 | EO85: 37 | EP85: 16 | EQ85: 82
A86: Peru | B86: PER | C86: The Americas | D86: Upper middle-income | E86: 18980.187 | F86: 33846000 | G86: 45.243636 | H86: PE | I86: 80 | J86: 34.123354 | K86: 43.36036 | L86: 51.642835 | M86: 51.847995 | N86: 91 | O86: 56 | P86: 86 | Q86: 77 | R86: 58.898765 | S86: 20.956711 | T86: 22.514585 | U86: 59.658887 | V86: 37.243116 | W86: 33.179078 | X86: 46.480247 | Y86: 55.437888 | Z86: 53.01037 | AA86: 25.544964 | AB86: 60.515398 | AC86: 69.483625 | AD86: 87 | AE86: 77 | AF86: 103 | AG86: 28 | AH86: 43 | AI86: 86 | AJ86: 85 | AK86: 78 | AL86: 89 | AM86: 97 | AN86: 80 | AO86: 50 | AP86: 60.392137 | AQ86: 54.542835 | AR86: 47.328988 | AS86: 69.842105 | AT86: 68.582073 | AU86: 52.704449 | AV86: 7.1675908 | AW86: 3.4616919 | AX86: 59.014541 | AY86: 14.183022 | AZ86: 47.937207 | BA86: 25.25 | BB86: 0 | BC86: 16.871134 | BD86: 35.676138 | BE86: 39.134555 | BF86: 73.577944 | BG86: 90.246911 | BH86: n/a | BI86: 81.730922 | BJ86: 1.3366619 | BK86: 48.580862 | BL86: 17.324019 | BM86: 80.474248 | BN86: 31.110347 | BO86: 18.666687 | BP86: 2.4650284 | BQ86: 54.013211 | BR86: 80.287653 | BS86: 33.91594 | BT86: 17.704184 | BU86: 49.540705 | BV86: 73.75 | BW86: 23.651951 | BX86: 75 | BY86: 55.246786 | BZ86: 73.910284 | CA86: 36.699282 | CB86: 60.16814 | CC86: 41.263773 | CD86: 0.24728262 | CE86: 60.816687 | CF86: 39.710955 | CG86: 1.4049288 | CH86: 60.031278 | CI86: 60.677083 | CJ86: 58.418367 | CK86: 63.2573 | CL86: 80 | CM86: 26.894963 | CN86: 92.727273 | CO86: 85.468245 | CP86: 65.688035 | CQ86: 77 | CR86: 78 | CS86: 26 | CT86: 104 | CU86: 79 | CV86: 61 | CW86: 63 | CX86: 67 | CY86: 83 | CZ86: 41 | DA86: 83 | DB86: 105 | DC86: 56 | DD86: 66 | DE86: 26 | DF86: 86 | DG86: 53 | DH86: 54 | DI86: n/a | DJ86: 24 | DK86: 85 | DL86: 36 | DM86: 43 | DN86: 40 | DO86: 58 | DP86: 96 | DQ86: 88 | DR86: 76 | DS86: 76 | DT86: 38 | DU86: 77 | DV86: 57 | DW86: 64 | DX86: 97 | DY86: 72 | DZ86: 80 | EA86: 42 | EB86: 109 | EC86: 77 | ED86: 60 | EE86: 69 | EF86: 46 | EG86: 61 | EH86: 118 | EI86: 63 | EJ86: 84 | EK86: 84 | EL86: 76 | EM86: 72 | EN86: 60 | EO86: 25 | EP86: 31 | EQ86: 57
A87: Mongolia | B87: MNG | C87: Asia & Pacific | D87: Upper middle-income | E87: 20378.301 | F87: 3432000 | G87: 45.052228 | H87: MN | I87: 81 | J87: 36.374473 | K87: 35.764936 | L87: 64.124719 | M87: 43.944782 | N87: 85 | O87: 85 | P87: 57 | Q87: 102 | R87: 67.261162 | S87: 16.127162 | T87: 25.735094 | U87: 52.733872 | V87: 18.911795 | W87: 35.649143 | X87: 63.943793 | Y87: 49.567872 | Z87: 78.862491 | AA87: 17.738737 | AB87: 58.888263 | AC87: 55.207347 | AD87: 68 | AE87: 95 | AF87: 96 | AG87: 59 | AH87: 110 | AI87: 77 | AJ87: 57 | AK87: 99 | AL87: 27 | AM87: 117 | AN87: 85 | AO87: 94 | AP87: 65.996132 | AQ87: 37.843664 | AR87: 32.874009 | AS87: 100 | AT87: 66.853169 | AU87: 100 | AV87: 6.5588104 | AW87: 2.0027166 | AX87: 55.323264 | AY87: 0.62385618 | AZ87: 37.259686 | BA87: 33 | BB87: n/a | BC87: 6.9455963 | BD87: 9.7045495 | BE87: 28.550529 | BF87: 74.766731 | BG87: 97.913678 | BH87: n/a | BI87: 30.919069 | BJ87: 11.331517 | BK87: 33.143268 | BL87: 0.25332614 | BM87: 78.608294 | BN87: 24.693168 | BO87: 38.062337 | BP87: 1.2327709 | BQ87: 63.193454 | BR87: 47.574756 | BS87: 83.40233 | BT87: 61.604631 | BU87: 37.835693 | BV87: 53.4375 | BW87: 29.990058 | BX87: 75 | BY87: 51.576109 | BZ87: 76.809141 | CA87: 94.012275 | CB87: 62.281375 | CC87: 82.347171 | CD87: 0 | CE87: 39.361315 | CF87: 28.599248 | CG87: 2.9943834 | CH87: 57.484361 | CI87: 50.130208 | CJ87: 80.612245 | CK87: 57.488195 | CL87: 66.666667 | CM87: 28.017316 | CN87: 86.363636 | CO87: 53.821313 | CP87: 38.58758 | CQ87: 65 | CR87: 101 | CS87: 59 | CT87: 1 | CU87: 91 | CV87: 1 | CW87: 65 | CX87: 81 | CY87: 91 | CZ87: 102 | DA87: 95 | DB87: 88 | DC87: n/a | DD87: 89 | DE87: 78 | DF87: 99 | DG87: 50 | DH87: 23 | DI87: n/a | DJ87: 96 | DK87: 44 | DL87: 102 | DM87: 115 | DN87: 41 | DO87: 67 | DP87: 61 | DQ87: 99 | DR87: 62 | DS87: 106 | DT87: 4 | DU87: 31 | DV87: 81 | DW87: 92 | DX87: 88 | DY87: 72 | DZ87: 85 | EA87: 37 | EB87: 22 | EC87: 70 | ED87: 8 | EE87: 81 | EF87: 103 | EG87: 80 | EH87: 107 | EI87: 75 | EJ87: 107 | EK87: 32 | EL87: 87 | EM87: 89 | EN87: 54 | EO87: 40 | EP87: 107 | EQ87: 99
A88: Bangladesh | B88: BGD | C88: Asia & Pacific | D88: Lower middle-income | E88: 10257.554 | F88: 171467000 | G88: 44.9036 | H88: BD | I88: 82 | J88: 48.595289 | K88: 33.551229 | L88: 49.648695 | M88: 47.819188 | N88: 43 | O88: 93 | P88: 94 | Q88: 88 | R88: 75.404812 | S88: 40.370484 | T88: 30.010572 | U88: 44.43992 | V88: 15.921841 | W88: 40.291926 | X88: 51.385871 | Y88: 41.002979 | Z88: 56.557234 | AA88: 32.218225 | AB88: 57.969285 | AC88: 53.270053 | AD88: 41 | AE88: 35 | AF88: 86 | AG88: 91 | AH88: 122 | AI88: 65 | AJ88: 69 | AK88: 112 | AL88: 82 | AM88: 63 | AN88: 86 | AO88: 97 | AP88: 82.685866 | AQ88: 39.375792 | AR88: 71.166301 | AS88: 98.526316 | AT88: 81.444902 | AU88: 79.229696 | AV88: 3.2373106 | AW88: 0.22840393 | AX88: 62.808544 | AY88: 95.207676 | AZ88: 48.874134 | BA88: 29 | BB88: n/a | BC88: 12.157582 | BD88: 46.832471 | BE88: 35.162445 | BF88: 28.072456 | BG88: 67.692308 | BH88: n/a | BI88: 17.619323 | BJ88: 0.88097643 | BK88: 39.638183 | BL88: 5.5488796 | BM88: 68.412315 | BN88: 24.004826 | BO88: 28.458637 | BP88: n/a | BQ88: 50.332731 | BR88: 96.351622 | BS88: n/a | BT88: 7.4732598 | BU88: 19.352052 | BV88: 35.3125 | BW88: 28.253701 | BX88: 75 | BY88: 47.09664 | BZ88: 59.415997 | CA88: 57.30332 | CB88: 15.967267 | CC88: 93.542352 | CD88: n/a | CE88: 70.636319 | CF88: 18.834606 | CG88: 7.1837511 | CH88: 13.203753 | CI88: 88.020833 | CJ88: 81.887755 | CK88: 63.478784 | CL88: 37.777778 | CM88: n/a | CN88: 26.363636 | CO88: 92.465016 | CP88: 44.185233 | CQ88: 32 | CR88: 99 | CS88: 5 | CT88: 47 | CU88: 20 | CV88: 51 | CW88: 91 | CX88: 114 | CY88: 69 | CZ88: 7 | DA88: 81 | DB88: 95 | DC88: n/a | DD88: 77 | DE88: 13 | DF88: 92 | DG88: 102 | DH88: 74 | DI88: n/a | DJ88: 104 | DK88: 87 | DL88: 68 | DM88: 60 | DN88: 67 | DO88: 69 | DP88: 80 | DQ88: n/a | DR88: 83 | DS88: 39 | DT88: n/a | DU88: 100 | DV88: 117 | DW88: 117 | DX88: 90 | DY88: 72 | DZ88: 93 | EA88: 69 | EB88: 83 | EC88: 100 | ED88: 2 | EE88: n/a | EF88: 23 | EG88: 96 | EH88: 83 | EI88: 117 | EJ88: 21 | EK88: 28 | EL88: 75 | EM88: 106 | EN88: n/a | EO88: 122 | EP88: 9 | EQ88: 87
A89: Panama | B89: PAN | C89: The Americas | D89: High-income | E89: 43651.385 | F89: 4459000 | G89: 43.818607 | H89: PA | I89: 83 | J89: 37.74367 | K89: 34.84135 | L89: 49.412566 | M89: 53.276842 | N89: 82 | O89: 86 | P89: 96 | Q89: 64 | R89: 56.048368 | S89: 22.309541 | T89: 34.873102 | U89: 58.995727 | V89: 16.093168 | W89: 29.435156 | X89: 45.635637 | Y89: 61.917584 | Z89: 40.684479 | AA89: 23.211407 | AB89: 69.217733 | AC89: 67.401384 | AD89: 96 | AE89: 74 | AF89: 61 | AG89: 30 | AH89: 121 | AI89: 93 | AJ89: 86 | AK89: 68 | AL89: 112 | AM89: 103 | AN89: 50 | AO89: 54 | AP89: 50.781942 | AQ89: 91.976997 | AR89: 15.651279 | AS89: 73.684211 | AT89: 63.335556 | AU89: 40.860222 | AV89: 3.6260784 | AW89: 16.944958 | AX89: 68.537799 | AY89: 0.12933005 | AZ89: 47.79848 | BA89: 40.25 | BB89: n/a | BC89: 16.570826 | BD89: n/a | BE89: 20.973475 | BF89: 61.773496 | BG89: 94.240208 | BH89: n/a | BI89: n/a | BJ89: 4.0716555 | BK89: 39.998288 | BL89: 4.2095605 | BM89: 57.951661 | BN89: 42.414676 | BO89: 14.970298 | BP89: 2.4039912 | BQ89: 62.080628 | BR89: 59.797704 | BS89: 41.218451 | BT89: 19.445765 | BU89: 45.200876 | BV89: 63.4375 | BW89: 43.660037 | BX89: 75 | BY89: 82.289506 | BZ89: 49.269996 | CA89: 26.393297 | CB89: 69.040726 | CC89: 18.033896 | CD89: 0.34130361 | CE89: 49.433575 | CF89: 32.358594 | CG89: 10.712157 | CH89: 70.308311 | CI89: 82.291667 | CJ89: 33.928571 | CK89: 76.177873 | CL89: 95.555556 | CM89: 17.102904 | CN89: 70 | CO89: 95.371367 | CP89: 78.706974 | CQ89: 95 | CR89: 26 | CS89: 102 | CT89: 100 | CU89: 106 | CV89: 68 | CW89: 88 | CX89: 37 | CY89: 50 | CZ89: 118 | DA89: 84 | DB89: 62 | DC89: n/a | DD89: 67 | DE89: n/a | DF89: 109 | DG89: 73 | DH89: 38 | DI89: n/a | DJ89: n/a | DK89: 69 | DL89: 66 | DM89: 66 | DN89: 83 | DO89: 42 | DP89: 102 | DQ89: 89 | DR89: 63 | DS89: 95 | DT89: 30 | DU89: 74 | DV89: 66 | DW89: 78 | DX89: 64 | DY89: 72 | DZ89: 24 | EA89: 81 | EB89: 117 | EC89: 22 | ED89: 73 | EE89: 63 | EF89: 76 | EG89: 73 | EH89: 72 | EI89: 38 | EJ89: 38 | EK89: 105 | EL89: 36 | EM89: 46 | EN89: 69 | EO89: 88 | EP89: 5 | EQ89: 33
A90: Iran (Islamic Republic of) | B90: IRN | C90: Asia & Pacific | D90: Upper middle-income | E90: 21473.13 | F90: 90609000 | G90: 43.253749 | H90: IR | I90: 84 | J90: 48.405071 | K90: 38.110558 | L90: 54.190897 | M90: 32.308472 | N90: 44 | O90: 76 | P90: 79 | Q90: 124 | R90: 57.211001 | S90: 40.649311 | T90: 47.3549 | U90: 55.722224 | V90: 37.725734 | W90: 20.883716 | X90: 56.429769 | Y90: 45.460388 | Z90: 60.682535 | AA90: 21.841218 | AB90: 45.48466 | AC90: 29.599536 | AD90: 92 | AE90: 34 | AF90: 30 | AG90: 43 | AH90: 42 | AI90: 112 | AJ90: 63 | AK90: 107 | AL90: 70 | AM90: 108 | AN90: 107 | AO90: 127 | AP90: 52.531589 | AQ90: 41.941695 | AR90: 28.133962 | AS90: 83.315789 | AT90: 80.131971 | AU90: n/a | AV90: 2.0994675 | AW90: 5.103545 | AX90: 55.39423 | AY90: 100 | AZ90: 62.599056 | BA90: 27.75 | BB90: n/a | BC90: 51.715645 | BD90: 51.103114 | BE90: 36.326518 | BF90: 52.500287 | BG90: 82.958975 | BH90: n/a | BI90: n/a | BJ90: n/a | BK90: 67.07941 | BL90: 8.3720585 | BM90: 25.083914 | BN90: n/a | BO90: 26.19314 | BP90: 11.374093 | BQ90: 71.557738 | BR90: 58.575541 | BS90: n/a | BT90: 39.156028 | BU90: 0 | BV90: 71.875 | BW90: 22.567132 | BX90: 75 | BY90: 57.859809 | BZ90: 13.044858 | CA90: 79.126006 | CB90: 63.64605 | CC90: 86.913227 | CD90: 0.63483512 | CE90: 70.668475 | CF90: 14.530184 | CG90: 1.5313783 | CH90: 40.951743 | CI90: 27.604167 | CJ90: 69.132653 | CK90: 66.663489 | CL90: 86.666667 | CM90: n/a | CN90: 0 | CO90: 13.455328 | CP90: 64.019896 | CQ90: 91 | CR90: 93 | CS90: 75 | CT90: 94 | CU90: 21 | CV90: n/a | CW90: 100 | CX90: 59 | CY90: 90 | CZ90: 1 | DA90: 59 | DB90: 100 | DC90: n/a | DD90: 5 | DE90: 9 | DF90: 89 | DG90: 88 | DH90: 61 | DI90: n/a | DJ90: n/a | DK90: n/a | DL90: 9 | DM90: 54 | DN90: 118 | DO90: n/a | DP90: 84 | DQ90: 50 | DR90: 48 | DS90: 102 | DT90: n/a | DU90: 54 | DV90: 127 | DW90: 70 | DX90: 99 | DY90: 72 | DZ90: 75 | EA90: 123 | EB90: 51 | EC90: 67 | ED90: 6 | EE90: 55 | EF90: 22 | EG90: 98 | EH90: 116 | EI90: 93 | EJ90: 118 | EK90: 63 | EL90: 61 | EM90: 63 | EN90: n/a | EO90: 127 | EP90: 123 | EQ90: 61
A91: Ghana | B91: GHA | C91: Africa | D91: Lower middle-income | E91: 8410.294 | F91: 33788000 | G91: 43.049241 | H91: GH | I91: 85 | J91: 35.5868 | K91: 36.632216 | L91: 55.990476 | M91: 43.987472 | N91: 87 | O91: 82 | P91: 74 | Q91: 101 | R91: 60.720063 | S91: 13.411643 | T91: 32.628694 | U91: 36.341146 | V91: 27.608529 | W91: 45.946974 | X91: 50.088273 | Y91: 58.299772 | Z91: 59.583383 | AA91: 25.647383 | AB91: 46.817564 | AC91: 59.497469 | AD91: 83 | AE91: 105 | AF91: 72 | AG91: 103 | AH91: 75 | AI91: 49 | AJ91: 71 | AK91: 75 | AL91: 72 | AM91: 96 | AN91: 104 | AO91: 84 | AP91: 64.604112 | AQ91: 33.952202 | AR91: 32.127854 | AS91: 97.368421 | AT91: 75.547726 | AU91: n/a | AV91: 2.7091745 | AW91: 0.28493459 | AX91: 39.200516 | AY91: 11.451945 | AZ91: 47.778119 | BA91: 49.25 | BB91: n/a | BC91: 0.85796363 | BD91: 21.439947 | BE91: 42.043936 | BF91: 18.056578 | BG91: 63.824123 | BH91: n/a | BI91: 61.042427 | BJ91: 8.409981 | BK91: 39.046965 | BL91: 1.934743 | BM91: 52.884349 | BN91: 38.309631 | BO91: 46.646941 | BP91: n/a | BQ91: 29.572074 | BR91: 99.125505 | BS91: 55.189261 | BT91: 16.46625 | BU91: 37.707629 | BV91: 64.375 | BW91: 32.168202 | BX91: 75 | BY91: 82.24803 | BZ91: 50.719424 | CA91: 68.908273 | CB91: n/a | CC91: 59.122451 | CD91: n/a | CE91: 53.011327 | CF91: 18.78821 | CG91: 5.1426137 | CH91: 24.128686 | CI91: 68.619792 | CJ91: 49.744898 | CK91: 45.663531 | CL91: 28.888889 | CM91: n/a | CN91: 63.636364 | CO91: 85.468245 | CP91: 29.886707 | CQ91: 69 | CR91: 107 | CS91: 61 | CT91: 57 | CU91: 40 | CV91: n/a | CW91: 95 | CX91: 113 | CY91: 114 | CZ91: 46 | DA91: 85 | DB91: 44 | DC91: n/a | DD91: 121 | DE91: 47 | DF91: 80 | DG91: 109 | DH91: 77 | DI91: n/a | DJ91: 53 | DK91: 52 | DL91: 70 | DM91: 82 | DN91: 86 | DO91: 47 | DP91: 40 | DQ91: n/a | DR91: 117 | DS91: 19 | DT91: 21 | DU91: 80 | DV91: 82 | DW91: 77 | DX91: 83 | DY91: 72 | DZ91: 25 | EA91: 80 | EB91: 70 | EC91: n/a | ED91: 48 | EE91: n/a | EF91: 66 | EG91: 97 | EH91: 93 | EI91: 111 | EJ91: 67 | EK91: 94 | EL91: 106 | EM91: 111 | EN91: n/a | EO91: 99 | EP91: 31 | EQ91: 111
A92: Paraguay | B92: PRY | C92: The Americas | D92: Upper middle-income | E92: 19717.194 | F92: 6844000 | G92: 42.945668 | H92: PY | I92: 86 | J92: 31.217934 | K92: 36.396852 | L92: 52.644784 | M92: 51.523103 | N92: 99 | O92: 83 | P92: 83 | Q92: 78 | R92: 59.974316 | S92: 15.478377 | T92: 18.20111 | U92: 42.300619 | V92: 43.141276 | W92: 23.748661 | X92: 39.905653 | Y92: 54.149983 | Z92: 63.878714 | AA92: 23.640582 | AB92: 68.394368 | AC92: 62.534361 | AD92: 85 | AE92: 99 | AF92: 113 | AG92: 96 | AH92: 35 | AI92: 106 | AJ92: 100 | AK92: 80 | AL92: 65 | AM92: 100 | AN92: 55 | AO92: 66 | AP92: 57.751192 | AQ92: 88.777769 | AR92: 33.074944 | AS92: 97.947368 | AT92: 58.08451 | AU92: 24.21011 | AV92: 3.0429959 | AW92: 1.8704656 | AX92: 56.782773 | AY92: 0.21727181 | AZ92: 32.234672 | BA92: 19 | BB92: n/a | BC92: 3.3686566 | BD92: 2.4416467 | BE92: 13.934843 | BF92: 60.730663 | BG92: 92.095325 | BH92: n/a | BI92: 91.847824 | BJ92: n/a | BK92: 35.284471 | BL92: 2.2915339 | BM92: 60.437194 | BN92: 21.735624 | BO92: 11.02458 | BP92: 1.7972467 | BQ92: 53.488736 | BR92: 69.884244 | BS92: 23.91161 | BT92: 12.338023 | BU92: 40.252955 | BV92: 33.4375 | BW92: 16.325325 | BX92: 100 | BY92: 80.734135 | BZ92: 57.966568 | CA92: 58.964513 | CB92: 70.520909 | CC92: 68.062869 | CD92: n/a | CE92: 45.709685 | CF92: 24.598768 | CG92: 0.61329138 | CH92: 65.058088 | CI92: 88.151042 | CJ92: 47.959184 | CK92: 55.988764 | CL92: 82.222222 | CM92: 9.2005811 | CN92: 91.818182 | CO92: 78.579117 | CP92: 58.856902 | CQ92: 83 | CR92: 34 | CS92: 58 | CT92: 53 | CU92: 118 | CV92: 78 | CW92: 92 | CX92: 83 | CY92: 87 | CZ92: 114 | DA92: 99 | DB92: 118 | DC92: n/a | DD92: 105 | DE92: 111 | DF92: 111 | DG92: 76 | DH92: 50 | DI92: n/a | DJ92: 12 | DK92: n/a | DL92: 91 | DM92: 78 | DN92: 79 | DO92: 72 | DP92: 106 | DQ92: 94 | DR92: 78 | DS92: 88 | DT92: 45 | DU92: 86 | DV92: 74 | DW92: 118 | DX92: 105 | DY92: 1 | DZ92: 27 | EA92: 71 | EB92: 82 | EC92: 14 | ED92: 33 | EE92: n/a | EF92: 85 | EG92: 84 | EH92: 126 | EI92: 52 | EJ92: 20 | EK92: 96 | EL92: 90 | EM92: 69 | EN92: 77 | EO92: 27 | EP92: 52 | EQ92: 71
A93: Rwanda | B93: RWA | C93: Africa | D93: Low-income | E93: 4100.683 | F93: 13954000 | G93: 42.815043 | H93: RW | I93: 87 | J93: 35.695752 | K93: 33.910215 | L93: 56.638144 | M93: 45.016059 | N93: 86 | O93: 92 | P93: 72 | Q93: 97 | R93: 56.635955 | S93: 12.53713 | T93: 37.91417 | U93: 33.12517 | V93: 21.208079 | W93: 47.397397 | X93: 69.059771 | Y93: 50.358362 | Z93: 50.496299 | AA93: 32.878478 | AB93: 34.543719 | AC93: 67.625981 | AD93: 93 | AE93: 107 | AF93: 51 | AG93: 107 | AH93: 104 | AI93: 43 | AJ93: 50 | AK93: 95 | AL93: 96 | AM93: 61 | AN93: 120 | AO93: 53 | AP93: 49.688229 | AQ93: 45.25076 | AR93: 27.536648 | AS93: 99.105263 | AT93: 61.698719 | AU93: 56.53611 | AV93: 4.1936097 | AW93: 0.18108059 | AX93: 41.974406 | AY93: 3.7994257 | AZ93: 59.734439 | BA93: 50 | BB93: n/a | BC93: 4.0080711 | BD93: 4.4670597 | BE93: 57.720966 | BF93: 2.6203464 | BG93: 67.692308 | BH93: n/a | BI93: 36.716395 | BJ93: 17.586791 | BK93: 30.199717 | BL93: 0.32941502 | BM93: 78.423022 | BN93: 33.037268 | BO93: 65.68587 | BP93: 12.443427 | BQ93: 40.432183 | BR93: 97.687358 | BS93: n/a | BT93: n/a | BU93: 45.349388 | BV93: 73.125 | BW93: 46.13368 | BX93: 50 | BY93: 37.183741 | BZ93: 73.910284 | CA93: 27.082314 | CB93: n/a | CC93: n/a | CD93: n/a | CE93: 36.615198 | CF93: 56.809969 | CG93: 5.2102683 | CH93: 0.17873101 | CI93: 49.088542 | CJ93: 60.204082 | CK93: 48.523686 | CL93: 31.111111 | CM93: n/a | CN93: 88.181818 | CO93: 77.933262 | CP93: 42.414615 | CQ93: 98 | CR93: 91 | CS93: 77 | CT93: 42 | CU93: 111 | CV93: 60 | CW93: 84 | CX93: 117 | CY93: 109 | CZ93: 72 | DA93: 66 | DB93: 42 | DC93: n/a | DD93: 102 | DE93: 99 | DF93: 48 | DG93: 123 | DH93: 74 | DI93: n/a | DJ93: 87 | DK93: 32 | DL93: 108 | DM93: 112 | DN93: 43 | DO93: 56 | DP93: 23 | DQ93: 47 | DR93: 100 | DS93: 30 | DT93: n/a | DU93: n/a | DV93: 65 | DW93: 67 | DX93: 57 | DY93: 107 | DZ93: 104 | EA93: 42 | EB93: 116 | EC93: n/a | ED93: n/a | EE93: n/a | EF93: 113 | EG93: 38 | EH93: 92 | EI93: 125 | EJ93: 108 | EK93: 79 | EL93: 102 | EM93: 109 | EN93: n/a | EO93: 34 | EP93: 57 | EQ93: 93
A94: Egypt | B94: EGY | C94: Arab States | D94: Lower middle-income | E94: 21758.838 | F94: 114536000 | G94: 42.695313 | H94: EG | I94: 88 | J94: 39.806509 | K94: 34.84106 | L94: 48.70974 | M94: 47.423943 | N94: 79 | O94: 87 | P94: 98 | Q94: 89 | R94: 61.722641 | S94: 25.896404 | T94: 31.800483 | U94: 46.666362 | V94: 20.368531 | W94: 37.488289 | X94: 46.671996 | Y94: 49.541397 | Z94: 49.915827 | AA94: 37.935831 | AB94: 42.999618 | AC94: 61.33638 | AD94: 80 | AE94: 62 | AF94: 74 | AG94: 81 | AH94: 106 | AI94: 72 | AJ94: 83 | AK94: 100 | AL94: 99 | AM94: 44 | AN94: 112 | AO94: 74 | AP94: 76.996329 | AQ94: 35.937537 | AR94: 45.182821 | AS94: 98.947368 | AT94: 82.861199 | AU94: 30.410589 | AV94: 3.7228381 | AW94: 0.48826347 | AX94: 59.535676 | AY94: 39.838838 | AZ94: 62.305727 | BA94: 37 | BB94: 0.083243654 | BC94: 27.812963 | BD94: 30.346041 | BE94: 48.560718 | BF94: 39.363951 | BG94: 68.394737 | BH94: n/a | BI94: n/a | BJ94: 3.7712837 | BK94: 49.100553 | BL94: 8.233755 | BM94: 63.927287 | BN94: 27.378107 | BO94: 42.433118 | BP94: 16.214643 | BQ94: 34.513677 | BR94: 100 | BS94: n/a | BT94: 5.5023103 | BU94: 25.575592 | BV94: 75.625 | BW94: 31.927379 | BX94: 100 | BY94: 14.579013 | BZ94: 56.517139 | CA94: 41.417973 | CB94: 34.704094 | CC94: 67.024102 | CD94: 0.12575089 | CE94: 73.270754 | CF94: 63.938555 | CG94: 14.408264 | CH94: 12.444147 | CI94: 45.442708 | CJ94: 88.010204 | CK94: 54.213796 | CL94: 77.777778 | CM94: n/a | CN94: 28.181818 | CO94: 84.714747 | CP94: 64.447373 | CQ94: 44 | CR94: 104 | CS94: 31 | CT94: 43 | CU94: 16 | CV94: 73 | CW94: 86 | CX94: 105 | CY94: 80 | CZ94: 19 | DA94: 61 | DB94: 72 | DC94: 54 | DD94: 31 | DE94: 36 | DF94: 67 | DG94: 99 | DH94: 72 | DI94: n/a | DJ94: n/a | DK94: 71 | DL94: 33 | DM94: 55 | DN94: 77 | DO94: 63 | DP94: 48 | DQ94: 41 | DR94: 110 | DS94: 1 | DT94: n/a | DU94: 109 | DV94: 106 | DW94: 59 | DX94: 84 | DY94: 1 | DZ94: 123 | EA94: 73 | EB94: 105 | EC94: 97 | ED94: 34 | EE94: 72 | EF94: 17 | EG94: 30 | EH94: 61 | EI94: 118 | EJ94: 112 | EK94: 15 | EL94: 95 | EM94: 76 | EN94: n/a | EO94: 121 | EP94: 34 | EQ94: 59
A95: North Macedonia | B95: MKD | C95: Europe | D95: Upper middle-income | E95: 29509.916 | F95: 1832000 | G95: 42.575324 | H95: MK | I95: 89 | J95: 34.763837 | K95: 27.15235 | L95: 60.96526 | M95: 47.419848 | N95: 89 | O95: 110 | P95: 64 | Q95: 90 | R95: 64.366236 | S95: 21.261804 | T95: 18.66347 | U95: 29.778083 | V95: 16.279728 | W95: 35.399239 | X95: 51.5933 | Y95: 67.104661 | Z95: 64.197818 | AA95: 24.320175 | AB95: 57.263319 | AC95: 60.676051 | AD95: 76 | AE95: 75 | AF95: 111 | AG95: 114 | AH95: 119 | AI95: 79 | AJ95: 68 | AK95: 49 | AL95: 63 | AM95: 98 | AN95: 88 | AO95: 76 | AP95: 52.069593 | AQ95: 96.210355 | AR95: 19.717288 | AS95: 99.315789 | AT95: 54.518155 | AU95: n/a | AV95: 12.173781 | AW95: 8.6359095 | AX95: 62.578421 | AY95: 1.6591022 | AZ95: 28.948927 | BA95: 17.5 | BB95: n/a | BC95: 9.5414832 | BD95: 3.8656113 | BE95: 26.482335 | BF95: 58.986302 | BG95: n/a | BH95: n/a | BI95: n/a | BJ95: 17.419501 | BK95: 28.859242 | BL95: 2.5604413 | BM95: 59.595048 | BN95: n/a | BO95: 40.459007 | BP95: 6.143663 | BQ95: 61.598653 | BR95: 59.012884 | BS95: 53.958659 | BT95: 31.803005 | BU95: 52.922383 | BV95: 74.6875 | BW95: 29.833787 | BX95: 100 | BY95: 78.079635 | BZ95: 55.067711 | CA95: 74.491213 | CB95: 58.308829 | CC95: 68.923519 | CD95: 0 | CE95: 36.070402 | CF95: 23.77721 | CG95: 37.433087 | CH95: 50.111707 | CI95: 51.171875 | CJ95: 75.255102 | CK95: 65.757649 | CL95: 86.666667 | CM95: 15.816683 | CN95: 78.181818 | CO95: 80.409042 | CP95: 49.926654 | CQ95: 92 | CR95: 14 | CS95: 93 | CT95: 39 | CU95: 122 | CV95: n/a | CW95: 54 | CX95: 49 | CY95: 70 | CZ95: 88 | DA95: 101 | DB95: 120 | DC95: n/a | DD95: 82 | DE95: 102 | DF95: 103 | DG95: 78 | DH95: n/a | DI95: n/a | DJ95: n/a | DK95: 33 | DL95: 111 | DM95: 76 | DN95: 80 | DO95: n/a | DP95: 52 | DQ95: 65 | DR95: 65 | DS95: 98 | DT95: 23 | DU95: 57 | DV95: 50 | DW95: 61 | DX95: 89 | DY95: 1 | DZ95: 32 | EA95: 75 | EB95: 60 | EC95: 80 | ED95: 32 | EE95: 81 | EF95: 115 | EG95: 88 | EH95: 22 | EI95: 82 | EJ95: 106 | EK95: 44 | EL95: 68 | EM95: 63 | EN95: 70 | EO95: 62 | EP95: 45 | EQ95: 80
A96: Kyrgyzstan | B96: KGZ | C96: CIS | D96: Lower middle-income | E96: 8870.37 | F96: 7074000 | G96: 42.438895 | H96: KG | I96: 90 | J96: 31.366456 | K96: 32.217895 | L96: 50.981621 | M96: 55.18961 | N96: 98 | O96: 94 | P96: 90 | Q96: 54 | R96: 56.175172 | S96: 18.081601 | T96: 19.842596 | U96: 49.812292 | V96: 18.466076 | W96: 28.375317 | X96: 44.438811 | Y96: 43.651449 | Z96: 64.854602 | AA96: 22.741726 | AB96: 77.350688 | AC96: 65.476415 | AD96: 94 | AE96: 89 | AF96: 109 | AG96: 71 | AH96: 114 | AI96: 97 | AJ96: 88 | AK96: 108 | AL96: 62 | AM96: 106 | AN96: 26 | AO96: 60 | AP96: 54.708087 | AQ96: 31.692109 | AR96: 40.072953 | AS96: 97.894737 | AT96: 71.31463 | AU96: 41.368515 | AV96: 5.7565188 | AW96: 0.64946901 | AX96: 63.176124 | AY96: 2.7442927 | AZ96: 36.256271 | BA96: 19.25 | BB96: n/a | BC96: 4.021516 | BD96: 19.112023 | BE96: 40.211341 | BF96: 40.514112 | BG96: 99.411692 | BH96: n/a | BI96: n/a | BJ96: n/a | BK96: 36.775517 | BL96: 0.15663437 | BM96: 52.7472 | BN96: 19.112649 | BO96: 40.80121 | BP96: 0.84020869 | BQ96: 57.700621 | BR96: 58.673146 | BS96: 40.249184 | BT96: 21.132293 | BU96: 26.795189 | BV96: 40 | BW96: 26.814607 | BX96: 75 | BY96: 49.647449 | BZ96: 43.482861 | CA96: 75.236088 | CB96: n/a | CC96: 75.844857 | CD96: n/a | CE96: 37.219711 | CF96: 27.114257 | CG96: 3.8912079 | CH96: 58.042895 | CI96: 95.963542 | CJ96: 91.326531 | CK96: 64.764722 | CL96: 75.555556 | CM96: n/a | CN96: 66.363636 | CO96: 62.109795 | CP96: 60.356072 | CQ96: 88 | CR96: 114 | CS96: 42 | CT96: 54 | CU96: 65 | CV96: 67 | CW96: 69 | CX96: 102 | CY96: 68 | CZ96: 79 | DA96: 96 | DB96: 117 | DC96: n/a | DD96: 101 | DE96: 53 | DF96: 83 | DG96: 96 | DH96: 12 | DI96: n/a | DJ96: n/a | DK96: n/a | DL96: 83 | DM96: 118 | DN96: 87 | DO96: 75 | DP96: 51 | DQ96: 102 | DR96: 70 | DS96: 100 | DT96: 31 | DU96: 70 | DV96: 103 | DW96: 112 | DX96: 91 | DY96: 72 | DZ96: 88 | EA96: 88 | EB96: 59 | EC96: n/a | ED96: 20 | EE96: n/a | EF96: 111 | EG96: 82 | EH96: 100 | EI96: 73 | EJ96: 5 | EK96: 12 | EL96: 72 | EM96: 79 | EN96: n/a | EO96: 95 | EP96: 98 | EQ96: 69
